Workbook
Name d.conn: Database!$S1
Name d.id: Database!#REF!
Name ff_calculation: WORKDAY(INDEX(Database!$AI:$AI,#REF!),(#REF!+#REF!))
Name fs_calculation: WORKDAY(INDEX(Database!$AI:$AI,#REF!),1+#REF!+IF(#REF! = "M",#REF!, 0))
Name ind.end: Database!#REF!
Name ind.start: Database!$R1
Name MDDataBase: BaseDeDatos[]
Name MDDataBase: BaseDeDatos[]
Name plan_end_calculation: IF(#REF!="M", WORKDAY(#REF!,(#REF!)-1), IF(#REF!="SS", IF(#REF!="SS", WORKDAY(#REF!,(#REF!+#REF!)-1), WORKDAY(INDEX(Database!$AH:$AH,#REF!),(#REF!+#REF!))), WORKDAY(#REF!,(#REF!+#REF!)-1)))
Name plan_start_calculation: IF(#REF!="M", WORKDAY(#REF!,(-1)*#REF!+1), IF(#REF!="SF", WORKDAY(#REF!,(-1)*(#REF!+#REF!)+1), IF(#REF!="FF",WORKDAY(#REF!,(-1)*(#REF!+#REF!)+1), WORKDAY(#REF!,(-1)*#REF!+1))))
Name SegmentaciónDeDatos_Project_No: #N/A
Name SegmentaciónDeDatos_Project_No1: #N/A
Name SegmentaciónDeDatos_Responsible: #N/A
Name SegmentaciónDeDatos_Responsible1: #N/A
Name SegmentaciónDeDatos_STATUS: #N/A
Name sf_calculation: WORKDAY(INDEX(Database!$AH:$AH,#REF!),(-1)+(#REF!+#REF!))
Name ss_calculation: IF(#REF!="M", WORKDAY(INDEX(Database!$AH:$AH,#REF!),(#REF!+#REF!)), WORKDAY(INDEX(Database!$AH:$AH,#REF!),#REF!))
Name type: #REF!

Sheet HD Forecast 2025
A1: #VALUE! | B1: Month | C1: September | Z1: October | BE1: November | CI1: December
B2: Week | C2: 37 | J2: 38 | Q2: 39 | X2: 40 | AE2: 41 | AL2: 42 | AS2: 43 | AZ2: 44 | BG2: 45 | BN2: 46 | BU2: 47 | CB2: 48 | CI2: 49 | CP2: 50 | CW2: 51 | DD2: 52
B3: Day | C3: 8 | D3: 9 | E3: 10 | F3: 11 | G3: 12 | H3: 13 | I3: 14 | J3: 15 | K3: 16 | L3: 17 | M3: 18 | N3: 19 | O3: 20 | P3: 21 | Q3: 22 | R3: 23 | S3: 24 | T3: 25 | U3: 26 | V3: 27 | W3: 28 | X3: 29 | Y3: 30 | Z3: 1 | AA3: 2 | AB3: 3 | AC3: 4 | AD3: 5 | AE3: 6 | AF3: 7 | AG3: 8 | AH3: 9 | AI3: 10 | AJ3: 11 | AK3: 12 | AL3: 13 | AM3: 14 | AN3: 15 | AO3: 16 | AP3: 17 | AQ3: 18 | AR3: 19 | AS3: 20 | AT3: 21 | AU3: 22 | AV3: 23 | AW3: 24 | AX3: 25 | AY3: 26 | AZ3: 27 | BA3: 28 | BB3: 29 | BC3: 30 | BD3: 31 | BE3: 1 | BF3: 2 | BG3: 3 | BH3: 4 | BI3: 5 | BJ3: 6 | BK3: 7 | BL3: 8 | BM3: 9 | BN3: 10 | BO3: 11 | BP3: 12 | BQ3: 13 | BR3: 14 | BS3: 15 | BT3: 16 | BU3: 17 | BV3: 18 | BW3: 19 | BX3: 20 | BY3: 21 | BZ3: 22 | CA3: 23 | CB3: 24 | CC3: 25 | CD3: 26 | CE3: 27 | CF3: 28 | CG3: 29 | CH3: 30 | CI3: 1 | CJ3: 2 | CK3: 3 | CL3: 4 | CM3: 5 | CN3: 6 | CO3: 7 | CP3: 8 | CQ3: 9 | CR3: 10 | CS3: 11 | CT3: 12 | CU3: 13 | CV3: 14 | CW3: 15 | CX3: 16 | CY3: 17 | CZ3: 18 | DA3: 19 | DB3: 20 | DC3: 21 | DD3: 22 | DE3: 23 | DF3: 24 | DG3: 25 | DH3: 26 | DI3: 27 | DJ3: 28 | DK3: 29 | DL3: 30 | DM3: 31
A4: IND | B4: Juan Adame | C4: 3336 | D4: 3336 | E4: 3336 | F4: 3328 | G4: 3328 | J4: 3336 | K4: PTO | L4: 3336 | M4: 3328 | N4: 3336 | Q4: 3336 | R4: 3328 | S4: 3328 | T4: PTO | U4: PTO | X4: 3328 | Y4: 3336 | Z4: 3328 | AA4: PTO | AB4: PTO | AE4: 3336 | AF4: 3328 | AG4: 3268 | AH4: ASSY | AI4: ASSY | AL4: 3300 | AM4: 3328 | AN4: 3336 | AO4: IND | AP4: IND | AS4: 3264 | AT4: IND | AU4: IND | AV4: IND | AW4: PTO | AZ4: PTO | BA4: PTO | BB4: PTO | BC4: PTO | BD4: PTO | BG4: 3336 | BH4: 3351 | BI4: 3351 | BJ4: IND | BK4: IND | BN4: 3351 | BO4: 3351 | BP4: IND | BQ4: IND | BR4: IND | BU4: PTO | BV4: 3351 | BW4: 3351 | BX4: 3351 | BY4: 3300 | CB4: 3272 | CC4: IND | CD4: IND | CE4: IND | CF4: IND | CI4: 3328 | CJ4: IND | CK4: IND | CL4: IND | CM4: IND | CP4: IND | CQ4: IND | CR4: IND | CS4: IND | CT4: IND | CW4: 3328 | CX4: IND | CY4: IND | CZ4: IND | DA4: IND | DD4: 3272 | DE4: IND | DF4: IND | DG4: PTO | DH4: PTO | DK4: PTO | DL4: PTO | DM4: PTO
A5: MNG | C5: 3336 | D5: 3336 | E5: 3336 | F5: 3328 | G5: 3328 | J5: 3336 | K5: PTO | L5: 3336 | M5: 3328 | N5: 3336 | Q5: 3336 | R5: 3328 | S5: 3328 | T5: PTO | U5: PTO | X5: 3328 | Y5: 3336 | Z5: 3328 | AA5: PTO | AB5: PTO | AE5: 3336 | AF5: 3328 | AG5: 3268 | AH5: ASSY | AI5: ASSY | AL5: 3300 | AM5: 3328 | AN5: 3336 | AO5: IND | AP5: IND | AS5: 3264 | AT5: IND | AU5: IND | AV5: IND | AW5: PTO | AZ5: PTO | BA5: PTO | BB5: PTO | BC5: PTO | BD5: PTO | BG5: 3336 | BH5: 3351 | BI5: 3351 | BJ5: IND | BK5: IND | BN5: 3351 | BO5: 3351 | BP5: IND | BQ5: IND | BR5: IND | BU5: PTO | BV5: 3351 | BW5: 3351 | BX5: 3351 | BY5: 3300 | CB5: 3300 | CC5: IND | CD5: IND | CE5: IND | CF5: IND | CI5: 3272 | CJ5: IND | CK5: IND | CL5: IND | CM5: IND | CP5: IND | CQ5: IND | CR5: IND | CS5: IND | CT5: IND | CW5: 3328 | CX5: IND | CY5: IND | CZ5: IND | DA5: IND | DD5: IND | DE5: IND | DF5: IND | DG5: PTO | DH5: PTO | DK5: PTO | DL5: PTO | DM5: PTO
A6: ASSY | C6: 3336 | D6: 3336 | E6: 3336 | F6: 3328 | G6: 3328 | J6: 3336 | K6: PTO | L6: 3336 | M6: 3328 | N6: 3300 | Q6: 3336 | R6: 3328 | S6: 3328 | T6: PTO | U6: PTO | X6: 3328 | Y6: 3336 | Z6: 3328 | AA6: PTO | AB6: PTO | AE6: 3336 | AF6: 3328 | AG6: 3264 | AH6: ASSY | AI6: ASSY | AL6: 3328 | AM6: 3328 | AN6: 3336 | AO6: IND | AP6: IND | AS6: 3268 | AT6: IND | AU6: IND | AV6: IND | AW6: PTO | AZ6: PTO | BA6: PTO | BB6: PTO | BC6: PTO | BD6: PTO | BG6: 3351 | BH6: 3351 | BI6: IND | BJ6: IND | BK6: IND | BN6: 3351 | BO6: 3351 | BP6: IND | BQ6: IND | BR6: IND | BU6: PTO | BV6: 3351 | BW6: 3351 | BX6: 3351 | BY6: 3272 | CB6: 3300 | CC6: IND | CD6: IND | CE6: IND | CF6: IND | CI6: 3336 | CJ6: IND | CK6: IND | CL6: IND | CM6: IND | CP6: IND | CQ6: IND | CR6: IND | CS6: IND | CT6: IND | CW6: 3336 | CX6: IND | CY6: IND | CZ6: IND | DA6: IND | DD6: IND | DE6: IND | DF6: IND | DG6: PTO | DH6: PTO | DK6: PTO | DL6: PTO | DM6: PTO
A7: PTO | C7: 3336 | D7: 3336 | E7: 3336 | F7: 3328 | G7: 3328 | J7: 3336 | K7: PTO | L7: 3336 | M7: 3328 | N7: 3300 | Q7: 3336 | R7: 3328 | S7: 3328 | T7: PTO | U7: PTO | X7: 3328 | Y7: 3268 | Z7: 3328 | AA7: PTO | AB7: PTO | AE7: 3336 | AF7: 3328 | AG7: 3264 | AH7: ASSY | AI7: ASSY | AL7: 3328 | AM7: 3336 | AN7: IND | AO7: IND | AP7: IND | AS7: 3328 | AT7: IND | AU7: IND | AV7: IND | AW7: PTO | AZ7: PTO | BA7: PTO | BB7: PTO | BC7: PTO | BD7: PTO | BG7: 3351 | BH7: 3351 | BI7: IND | BJ7: IND | BK7: IND | BN7: 3351 | BO7: 3351 | BP7: IND | BQ7: IND | BR7: IND | BU7: PTO | BV7: 3351 | BW7: 3351 | BX7: 3351 | BY7: IND | CB7: 3328 | CC7: IND | CD7: IND | CE7: IND | CF7: IND | CI7: 3336 | CJ7: IND | CK7: IND | CL7: IND | CM7: IND | CP7: IND | CQ7: IND | CR7: IND | CS7: IND | CT7: IND | CW7: IND | CX7: IND | CY7: IND | CZ7: IND | DA7: IND | DD7: IND | DE7: IND | DF7: IND | DG7: PTO | DH7: PTO | DK7: PTO | DL7: PTO | DM7: PTO
A8: 3268 | C8: 3336 | D8: 3336 | E8: 3336 | F8: 3328 | G8: 3328 | J8: 3336 | K8: PTO | L8: 3336 | M8: 3328 | N8: 3300 | Q8: 3336 | R8: 3328 | S8: 3328 | T8: PTO | U8: PTO | X8: 3328 | Y8: 3268 | Z8: 3328 | AA8: PTO | AB8: PTO | AE8: 3336 | AF8: IND | AG8: 3272 | AH8: ASSY | AI8: ASSY | AL8: 3328 | AM8: 3336 | AN8: IND | AO8: IND | AP8: IND | AS8: 3351 | AT8: IND | AU8: IND | AV8: IND | AW8: PTO | AZ8: PTO | BA8: PTO | BB8: PTO | BC8: PTO | BD8: PTO | BG8: 3351 | BH8: 3351 | BI8: IND | BJ8: IND | BK8: IND | BN8: 3351 | BO8: 3351 | BP8: IND | BQ8: IND | BR8: IND | BU8: PTO | BV8: 3351 | BW8: 3351 | BX8: 3351 | BY8: IND | CB8: 3328 | CC8: IND | CD8: IND | CE8: IND | CF8: IND | CI8: 3336 | CJ8: IND | CK8: IND | CL8: PTO | CM8: IND | CP8: IND | CQ8: IND | CR8: IND | CS8: IND | CT8: IND | CW8: IND | CX8: IND | CY8: IND | CZ8: IND | DA8: IND | DD8: IND | DE8: IND | DF8: IND | DG8: PTO | DH8: PTO | DK8: PTO | DL8: PTO | DM8: PTO
A9: 3335 | C9: 3336 | D9: 3336 | E9: 3336 | F9: 3328 | G9: 3328 | J9: 3336 | K9: PTO | L9: 3336 | M9: 3328 | N9: IND | Q9: 3336 | R9: 3328 | S9: 3328 | T9: PTO | U9: PTO | X9: 3328 | Y9: 3328 | Z9: IND | AA9: PTO | AB9: PTO | AE9: IND | AF9: IND | AG9: ASSY | AH9: ASSY | AI9: ASSY | AL9: 3328 | AM9: 3336 | AN9: IND | AO9: IND | AP9: IND | AS9: 3351 | AT9: IND | AU9: IND | AV9: IND | AW9: PTO | AZ9: PTO | BA9: PTO | BB9: PTO | BC9: PTO | BD9: PTO | BG9: 3351 | BH9: 3351 | BI9: IND | BJ9: IND | BK9: IND | BN9: 3351 | BO9: 3351 | BP9: IND | BQ9: IND | BR9: IND | BU9: PTO | BV9: 3351 | BW9: 3351 | BX9: 3351 | BY9: IND | CB9: 3336 | CC9: IND | CD9: IND | CE9: IND | CF9: IND | CI9: 3336 | CJ9: IND | CK9: IND | CL9: PTO | CM9: IND | CP9: IND | CQ9: IND | CR9: IND | CS9: IND | CT9: IND | CW9: IND | CX9: IND | CY9: IND | CZ9: IND | DA9: IND | DD9: IND | DE9: IND | DF9: IND | DG9: PTO | DH9: PTO | DK9: PTO | DL9: PTO | DM9: PTO
A10: 3332 | C10: 3336 | D10: 3336 | E10: 3336 | F10: 3328 | G10: 3264 | J10: 3336 | K10: PTO | L10: 3336 | M10: 3328 | N10: 3272 | Q10: 3336 | R10: 3328 | S10: 3328 | T10: PTO | U10: PTO | X10: 3328 | Y10: 3328 | Z10: IND | AA10: PTO | AB10: PTO | AE10: IND | AF10: IND | AG10: ASSY | AH10: ASSY | AI10: ASSY | AL10: 3328 | AM10: 3336 | AN10: IND | AO10: IND | AP10: IND | AS10: 3351 | AT10: IND | AU10: IND | AV10: IND | AW10: PTO | AZ10: PTO | BA10: PTO | BB10: PTO | BC10: PTO | BD10: PTO | BG10: 3351 | BH10: 3351 | BI10: IND | BJ10: IND | BK10: IND | BN10: 3351 | BO10: 3351 | BP10: IND | BQ10: IND | BR10: IND | BU10: PTO | BV10: 3351 | BW10: 3351 | BX10: 3351 | BY10: IND | CB10: IND | CC10: IND | CD10: IND | CE10: IND | CF10: IND | CI10: 3336 | CJ10: IND | CK10: IND | CL10: PTO | CM10: IND | CP10: IND | CQ10: IND | CR10: IND | CS10: IND | CT10: IND | CW10: IND | CX10: IND | CY10: IND | CZ10: IND | DA10: IND | DD10: IND | DE10: IND | DF10: IND | DG10: PTO | DH10: PTO | DK10: PTO | DL10: PTO | DM10: PTO
A11: 3328 | C11: 3336 | D11: 3336 | E11: 3268 | F11: 3328 | G11: 3264 | J11: 3336 | K11: PTO | L11: 3300 | M11: 3328 | N11: 3264 | Q11: 3336 | R11: 3328 | S11: 3328 | T11: PTO | U11: PTO | X11: 3328 | Y11: 3328 | Z11: 3264 | AA11: PTO | AB11: PTO | AE11: IND | AF11: IND | AG11: ASSY | AH11: ASSY | AI11: ASSY | AL11: 3328 | AM11: 3336 | AN11: IND | AO11: IND | AP11: IND | AS11: 3351 | AT11: IND | AU11: IND | AV11: IND | AW11: PTO | AZ11: PTO | BA11: PTO | BB11: PTO | BC11: PTO | BD11: PTO | BG11: 3351 | BH11: 3351 | BI11: IND | BJ11: IND | BK11: IND | BN11: 3351 | BO11: 3351 | BP11: IND | BQ11: IND | BR11: IND | BU11: PTO | BV11: 3351 | BW11: 3351 | BX11: 3351 | BY11: IND | CB11: IND | CC11: IND | CD11: IND | CE11: IND | CF11: IND | CI11: 3336 | CJ11: IND | CK11: IND | CL11: PTO | CM11: IND | CP11: IND | CQ11: IND | CR11: IND | CS11: IND | CT11: IND | CW11: IND | CX11: IND | CY11: IND | CZ11: IND | DA11: IND | DD11: IND | DE11: IND | DF11: IND | DG11: PTO | DH11: PTO | DK11: PTO | DL11: PTO | DM11: PTO
A12: 3346 | C12: 3336 | D12: 3336 | E12: 3268 | F12: 3328 | G12: 3272 | J12: 3336 | K12: PTO | L12: 3300 | M12: 3328 | N12: 3264 | Q12: 3328 | R12: 3272 | S12: 3328 | T12: PTO | U12: PTO | X12: 3328 | Y12: 3328 | Z12: 3264 | AA12: PTO | AB12: PTO | AE12: IND | AF12: IND | AG12: ASSY | AH12: ASSY | AI12: ASSY | AL12: 3328 | AM12: 3336 | AN12: IND | AO12: IND | AP12: IND | AS12: 3351 | AT12: IND | AU12: IND | AV12: IND | AW12: PTO | AZ12: PTO | BA12: PTO | BB12: PTO | BC12: PTO | BD12: PTO | BG12: 3351 | BH12: 3351 | BI12: IND | BJ12: IND | BK12: IND | BN12: 3351 | BO12: 3351 | BP12: IND | BQ12: IND | BR12: IND | BU12: PTO | BV12: 3351 | BW12: 3351 | BX12: 3351 | BY12: IND | CB12: IND | CC12: IND | CD12: IND | CE12: IND | CF12: IND | CI12: IND | CJ12: IND | CK12: IND | CL12: PTO | CM12: IND | CP12: IND | CQ12: IND | CR12: IND | CS12: IND | CT12: IND | CW12: IND | CX12: IND | CY12: IND | CZ12: IND | DA12: IND | DD12: IND | DE12: IND | DF12: IND | DG12: PTO | DH12: PTO | DK12: PTO | DL12: PTO | DM12: PTO
A13: 3334
A14: 3336
A15: 3272
A16: 3340 | B16: Fidel Maldonado | C16: 3332 | D16: 3332 | E16: IND | F16: 3328 | G16: 3328 | J16: PTO | K16: PTO | L16: 3328 | M16: 3332 | N16: 3335 | Q16: 3328 | R16: 3332 | S16: 3335 | T16: IND | U16: IND | X16: 3328 | Y16: ASSY | Z16: ASSY | AA16: ASSY | AB16: ASSY | AE16: ASSY | AF16: ASSY | AG16: ASSY | AH16: ASSY | AI16: ASSY | AL16: ASSY | AM16: ASSY | AN16: IND | AO16: IND | AP16: IND | AS16: 3328 | AT16: IND | AU16: IND | AV16: IND | AW16: IND | AZ16: IND | BA16: IND | BB16: IND | BC16: IND | BD16: PTO | BG16: PTO | BH16: IND | BI16: IND | BJ16: IND | BK16: IND | BN16: IND | BO16: IND | BP16: IND | BQ16: IND | BR16: IND | BU16: PTO | BV16: IND | BW16: IND | BX16: IND | BY16: IND | CB16: 3321 | CC16: 3321 | CD16: IND | CE16: IND | CF16: 3335 | CI16: 3321 | CJ16: 3328 | CK16: IND | CL16: IND | CM16: IND | CP16: IND | CQ16: IND | CR16: IND | CS16: IND | CT16: IND | CW16: 3335 | CX16: IND | CY16: IND | CZ16: IND | DA16: IND | DD16: 3332 | DE16: 3332 | DF16: 3335 | DG16: PTO | DH16: PTO | DK16: PTO | DL16: PTO | DM16: PTO
A17: 3300 | C17: 3332 | D17: 3332 | E17: IND | F17: 3328 | G17: 3328 | J17: PTO | K17: PTO | L17: 3328 | M17: 3332 | N17: IND | Q17: 3328 | R17: 3332 | S17: 3335 | T17: IND | U17: IND | X17: 3328 | Y17: ASSY | Z17: ASSY | AA17: ASSY | AB17: ASSY | AE17: ASSY | AF17: ASSY | AG17: ASSY | AH17: ASSY | AI17: ASSY | AL17: ASSY | AM17: ASSY | AN17: IND | AO17: IND | AP17: IND | AS17: IND | AT17: IND | AU17: IND | AV17: IND | AW17: IND | AZ17: IND | BA17: IND | BB17: IND | BC17: IND | BD17: PTO | BG17: PTO | BH17: IND | BI17: IND | BJ17: IND | BK17: IND | BN17: IND | BO17: IND | BP17: IND | BQ17: IND | BR17: IND | BU17: PTO | BV17: IND | BW17: IND | BX17: IND | BY17: IND | CB17: 3321 | CC17: 3321 | CD17: IND | CE17: IND | CF17: 3335 | CI17: 3321 | CJ17: 3334 | CK17: IND | CL17: IND | CM17: IND | CP17: IND | CQ17: IND | CR17: IND | CS17: IND | CT17: IND | CW17: IND | CX17: IND | CY17: IND | CZ17: IND | DA17: IND | DD17: 3332 | DE17: 3332 | DF17: 3335 | DG17: PTO | DH17: PTO | DK17: PTO | DL17: PTO | DM17: PTO
A18: 3331 | C18: 3332 | D18: 3332 | E18: IND | F18: 3328 | G18: 3328 | J18: PTO | K18: PTO | L18: 3328 | M18: 3332 | N18: IND | Q18: 3328 | R18: 3332 | S18: 3335 | T18: IND | U18: IND | X18: 3336 | Y18: ASSY | Z18: ASSY | AA18: ASSY | AB18: ASSY | AE18: ASSY | AF18: ASSY | AG18: ASSY | AH18: ASSY | AI18: ASSY | AL18: ASSY | AM18: ASSY | AN18: IND | AO18: IND | AP18: IND | AS18: IND | AT18: IND | AU18: IND | AV18: IND | AW18: IND | AZ18: IND | BA18: IND | BB18: IND | BC18: IND | BD18: PTO | BG18: PTO | BH18: IND | BI18: IND | BJ18: IND | BK18: IND | BN18: IND | BO18: IND | BP18: IND | BQ18: IND | BR18: IND | BU18: PTO | BV18: IND | BW18: IND | BX18: IND | BY18: IND | CB18: 3321 | CC18: 3321 | CD18: IND | CE18: IND | CF18: IND | CI18: 3321 | CJ18: 3334 | CK18: IND | CL18: IND | CM18: IND | CP18: IND | CQ18: IND | CR18: IND | CS18: IND | CT18: IND | CW18: IND | CX18: IND | CY18: IND | CZ18: IND | DA18: IND | DD18: 3332 | DE18: 3332 | DF18: 3334 | DG18: PTO | DH18: PTO | DK18: PTO | DL18: PTO | DM18: PTO
A19: 3341 | C19: 3332 | D19: 3332 | E19: IND | F19: 3328 | G19: 3328 | J19: PTO | K19: PTO | L19: 3328 | M19: 3332 | N19: IND | Q19: 3328 | R19: 3332 | S19: 3335 | T19: IND | U19: IND | X19: 3336 | Y19: ASSY | Z19: ASSY | AA19: ASSY | AB19: ASSY | AE19: ASSY | AF19: ASSY | AG19: ASSY | AH19: ASSY | AI19: ASSY | AL19: ASSY | AM19: ASSY | AN19: IND | AO19: IND | AP19: IND | AS19: IND | AT19: IND | AU19: IND | AV19: IND | AW19: IND | AZ19: IND | BA19: IND | BB19: IND | BC19: IND | BD19: PTO | BG19: PTO | BH19: IND | BI19: IND | BJ19: IND | BK19: IND | BN19: IND | BO19: IND | BP19: IND | BQ19: IND | BR19: IND | BU19: PTO | BV19: IND | BW19: IND | BX19: IND | BY19: IND | CB19: 3321 | CC19: 3321 | CD19: IND | CE19: IND | CF19: IND | CI19: 3321 | CJ19: 3335 | CK19: IND | CL19: IND | CM19: IND | CP19: IND | CQ19: IND | CR19: IND | CS19: IND | CT19: IND | CW19: IND | CX19: IND | CY19: IND | CZ19: IND | DA19: IND | DD19: 3332 | DE19: 3332 | DF19: IND | DG19: PTO | DH19: PTO | DK19: PTO | DL19: PTO | DM19: PTO
A20: 3351 | C20: 3332 | D20: 3332 | E20: IND | F20: 3328 | G20: 3328 | J20: PTO | K20: PTO | L20: 3328 | M20: 3332 | N20: IND | Q20: IND | R20: 3332 | S20: 3335 | T20: IND | U20: IND | X20: 3334 | Y20: ASSY | Z20: ASSY | AA20: ASSY | AB20: ASSY | AE20: ASSY | AF20: ASSY | AG20: ASSY | AH20: ASSY | AI20: ASSY | AL20: ASSY | AM20: ASSY | AN20: IND | AO20: IND | AP20: IND | AS20: IND | AT20: IND | AU20: IND | AV20: IND | AW20: IND | AZ20: IND | BA20: IND | BB20: IND | BC20: IND | BD20: PTO | BG20: PTO | BH20: IND | BI20: IND | BJ20: IND | BK20: IND | BN20: IND | BO20: IND | BP20: IND | BQ20: IND | BR20: IND | BU20: PTO | BV20: IND | BW20: IND | BX20: IND | BY20: IND | CB20: 3321 | CC20: 3321 | CD20: IND | CE20: IND | CF20: IND | CI20: 3321 | CJ20: 3335 | CK20: IND | CL20: PTO | CM20: IND | CP20: IND | CQ20: IND | CR20: IND | CS20: IND | CT20: IND | CW20: IND | CX20: IND | CY20: IND | CZ20: IND | DA20: IND | DD20: 3332 | DE20: 3332 | DF20: IND | DG20: PTO | DH20: PTO | DK20: PTO | DL20: PTO | DM20: PTO
A21: 3321 | C21: 3332 | D21: 3332 | E21: IND | F21: 3328 | G21: 3328 | J21: PTO | K21: PTO | L21: 3328 | M21: 3332 | N21: IND | Q21: IND | R21: 3332 | S21: 3335 | T21: IND | U21: IND | X21: 3334 | Y21: ASSY | Z21: ASSY | AA21: ASSY | AB21: ASSY | AE21: ASSY | AF21: ASSY | AG21: ASSY | AH21: ASSY | AI21: ASSY | AL21: ASSY | AM21: ASSY | AN21: IND | AO21: IND | AP21: IND | AS21: IND | AT21: IND | AU21: IND | AV21: IND | AW21: IND | AZ21: IND | BA21: IND | BB21: IND | BC21: IND | BD21: PTO | BG21: PTO | BH21: IND | BI21: IND | BJ21: IND | BK21: IND | BN21: IND | BO21: IND | BP21: IND | BQ21: IND | BR21: IND | BU21: PTO | BV21: IND | BW21: IND | BX21: IND | BY21: IND | CB21: 3321 | CC21: 3321 | CD21: IND | CE21: IND | CF21: IND | CI21: 3321 | CJ21: IND | CK21: IND | CL21: PTO | CM21: IND | CP21: IND | CQ21: IND | CR21: IND | CS21: IND | CT21: IND | CW21: IND | CX21: IND | CY21: IND | CZ21: IND | DA21: IND | DD21: 3332 | DE21: 3332 | DF21: IND | DG21: PTO | DH21: PTO | DK21: PTO | DL21: PTO | DM21: PTO
C22: 3332 | D22: 3332 | E22: IND | F22: 3328 | G22: 3328 | J22: PTO | K22: PTO | L22: 3328 | M22: 3332 | N22: IND | Q22: IND | R22: 3332 | S22: IND | T22: IND | U22: IND | X22: 3334 | Y22: ASSY | Z22: ASSY | AA22: ASSY | AB22: ASSY | AE22: ASSY | AF22: ASSY | AG22: ASSY | AH22: ASSY | AI22: ASSY | AL22: ASSY | AM22: ASSY | AN22: IND | AO22: IND | AP22: IND | AS22: IND | AT22: IND | AU22: IND | AV22: IND | AW22: IND | AZ22: IND | BA22: IND | BB22: IND | BC22: IND | BD22: PTO | BG22: PTO | BH22: IND | BI22: IND | BJ22: IND | BK22: IND | BN22: IND | BO22: IND | BP22: IND | BQ22: IND | BR22: IND | BU22: PTO | BV22: IND | BW22: IND | BX22: IND | BY22: IND | CB22: 3321 | CC22: 3321 | CD22: IND | CE22: IND | CF22: IND | CI22: 3321 | CJ22: IND | CK22: IND | CL22: PTO | CM22: IND | CP22: IND | CQ22: IND | CR22: IND | CS22: IND | CT22: IND | CW22: IND | CX22: IND | CY22: IND | CZ22: IND | DA22: IND | DD22: 3332 | DE22: 3332 | DF22: IND | DG22: PTO | DH22: PTO | DK22: PTO | DL22: PTO | DM22: PTO
C23: 3332 | D23: 3332 | E23: IND | F23: 3328 | G23: 3328 | J23: PTO | K23: PTO | L23: 3328 | M23: 3332 | N23: IND | Q23: IND | R23: 3332 | S23: IND | T23: IND | U23: IND | X23: 3334 | Y23: ASSY | Z23: ASSY | AA23: ASSY | AB23: ASSY | AE23: ASSY | AF23: ASSY | AG23: ASSY | AH23: ASSY | AI23: ASSY | AL23: ASSY | AM23: ASSY | AN23: IND | AO23: IND | AP23: IND | AS23: IND | AT23: IND | AU23: IND | AV23: IND | AW23: IND | AZ23: IND | BA23: IND | BB23: IND | BC23: IND | BD23: PTO | BG23: PTO | BH23: IND | BI23: IND | BJ23: IND | BK23: IND | BN23: IND | BO23: IND | BP23: IND | BQ23: IND | BR23: IND | BU23: PTO | BV23: IND | BW23: IND | BX23: IND | BY23: IND | CB23: 3321 | CC23: 3321 | CD23: IND | CE23: IND | CF23: IND | CI23: 3321 | CJ23: IND | CK23: IND | CL23: PTO | CM23: IND | CP23: IND | CQ23: IND | CR23: IND | CS23: IND | CT23: IND | CW23: IND | CX23: IND | CY23: IND | CZ23: IND | DA23: IND | DD23: 3332 | DE23: 3332 | DF23: IND | DG23: PTO | DH23: PTO | DK23: PTO | DL23: PTO | DM23: PTO
C24: 3332 | D24: 3332 | E24: IND | F24: 3328 | G24: 3328 | J24: PTO | K24: PTO | L24: 3328 | M24: 3332 | N24: IND | Q24: IND | R24: 3332 | S24: IND | T24: IND | U24: IND | X24: ASSY | Y24: ASSY | Z24: ASSY | AA24: ASSY | AB24: ASSY | AE24: ASSY | AF24: ASSY | AG24: ASSY | AH24: ASSY | AI24: ASSY | AL24: ASSY | AM24: ASSY | AN24: IND | AO24: IND | AP24: IND | AS24: IND | AT24: IND | AU24: IND | AV24: IND | AW24: IND | AZ24: IND | BA24: IND | BB24: IND | BC24: IND | BD24: PTO | BG24: PTO | BH24: IND | BI24: IND | BJ24: IND | BK24: IND | BN24: IND | BO24: IND | BP24: IND | BQ24: IND | BR24: IND | BU24: PTO | BV24: IND | BW24: IND | BX24: IND | BY24: IND | CB24: 3321 | CC24: 3321 | CD24: IND | CE24: IND | CF24: IND | CI24: 3321 | CJ24: IND | CK24: IND | CL24: PTO | CM24: IND | CP24: IND | CQ24: IND | CR24: IND | CS24: IND | CT24: IND | CW24: IND | CX24: IND | CY24: IND | CZ24: IND | DA24: IND | DD24: 3332 | DE24: 3332 | DF24: IND | DG24: PTO | DH24: PTO | DK24: PTO | DL24: PTO | DM24: PTO
B28: Hilda Mata | C28: 3336 | D28: 3336 | E28: 3336 | F28: 3346 | G28: 3328 | J28: 3336 | K28: PTO | L28: 3336 | M28: 3346 | N28: 3328 | Q28: PTO | R28: 3328 | S28: 3328 | T28: 3336 | U28: 3346 | X28: PTO | Y28: 3328 | Z28: 3328 | AA28: 3336 | AB28: IND | AE28: PTO | AF28: 3336 | AG28: 3272 | AH28: ASSY | AI28: ASSY | AL28: 3272 | AM28: 3328 | AN28: 3328 | AO28: 3346 | AP28: 3346 | AS28: 3346 | AT28: 3346 | AU28: 3346 | AV28: IND | AW28: IND | AZ28: 3328 | BA28: IND | BB28: IND | BC28: IND | BD28: IND | BG28: 3346 | BH28: 3346 | BI28: IND | BJ28: IND | BK28: IND | BN28: 3346 | BO28: 3346 | BP28: IND | BQ28: IND | BR28: PTO | BU28: PTO | BV28: 3328 | BW28: IND | BX28: IND | BY28: IND | CB28: 3346 | CC28: IND | CD28: IND | CE28: IND | CF28: IND | CI28: 3328 | CJ28: IND | CK28: IND | CL28: IND | CM28: IND | CP28: 3346 | CQ28: IND | CR28: IND | CS28: IND | CT28: PTO | CW28: 3336 | CX28: IND | CY28: IND | CZ28: IND | DA28: IND | DD28: 3346 | DE28: IND | DF28: IND | DG28: PTO | DH28: IND | DK28: IND | DL28: IND | DM28: IND
C29: 3336 | D29: 3336 | E29: 3336 | F29: 3346 | G29: 3328 | J29: 3336 | K29: PTO | L29: 3336 | M29: 3346 | N29: 3328 | Q29: PTO | R29: 3328 | S29: 3328 | T29: 3336 | U29: 3346 | X29: PTO | Y29: 3328 | Z29: 3328 | AA29: 3336 | AB29: IND | AE29: PTO | AF29: 3336 | AG29: ASSY | AH29: ASSY | AI29: ASSY | AL29: 3272 | AM29: 3328 | AN29: 3328 | AO29: 3346 | AP29: 3346 | AS29: 3346 | AT29: 3346 | AU29: 3346 | AV29: IND | AW29: IND | AZ29: 3336 | BA29: IND | BB29: IND | BC29: IND | BD29: IND | BG29: 3346 | BH29: 3328 | BI29: IND | BJ29: IND | BK29: IND | BN29: 3346 | BO29: 3346 | BP29: IND | BQ29: IND | BR29: PTO | BU29: PTO | BV29: 3336 | BW29: IND | BX29: IND | BY29: IND | CB29: 3346 | CC29: IND | CD29: IND | CE29: IND | CF29: IND | CI29: 3336 | CJ29: IND | CK29: IND | CL29: IND | CM29: IND | CP29: 3346 | CQ29: IND | CR29: IND | CS29: IND | CT29: PTO | CW29: 3335 | CX29: IND | CY29: IND | CZ29: IND | DA29: IND | DD29: 3346 | DE29: IND | DF29: IND | DG29: PTO | DH29: IND | DK29: IND | DL29: IND | DM29: IND
C30: 3336 | D30: 3336 | E30: 3346 | F30: 3346 | G30: 3328 | J30: 3336 | K30: PTO | L30: 3336 | M30: 3346 | N30: 3328 | Q30: PTO | R30: 3328 | S30: 3328 | T30: 3336 | U30: IND | X30: PTO | Y30: 3328 | Z30: 3328 | AA30: 3336 | AB30: IND | AE30: PTO | AF30: 3336 | AG30: ASSY | AH30: ASSY | AI30: ASSY | AL30: 3272 | AM30: 3328 | AN30: 3336 | AO30: 3346 | AP30: 3346 | AS30: 3346 | AT30: 3346 | AU30: 3328 | AV30: IND | AW30: IND | AZ30: IND | BA30: IND | BB30: IND | BC30: IND | BD30: IND | BG30: 3346 | BH30: IND | BI30: IND | BJ30: IND | BK30: IND | BN30: 3346 | BO30: 3346 | BP30: IND | BQ30: IND | BR30: PTO | BU30: PTO | BV30: 3346 | BW30: IND | BX30: IND | BY30: IND | CB30: 3328 | CC30: IND | CD30: IND | CE30: IND | CF30: IND | CI30: 3336 | CJ30: IND | CK30: IND | CL30: IND | CM30: IND | CP30: 3346 | CQ30: IND | CR30: IND | CS30: IND | CT30: PTO | CW30: 3346 | CX30: IND | CY30: IND | CZ30: IND | DA30: IND | DD30: IND | DE30: IND | DF30: IND | DG30: PTO | DH30: IND | DK30: IND | DL30: IND | DM30: IND
C31: 3336 | D31: 3336 | E31: 3346 | F31: 3346 | G31: 3328 | J31: 3336 | K31: PTO | L31: 3336 | M31: 3346 | N31: 3328 | Q31: PTO | R31: 3328 | S31: 3328 | T31: 3336 | U31: IND | X31: PTO | Y31: 3328 | Z31: 3328 | AA31: IND | AB31: IND | AE31: PTO | AF31: 3336 | AG31: ASSY | AH31: ASSY | AI31: ASSY | AL31: 3272 | AM31: 3328 | AN31: 3336 | AO31: 3346 | AP31: 3346 | AS31: 3346 | AT31: 3346 | AU31: 3336 | AV31: IND | AW31: IND | AZ31: IND | BA31: IND | BB31: IND | BC31: IND | BD31: IND | BG31: 3346 | BH31: IND | BI31: IND | BJ31: IND | BK31: IND | BN31: 3346 | BO31: 3346 | BP31: IND | BQ31: IND | BR31: PTO | BU31: PTO | BV31: 3346 | BW31: IND | BX31: IND | BY31: IND | CB31: IND | CC31: IND | CD31: IND | CE31: IND | CF31: IND | CI31: 3336 | CJ31: IND | CK31: IND | CL31: IND | CM31: IND | CP31: 3346 | CQ31: IND | CR31: IND | CS31: IND | CT31: PTO | CW31: 3346 | CX31: IND | CY31: IND | CZ31: IND | DA31: IND | DD31: IND | DE31: IND | DF31: IND | DG31: PTO | DH31: IND | DK31: IND | DL31: IND | DM31: IND
C32: 3336 | D32: 3336 | E32: 3346 | F32: 3346 | G32: 3328 | J32: 3336 | K32: PTO | L32: 3336 | M32: 3346 | N32: 3328 | Q32: PTO | R32: 3328 | S32: 3328 | T32: 3336 | U32: IND | X32: PTO | Y32: 3328 | Z32: 3328 | AA32: IND | AB32: IND | AE32: PTO | AF32: 3328 | AG32: ASSY | AH32: ASSY | AI32: ASSY | AL32: 3272 | AM32: 3328 | AN32: 3336 | AO32: 3346 | AP32: 3346 | AS32: 3346 | AT32: 3346 | AU32: 3336 | AV32: IND | AW32: IND | AZ32: IND | BA32: IND | BB32: IND | BC32: IND | BD32: IND | BG32: 3346 | BH32: IND | BI32: IND | BJ32: IND | BK32: IND | BN32: 3346 | BO32: 3328 | BP32: IND | BQ32: IND | BR32: PTO | BU32: PTO | BV32: 3346 | BW32: IND | BX32: IND | BY32: IND | CB32: IND | CC32: IND | CD32: IND | CE32: IND | CF32: IND | CI32: 3336 | CJ32: IND | CK32: IND | CL32: PTO | CM32: IND | CP32: IND | CQ32: IND | CR32: IND | CS32: IND | CT32: PTO | CW32: IND | CX32: IND | CY32: IND | CZ32: IND | DA32: IND | DD32: IND | DE32: IND | DF32: IND | DG32: PTO | DH32: IND | DK32: IND | DL32: IND | DM32: IND
C33: 3336 | D33: 3336 | E33: 3346 | F33: 3346 | G33: 3328 | J33: 3336 | K33: PTO | L33: 3336 | M33: IND | N33: 3328 | Q33: PTO | R33: 3328 | S33: 3328 | T33: 3336 | U33: IND | X33: PTO | Y33: 3328 | Z33: 3328 | AA33: IND | AB33: IND | AE33: PTO | AF33: 3328 | AG33: ASSY | AH33: ASSY | AI33: ASSY | AL33: 3272 | AM33: 3328 | AN33: 3346 | AO33: 3346 | AP33: 3346 | AS33: 3346 | AT33: 3346 | AU33: 3336 | AV33: IND | AW33: IND | AZ33: IND | BA33: IND | BB33: IND | BC33: IND | BD33: IND | BG33: 3346 | BH33: IND | BI33: IND | BJ33: IND | BK33: IND | BN33: 3346 | BO33: IND | BP33: IND | BQ33: IND | BR33: PTO | BU33: PTO | BV33: 3346 | BW33: IND | BX33: IND | BY33: IND | CB33: IND | CC33: IND | CD33: IND | CE33: IND | CF33: IND | CI33: 3336 | CJ33: IND | CK33: IND | CL33: PTO | CM33: IND | CP33: IND | CQ33: IND | CR33: IND | CS33: IND | CT33: PTO | CW33: IND | CX33: IND | CY33: IND | CZ33: IND | DA33: IND | DD33: IND | DE33: IND | DF33: IND | DG33: PTO | DH33: IND | DK33: IND | DL33: IND | DM33: IND
C34: 3336 | D34: 3336 | E34: 3346 | F34: 3346 | G34: 3328 | J34: 3336 | K34: PTO | L34: 3336 | M34: IND | N34: 3328 | Q34: PTO | R34: 3328 | S34: 3328 | T34: 3336 | U34: IND | X34: PTO | Y34: 3328 | Z34: 3328 | AA34: IND | AB34: IND | AE34: PTO | AF34: 3328 | AG34: ASSY | AH34: ASSY | AI34: ASSY | AL34: 3272 | AM34: 3328 | AN34: 3346 | AO34: 3346 | AP34: 3346 | AS34: 3346 | AT34: 3346 | AU34: IND | AV34: IND | AW34: IND | AZ34: IND | BA34: IND | BB34: IND | BC34: IND | BD34: IND | BG34: 3346 | BH34: IND | BI34: IND | BJ34: IND | BK34: IND | BN34: 3346 | BO34: IND | BP34: IND | BQ34: IND | BR34: PTO | BU34: PTO | BV34: IND | BW34: IND | BX34: IND | BY34: IND | CB34: IND | CC34: IND | CD34: IND | CE34: IND | CF34: IND | CI34: 3336 | CJ34: IND | CK34: IND | CL34: PTO | CM34: IND | CP34: IND | CQ34: IND | CR34: IND | CS34: IND | CT34: PTO | CW34: IND | CX34: IND | CY34: IND | CZ34: IND | DA34: IND | DD34: IND | DE34: IND | DF34: IND | DG34: PTO | DH34: IND | DK34: IND | DL34: IND | DM34: IND
C35: 3336 | D35: 3336 | E35: 3346 | F35: 3346 | G35: 3328 | J35: 3336 | K35: PTO | L35: 3336 | M35: IND | N35: 3328 | Q35: PTO | R35: 3328 | S35: 3328 | T35: 3336 | U35: IND | X35: PTO | Y35: 3328 | Z35: 3328 | AA35: IND | AB35: IND | AE35: PTO | AF35: 3328 | AG35: ASSY | AH35: ASSY | AI35: ASSY | AL35: 3272 | AM35: 3328 | AN35: 3346 | AO35: 3346 | AP35: IND | AS35: 3346 | AT35: 3346 | AU35: IND | AV35: IND | AW35: IND | AZ35: IND | BA35: IND | BB35: IND | BC35: IND | BD35: IND | BG35: 3346 | BH35: IND | BI35: IND | BJ35: IND | BK35: IND | BN35: 3346 | BO35: IND | BP35: IND | BQ35: IND | BR35: PTO | BU35: PTO | BV35: IND | BW35: IND | BX35: IND | BY35: IND | CB35: IND | CC35: IND | CD35: IND | CE35: IND | CF35: IND | CI35: IND | CJ35: IND | CK35: IND | CL35: PTO | CM35: IND | CP35: IND | CQ35: IND | CR35: IND | CS35: IND | CT35: PTO | CW35: IND | CX35: IND | CY35: IND | CZ35: IND | DA35: IND | DD35: IND | DE35: IND | DF35: IND | DG35: PTO | DH35: IND | DK35: IND | DL35: IND | DM35: IND
C36: 3336 | D36: 3336 | E36: 3272 | F36: 3346 | G36: 3328 | J36: 3336 | K36: PTO | L36: 3336 | M36: 3272 | N36: 3328 | Q36: PTO | R36: 3328 | S36: 3328 | T36: 3336 | U36: IND | X36: PTO | Y36: 3328 | Z36: 3328 | AA36: IND | AB36: IND | AE36: PTO | AF36: 3328 | AG36: ASSY | AH36: ASSY | AI36: ASSY | AL36: 3272 | AM36: 3328 | AN36: 3346 | AO36: 3346 | AP36: IND | AS36: 3346 | AT36: 3346 | AU36: IND | AV36: IND | AW36: IND | AZ36: IND | BA36: IND | BB36: IND | BC36: IND | BD36: IND | BG36: 3346 | BH36: IND | BI36: IND | BJ36: IND | BK36: IND | BN36: 3346 | BO36: IND | BP36: IND | BQ36: IND | BR36: PTO | BU36: PTO | BV36: IND | BW36: IND | BX36: IND | BY36: IND | CB36: IND | CC36: IND | CD36: IND | CE36: IND | CF36: IND | CI36: IND | CJ36: IND | CK36: IND | CL36: PTO | CM36: IND | CP36: IND | CQ36: IND | CR36: IND | CS36: IND | CT36: PTO | CW36: IND | CX36: IND | CY36: IND | CZ36: IND | DA36: IND | DD36: IND | DE36: IND | DF36: IND | DG36: PTO | DH36: IND | DK36: IND | DL36: IND | DM36: IND
B40: José Wenceslao
B52: Adrian C | C52: IND | D52: 3340 | E52: 3340 | F52: 3328 | G52: 3328 | J52: MG | K52: PTO | L52: 3328 | M52: IND | N52: IND | Q52: MNG | R52: 3340 | S52: IND | T52: PTO | U52: PTO | X52: PTO | Y52: PTO | Z52: 3328 | AA52: MNG | AB52: 3340 | AE52: MNG | AF52: MNG | AG52: MNG | AH52: IND | AI52: MNG | AL52: MNG | AM52: MNG | AN52: MNG | AO52: 3341 | AP52: MNG | AS52: MNG | AT52: MNG | AU52: MNG | AV52: 3331 | AW52: 3340 | AZ52: MNG | BA52: MNG | BB52: MNG | BC52: IND | BD52: IND | BG52: MNG | BH52: MNG | BI52: MNG | BJ52: IND | BK52: IND | BN52: MNG | BO52: MNG | BP52: MNG | BQ52: IND | BR52: IND | BU52: PTO | BV52: MNG | BW52: MNG | BX52: IND | BY52: IND | CB52: MNG | CC52: MNG | CD52: MNG | CE52: IND | CF52: IND | CI52: MNG | CJ52: MNG | CK52: MNG | CL52: IND | CM52: 3328 | CP52: MNG | CQ52: MNG | CR52: MNG | CS52: IND | CT52: IND | CW52: MNG | CX52: MNG | CY52: MNG | CZ52: IND | DA52: 3328 | DD52: PTO | DE52: PTO | DF52: PTO | DG52: PTO | DH52: PTO | DK52: PTO | DL52: PTO | DM52: PTO
C53: IND | D53: 3340 | E53: 3340 | F53: 3328 | G53: 3328 | J53: IND | K53: PTO | L53: 3328 | M53: IND | N53: IND | Q53: MNG | R53: IND | S53: IND | T53: PTO | U53: PTO | X53: PTO | Y53: PTO | Z53: 3328 | AA53: MNG | AB53: 3340 | AE53: MNG | AF53: 3331 | AG53: MNG | AH53: IND | AI53: MNG | AL53: MNG | AM53: IND | AN53: MNG | AO53: 3341 | AP53: MNG | AS53: MNG | AT53: 3328 | AU53: MNG | AV53: 3331 | AW53: 3340 | AZ53: MNG | BA53: IND | BB53: MNG | BC53: IND | BD53: IND | BG53: MNG | BH53: IND | BI53: MNG | BJ53: IND | BK53: IND | BN53: MNG | BO53: IND | BP53: MNG | BQ53: IND | BR53: IND | BU53: PTO | BV53: IND | BW53: MNG | BX53: IND | BY53: IND | CB53: MNG | CC53: IND | CD53: MNG | CE53: IND | CF53: IND | CI53: MNG | CJ53: IND | CK53: MNG | CL53: IND | CM53: IND | CP53: MNG | CQ53: IND | CR53: MNG | CS53: IND | CT53: IND | CW53: MNG | CX53: IND | CY53: MNG | CZ53: IND | DA53: 3328 | DD53: PTO | DE53: PTO | DF53: PTO | DG53: PTO | DH53: PTO | DK53: PTO | DL53: PTO | DM53: PTO
C54: IND | D54: 3340 | E54: 3340 | F54: 3328 | G54: 3328 | J54: IND | K54: PTO | L54: 3328 | M54: IND | N54: IND | Q54: MNG | R54: IND | S54: IND | T54: PTO | U54: PTO | X54: PTO | Y54: PTO | Z54: IND | AA54: IND | AB54: 3340 | AE54: IND | AF54: 3331 | AG54: MNG | AH54: IND | AI54: IND | AL54: IND | AM54: IND | AN54: MNG | AO54: 3341 | AP54: 3331 | AS54: IND | AT54: IND | AU54: MNG | AV54: 3331 | AW54: 3340 | AZ54: IND | BA54: IND | BB54: MNG | BC54: IND | BD54: IND | BG54: IND | BH54: IND | BI54: MNG | BJ54: IND | BK54: IND | BN54: IND | BO54: IND | BP54: MNG | BQ54: IND | BR54: IND | BU54: PTO | BV54: IND | BW54: MNG | BX54: IND | BY54: IND | CB54: IND | CC54: IND | CD54: MNG | CE54: IND | CF54: IND | CI54: IND | CJ54: IND | CK54: MNG | CL54: IND | CM54: IND | CP54: IND | CQ54: IND | CR54: MNG | CS54: IND | CT54: IND | CW54: IND | CX54: IND | CY54: MNG | CZ54: IND | DA54: 3346 | DD54: PTO | DE54: PTO | DF54: PTO | DG54: PTO | DH54: PTO | DK54: PTO | DL54: PTO | DM54: PTO
C55: IND | D55: 3340 | E55: 3340 | F55: 3328 | G55: 3328 | J55: IND | K55: PTO | L55: 3328 | M55: IND | N55: IND | Q55: IND | R55: IND | S55: IND | T55: PTO | U55: PTO | X55: PTO | Y55: PTO | Z55: IND | AA55: IND | AB55: 3340 | AE55: IND | AF55: IND | AG55: IND | AH55: IND | AI55: IND | AL55: IND | AM55: IND | AN55: IND | AO55: 3341 | AP55: 3331 | AS55: IND | AT55: IND | AU55: IND | AV55: IND | AW55: 3340 | AZ55: IND | BA55: IND | BB55: IND | BC55: IND | BD55: IND | BG55: IND | BH55: IND | BI55: IND | BJ55: IND | BK55: IND | BN55: IND | BO55: IND | BP55: IND | BQ55: IND | BR55: IND | BU55: PTO | BV55: IND | BW55: IND | BX55: IND | BY55: IND | CB55: IND | CC55: IND | CD55: IND | CE55: IND | CF55: IND | CI55: IND | CJ55: IND | CK55: IND | CL55: IND | CM55: IND | CP55: IND | CQ55: IND | CR55: IND | CS55: IND | CT55: IND | CW55: IND | CX55: IND | CY55: IND | CZ55: IND | DA55: 3346 | DD55: PTO | DE55: PTO | DF55: PTO | DG55: PTO | DH55: PTO | DK55: PTO | DL55: PTO | DM55: PTO
C56: IND | D56: 3340 | E56: 3340 | F56: 3328 | G56: 3328 | J56: IND | K56: PTO | L56: 3328 | M56: IND | N56: IND | Q56: IND | R56: IND | S56: IND | T56: PTO | U56: PTO | X56: PTO | Y56: PTO | Z56: IND | AA56: IND | AB56: 3340 | AE56: IND | AF56: IND | AG56: IND | AH56: IND | AI56: IND | AL56: IND | AM56: IND | AN56: IND | AO56: 3341 | AP56: 3331 | AS56: IND | AT56: IND | AU56: IND | AV56: IND | AW56: 3340 | AZ56: IND | BA56: IND | BB56: IND | BC56: IND | BD56: IND | BG56: IND | BH56: IND | BI56: IND | BJ56: IND | BK56: IND | BN56: IND | BO56: IND | BP56: IND | BQ56: IND | BR56: IND | BU56: PTO | BV56: IND | BW56: IND | BX56: IND | BY56: IND | CB56: IND | CC56: IND | CD56: IND | CE56: IND | CF56: IND | CI56: IND | CJ56: IND | CK56: IND | CL56: PTO | CM56: IND | CP56: IND | CQ56: IND | CR56: IND | CS56: IND | CT56: IND | CW56: IND | CX56: IND | CY56: IND | CZ56: IND | DA56: IND | DD56: PTO | DE56: PTO | DF56: PTO | DG56: PTO | DH56: PTO | DK56: PTO | DL56: PTO | DM56: PTO
C57: IND | D57: 3340 | E57: 3340 | F57: 3328 | G57: 3328 | J57: IND | K57: PTO | L57: 3328 | M57: IND | N57: IND | Q57: IND | R57: IND | S57: IND | T57: PTO | U57: PTO | X57: PTO | Y57: PTO | Z57: IND | AA57: IND | AB57: 3340 | AE57: IND | AF57: IND | AG57: IND | AH57: IND | AI57: IND | AL57: IND | AM57: IND | AN57: IND | AO57: 3341 | AP57: IND | AS57: IND | AT57: IND | AU57: IND | AV57: IND | AW57: 3340 | AZ57: IND | BA57: IND | BB57: IND | BC57: IND | BD57: IND | BG57: IND | BH57: IND | BI57: IND | BJ57: IND | BK57: IND | BN57: IND | BO57: IND | BP57: IND | BQ57: IND | BR57: IND | BU57: PTO | BV57: IND | BW57: IND | BX57: IND | BY57: IND | CB57: IND | CC57: IND | CD57: IND | CE57: IND | CF57: IND | CI57: IND | CJ57: IND | CK57: IND | CL57: PTO | CM57: IND | CP57: IND | CQ57: IND | CR57: IND | CS57: IND | CT57: IND | CW57: IND | CX57: IND | CY57: IND | CZ57: IND | DA57: IND | DD57: PTO | DE57: PTO | DF57: PTO | DG57: PTO | DH57: PTO | DK57: PTO | DL57: PTO | DM57: PTO
C58: IND | D58: 3340 | E58: 3340 | F58: 3328 | G58: 3328 | J58: IND | K58: PTO | L58: 3328 | M58: IND | N58: IND | Q58: IND | R58: IND | S58: IND | T58: PTO | U58: PTO | X58: PTO | Y58: PTO | Z58: IND | AA58: IND | AB58: 3340 | AE58: IND | AF58: IND | AG58: IND | AH58: IND | AI58: IND | AL58: IND | AM58: IND | AN58: IND | AO58: 3341 | AP58: IND | AS58: IND | AT58: IND | AU58: IND | AV58: IND | AW58: 3340 | AZ58: IND | BA58: IND | BB58: IND | BC58: IND | BD58: IND | BG58: IND | BH58: IND | BI58: IND | BJ58: IND | BK58: IND | BN58: IND | BO58: IND | BP58: IND | BQ58: IND | BR58: IND | BU58: PTO | BV58: IND | BW58: IND | BX58: IND | BY58: IND | CB58: IND | CC58: IND | CD58: IND | CE58: IND | CF58: IND | CI58: IND | CJ58: IND | CK58: IND | CL58: PTO | CM58: IND | CP58: IND | CQ58: IND | CR58: IND | CS58: IND | CT58: IND | CW58: IND | CX58: IND | CY58: IND | CZ58: IND | DA58: IND | DD58: PTO | DE58: PTO | DF58: PTO | DG58: PTO | DH58: PTO | DK58: PTO | DL58: PTO | DM58: PTO
C59: IND | D59: 3340 | E59: 3340 | F59: 3328 | G59: 3328 | J59: IND | K59: PTO | L59: 3328 | M59: IND | N59: IND | Q59: IND | R59: IND | S59: IND | T59: PTO | U59: PTO | X59: PTO | Y59: PTO | Z59: IND | AA59: IND | AB59: 3340 | AE59: IND | AF59: IND | AG59: IND | AH59: IND | AI59: IND | AL59: IND | AM59: IND | AN59: IND | AO59: 3341 | AP59: IND | AS59: IND | AT59: IND | AU59: IND | AV59: IND | AW59: 3340 | AZ59: IND | BA59: IND | BB59: IND | BC59: IND | BD59: IND | BG59: IND | BH59: IND | BI59: IND | BJ59: IND | BK59: IND | BN59: IND | BO59: IND | BP59: IND | BQ59: IND | BR59: IND | BU59: PTO | BV59: IND | BW59: IND | BX59: IND | BY59: IND | CB59: IND | CC59: IND | CD59: IND | CE59: IND | CF59: IND | CI59: IND | CJ59: IND | CK59: IND | CL59: PTO | CM59: IND | CP59: IND | CQ59: IND | CR59: IND | CS59: IND | CT59: IND | CW59: IND | CX59: IND | CY59: IND | CZ59: IND | DA59: IND | DD59: PTO | DE59: PTO | DF59: PTO | DG59: PTO | DH59: PTO | DK59: PTO | DL59: PTO | DM59: PTO
C60: IND | D60: 3340 | E60: 3340 | F60: 3328 | G60: 3328 | J60: IND | K60: PTO | L60: 3328 | M60: IND | N60: IND | Q60: IND | R60: IND | S60: IND | T60: PTO | U60: PTO | X60: PTO | Y60: PTO | Z60: IND | AA60: IND | AB60: 3340 | AE60: IND | AF60: IND | AG60: IND | AH60: IND | AI60: IND | AL60: IND | AM60: IND | AN60: IND | AO60: 3341 | AP60: IND | AS60: IND | AT60: IND | AU60: IND | AV60: IND | AW60: 3340 | AZ60: IND | BA60: IND | BB60: IND | BC60: IND | BD60: IND | BG60: IND | BH60: IND | BI60: IND | BJ60: IND | BK60: IND | BN60: IND | BO60: IND | BP60: IND | BQ60: IND | BR60: IND | BU60: PTO | BV60: IND | BW60: IND | BX60: IND | BY60: IND | CB60: IND | CC60: IND | CD60: IND | CE60: IND | CF60: IND | CI60: IND | CJ60: IND | CK60: IND | CL60: PTO | CM60: IND | CP60: IND | CQ60: IND | CR60: IND | CS60: IND | CT60: IND | CW60: IND | CX60: IND | CY60: IND | CZ60: IND | DA60: IND | DD60: PTO | DE60: PTO | DF60: PTO | DG60: PTO | DH60: PTO | DK60: PTO | DL60: PTO | DM60: PTO

Sheet HD Forecast 2026
A1: #VALUE! | B1: Month | C1: January | AH1: February | BJ1: March | CO1: April | DS1: May | EX1: June | GB1: July | HG1: August | IL1: September | JP1: October | KU1: November | LY1: December
B2: Week | C2: 1 | G2: 2 | N2: 3 | U2: 4 | AB2: 5 | AI2: 6 | AP2: 7 | AW2: 8 | BD2: 9 | BK2: 10 | BR2: 11 | BY2: 12 | CF2: 13 | CM2: 14 | CT2: 15 | DA2: 16 | DH2: 17 | DO2: 18 | DV2: 19 | EC2: 20 | EJ2: 21 | EQ2: 22 | EX2: 23 | FE2: 24 | FL2: 25 | FS2: 26 | FZ2: 27 | GG2: 28 | GN2: 29 | GU2: 30 | HB2: 31 | HI2: 32 | HP2: 33 | HW2: 34 | ID2: 35 | IK2: 36 | IR2: 37 | IY2: 38 | JF2: 39 | JM2: 40 | JT2: 41 | KA2: 42 | KH2: 43 | KO2: 44 | KV2: 45 | LC2: 46 | LJ2: 47 | LQ2: 48 | LX2: 49 | ME2: 50 | ML2: 51 | MS2: 52 | MZ2: 53
B3: Day | C3: 1 | D3: 2 | E3: 3 | F3: 4 | G3: 5 | H3: 6 | I3: 7 | J3: 8 | K3: 9 | L3: 10 | M3: 11 | N3: 12 | O3: 13 | P3: 14 | Q3: 15 | R3: 16 | S3: 17 | T3: 18 | U3: 19 | V3: 20 | W3: 21 | X3: 22 | Y3: 23 | Z3: 24 | AA3: 25 | AB3: 26 | AC3: 27 | AD3: 28 | AE3: 29 | AF3: 30 | AG3: 31 | AH3: 1 | AI3: 2 | AJ3: 3 | AK3: 4 | AL3: 5 | AM3: 6 | AN3: 7 | AO3: 8 | AP3: 9 | AQ3: 10 | AR3: 11 | AS3: 12 | AT3: 13 | AU3: 14 | AV3: 15 | AW3: 16 | AX3: 17 | AY3: 18 | AZ3: 19 | BA3: 20 | BB3: 21 | BC3: 22 | BD3: 23 | BE3: 24 | BF3: 25 | BG3: 26 | BH3: 27 | BI3: 28 | BJ3: 1 | BK3: 2 | BL3: 3 | BM3: 4 | BN3: 5 | BO3: 6 | BP3: 7 | BQ3: 8 | BR3: 9 | BS3: 10 | BT3: 11 | BU3: 12 | BV3: 13 | BW3: 14 | BX3: 15 | BY3: 16 | BZ3: 17 | CA3: 18 | CB3: 19 | CC3: 20 | CD3: 21 | CE3: 22 | CF3: 23 | CG3: 24 | CH3: 25 | CI3: 26 | CJ3: 27 | CK3: 28 | CL3: 29 | CM3: 30 | CN3: 31 | CO3: 1 | CP3: 2 | CQ3: 3 | CR3: 4 | CS3: 5 | CT3: 6 | CU3: 7 | CV3: 8 | CW3: 9 | CX3: 10 | CY3: 11 | CZ3: 12 | DA3: 13 | DB3: 14 | DC3: 15 | DD3: 16 | DE3: 17 | DF3: 18 | DG3: 19 | DH3: 20 | DI3: 21 | DJ3: 22 | DK3: 23 | DL3: 24 | DM3: 25 | DN3: 26 | DO3: 27 | DP3: 28 | DQ3: 29 | DR3: 30 | DS3: 1 | DT3: 2 | DU3: 3 | DV3: 4 | DW3: 5 | DX3: 6 | DY3: 7 | DZ3: 8 | EA3: 9 | EB3: 10 | EC3: 11 | ED3: 12 | EE3: 13 | EF3: 14 | EG3: 15 | EH3: 16 | EI3: 17 | EJ3: 18 | EK3: 19 | EL3: 20 | EM3: 21 | EN3: 22 | EO3: 23 | EP3: 24 | EQ3: 25 | ER3: 26 | ES3: 27 | ET3: 28 | EU3: 29 | EV3: 30 | EW3: 31 | EX3: 1 | EY3: 2 | EZ3: 3 | FA3: 4 | FB3: 5 | FC3: 6 | FD3: 7 | FE3: 8 | FF3: 9 | FG3: 10 | FH3: 11 | FI3: 12 | FJ3: 13 | FK3: 14 | FL3: 15 | FM3: 16 | FN3: 17 | FO3: 18 | FP3: 19 | FQ3: 20 | FR3: 21 | FS3: 22 | FT3: 23 | FU3: 24 | FV3: 25 | FW3: 26 | FX3: 27 | FY3: 28 | FZ3: 29 | GA3: 30 | GB3: 1 | GC3: 2 | GD3: 3 | GE3: 4 | GF3: 5 | GG3: 6 | GH3: 7 | GI3: 8 | GJ3: 9 | GK3: 10 | GL3: 11 | GM3: 12 | GN3: 13 | GO3: 14 | GP3: 15 | GQ3: 16 | GR3: 17 | GS3: 18 | GT3: 19 | GU3: 20 | GV3: 21 | GW3: 22 | GX3: 23 | GY3: 24 | GZ3: 25 | HA3: 26 | HB3: 27 | HC3: 28 | HD3: 29 | HE3: 30 | HF3: 31 | HG3: 1 | HH3: 2 | HI3: 3 | HJ3: 4 | HK3: 5 | HL3: 6 | HM3: 7 | HN3: 8 | HO3: 9 | HP3: 10 | HQ3: 11 | HR3: 12 | HS3: 13 | HT3: 14 | HU3: 15 | HV3: 16 | HW3: 17 | HX3: 18 | HY3: 19 | HZ3: 20 | IA3: 21 | IB3: 22 | IC3: 23 | ID3: 24 | IE3: 25 | IF3: 26 | IG3: 27 | IH3: 28 | II3: 29 | IJ3: 30 | IK3: 31 | IL3: 1 | IM3: 2 | IN3: 3 | IO3: 4 | IP3: 5 | IQ3: 6 | IR3: 7 | IS3: 8 | IT3: 9 | IU3: 10 | IV3: 11 | IW3: 12 | IX3: 13 | IY3: 14 | IZ3: 15 | JA3: 16 | JB3: 17 | JC3: 18 | JD3: 19 | JE3: 20 | JF3: 21 | JG3: 22 | JH3: 23 | JI3: 24 | JJ3: 25 | JK3: 26 | JL3: 27 | JM3: 28 | JN3: 29 | JO3: 30 | JP3: 1 | JQ3: 2 | JR3: 3 | JS3: 4 | JT3: 5 | JU3: 6 | JV3: 7 | JW3: 8 | JX3: 9 | JY3: 10 | JZ3: 11 | KA3: 12 | KB3: 13 | KC3: 14 | KD3: 15 | KE3: 16 | KF3: 17 | KG3: 18 | KH3: 19 | KI3: 20 | KJ3: 21 | KK3: 22 | KL3: 23 | KM3: 24 | KN3: 25 | KO3: 26 | KP3: 27 | KQ3: 28 | KR3: 29 | KS3: 30 | KT3: 31 | KU3: 1 | KV3: 2 | KW3: 3 | KX3: 4 | KY3: 5 | KZ3: 6 | LA3: 7 | LB3: 8 | LC3: 9 | LD3: 10 | LE3: 11 | LF3: 12 | LG3: 13 | LH3: 14 | LI3: 15 | LJ3: 16 | LK3: 17 | LL3: 18 | LM3: 19 | LN3: 20 | LO3: 21 | LP3: 22 | LQ3: 23 | LR3: 24 | LS3: 25 | LT3: 26 | LU3: 27 | LV3: 28 | LW3: 29 | LX3: 30 | LY3: 1 | LZ3: 2 | MA3: 3 | MB3: 4 | MC3: 5 | MD3: 6 | ME3: 7 | MF3: 8 | MG3: 9 | MH3: 10 | MI3: 11 | MJ3: 12 | MK3: 13 | ML3: 14 | MM3: 15 | MN3: 16 | MO3: 17 | MP3: 18 | MQ3: 19 | MR3: 20 | MS3: 21 | MT3: 22 | MU3: 23 | MV3: 24 | MW3: 25 | MX3: 26 | MY3: 27 | MZ3: 28 | NA3: 29 | NB3: 30 | NC3: 31
A4: IND | B4: Juan Adame | C4: PTO | D4: IND | N4: 3272 | O4: 3363 | P4: IND | Q4: IND | R4: IND | U4: 3300 | V4: 3300 | W4: 3363 | X4: 3363 | Y4: IND | AB4: 3300 | AC4: 3300 | AD4: 3363 | AE4: 3363 | AF4: 3336 | AI4: HOL | AJ4: IND | AK4: IND | AL4: IND | AM4: IND | AP4: 3300 | AQ4: 3300 | AR4: 3363 | AS4: 3363 | AT4: IND | AW4: 3300 | AX4: 3300 | AY4: 3300 | AZ4: 3363 | BA4: IND | BD4: 3300 | BE4: 3300 | BF4: IND | BG4: IND | BH4: IND | BK4: 3300 | BL4: 3300 | BM4: 3300 | BN4: IND | BO4: IND
A5: MNG | C5: PTO | D5: IND | N5: 3336 | O5: 3363 | P5: IND | Q5: IND | R5: IND | U5: 3300 | V5: 3300 | W5: 3363 | X5: 3363 | Y5: IND | AB5: 3300 | AC5: 3300 | AD5: 3363 | AE5: 3363 | AF5: 3336 | AI5: HOL | AJ5: IND | AK5: IND | AL5: IND | AM5: IND | AP5: 3300 | AQ5: 3300 | AR5: 3363 | AS5: 3363 | AT5: IND | AW5: 3300 | AX5: 3300 | AY5: 3300 | AZ5: 3363 | BA5: IND | BD5: 3300 | BE5: 3300 | BF5: IND | BG5: IND | BH5: IND | BK5: 3300 | BL5: 3300 | BM5: 3300 | BN5: IND | BO5: IND
A6: ASSY | C6: PTO | D6: IND | N6: 3336 | O6: 3363 | P6: IND | Q6: IND | R6: IND | U6: 3300 | V6: 3300 | W6: 3363 | X6: 3363 | Y6: IND | AB6: 3300 | AC6: 3300 | AD6: 3363 | AE6: 3363 | AF6: 3336 | AI6: HOL | AJ6: IND | AK6: IND | AL6: IND | AM6: IND | AP6: 3300 | AQ6: 3300 | AR6: 3363 | AS6: 3363 | AT6: IND | AW6: 3300 | AX6: 3300 | AY6: 3300 | AZ6: IND | BA6: IND | BD6: 3300 | BE6: 3300 | BF6: IND | BG6: IND | BH6: IND | BK6: 3300 | BL6: 3300 | BM6: 3300 | BN6: IND | BO6: IND
A7: PTO | C7: PTO | D7: IND | N7: 3363 | O7: 3363 | P7: IND | Q7: IND | R7: IND | U7: 3300 | V7: 3300 | W7: 3363 | X7: 3272 | Y7: IND | AB7: 3300 | AC7: 3300 | AD7: 3363 | AE7: 3363 | AF7: 3336 | AI7: HOL | AJ7: IND | AK7: IND | AL7: IND | AM7: IND | AP7: 3300 | AQ7: 3300 | AR7: 3363 | AS7: 3363 | AT7: IND | AW7: 3300 | AX7: 3300 | AY7: 3300 | AZ7: IND | BA7: IND | BD7: 3300 | BE7: 3300 | BF7: IND | BG7: IND | BH7: IND | BK7: 3300 | BL7: 3300 | BM7: 3300 | BN7: IND | BO7: IND
A8: 3268 | C8: PTO | D8: IND | N8: 3363 | O8: 3363 | P8: IND | Q8: IND | R8: IND | U8: 3300 | V8: 3300 | W8: 3363 | X8: IND | Y8: IND | AB8: 3300 | AC8: 3300 | AD8: 3363 | AE8: 3363 | AF8: 3336 | AI8: HOL | AJ8: IND | AK8: IND | AL8: IND | AM8: IND | AP8: 3300 | AQ8: 3300 | AR8: 3363 | AS8: 3363 | AT8: IND | AW8: 3300 | AX8: 3300 | AY8: 3300 | AZ8: IND | BA8: IND | BD8: 3300 | BE8: 3300 | BF8: IND | BG8: IND | BH8: IND | BK8: 3300 | BL8: 3300 | BM8: 3300 | BN8: IND | BO8: IND
A9: 3335 | C9: PTO | D9: IND | N9: 3363 | O9: 3363 | P9: IND | Q9: IND | R9: IND | U9: 3300 | V9: 3300 | W9: 3363 | X9: IND | Y9: IND | AB9: 3300 | AC9: 3300 | AD9: 3363 | AE9: 3363 | AF9: 3336 | AI9: HOL | AJ9: IND | AK9: IND | AL9: IND | AM9: IND | AP9: 3300 | AQ9: 3300 | AR9: 3363 | AS9: 3363 | AT9: IND | AW9: 3300 | AX9: 3300 | AY9: 3300 | AZ9: IND | BA9: IND | BD9: 3300 | BE9: 3300 | BF9: IND | BG9: IND | BH9: IND | BK9: 3300 | BL9: 3300 | BM9: 3300 | BN9: IND | BO9: IND
A10: 3332 | C10: PTO | D10: IND | N10: 3363 | O10: 3363 | P10: IND | Q10: IND | R10: IND | U10: 3300 | V10: 3363 | W10: 3363 | X10: IND | Y10: IND | AB10: 3300 | AC10: 3300 | AD10: 3363 | AE10: 3336 | AF10: 3336 | AI10: HOL | AJ10: IND | AK10: IND | AL10: IND | AM10: IND | AP10: 3300 | AQ10: 3300 | AR10: 3363 | AS10: IND | AT10: IND | AW10: 3300 | AX10: 3300 | AY10: 3300 | AZ10: IND | BA10: IND | BD10: 3300 | BE10: 3300 | BF10: IND | BG10: IND | BH10: IND | BK10: 3300 | BL10: 3300 | BM10: 3300 | BN10: IND | BO10: IND
A11: 3328 | C11: PTO | D11: IND | N11: 3363 | O11: 3363 | P11: IND | Q11: IND | R11: IND | U11: 3300 | V11: 3363 | W11: 3363 | X11: IND | Y11: IND | AB11: 3300 | AC11: 3300 | AD11: 3363 | AE11: 3336 | AF11: 3336 | AI11: HOL | AJ11: IND | AK11: IND | AL11: IND | AM11: IND | AP11: 3300 | AQ11: 3300 | AR11: 3363 | AS11: IND | AT11: IND | AW11: 3300 | AX11: 3300 | AY11: 3300 | AZ11: IND | BA11: IND | BD11: 3300 | BE11: 3300 | BF11: IND | BG11: IND | BH11: IND | BK11: 3300 | BL11: 3300 | BM11: 3300 | BN11: IND | BO11: IND
A12: 3346 | C12: PTO | D12: IND | N12: 3363 | O12: 3363 | P12: IND | Q12: IND | R12: IND | U12: 3300 | V12: 3363 | W12: 3363 | X12: IND | Y12: IND | AB12: 3300 | AC12: 3300 | AD12: 3363 | AE12: 3336 | AF12: 3272 | AI12: HOL | AJ12: IND | AK12: IND | AL12: IND | AM12: IND | AP12: 3300 | AQ12: 3300 | AR12: 3363 | AS12: IND | AT12: 3272 | AW12: 3300 | AX12: 3300 | AY12: 3300 | AZ12: IND | BA12: IND | BD12: 3300 | BE12: 3300 | BF12: IND | BG12: IND | BH12: IND | BK12: 3300 | BL12: 3300 | BM12: 3300 | BN12: IND | BO12: IND
A13: 3334
A14: 3336
A15: 3272
A16: 3363 | B16: Fidel Maldonado | C16: PTO | D16: PTO | G16: IND | H16: 3332 | I16: 3332 | J16: 3332 | K16: 3332 | N16: 3334 | O16: 3332 | P16: 3332 | Q16: 3332 | R16: 3332 | U16: 3297 | V16: 3335 | W16: IND | X16: IND | Y16: IND | AB16: 3297 | AC16: 3297 | AD16: IND | AE16: IND | AF16: IND | AI16: HOL | AJ16: 3297 | AK16: 3332 | AL16: 3332 | AM16: 3332 | AP16: 3332 | AQ16: 3332 | AR16: 3332 | AS16: 3332 | AT16: IND | AW16: 3297 | AX16: 3297 | AY16: 3297 | AZ16: 3332 | BA16: 3332 | BD16: IND | BE16: IND | BF16: IND | BG16: IND | BH16: IND | BK16: 3332 | BL16: 3332 | BM16: 3332 | BN16: 3332 | BO16: IND
A17: 3300 | C17: PTO | D17: PTO | G17: IND | H17: 3332 | I17: 3332 | J17: 3332 | K17: 3332 | N17: 3335 | O17: 3332 | P17: 3332 | Q17: 3332 | R17: 3332 | U17: 3297 | V17: IND | W17: IND | X17: IND | Y17: IND | AB17: 3297 | AC17: 3297 | AD17: IND | AE17: IND | AF17: IND | AI17: HOL | AJ17: 3297 | AK17: 3332 | AL17: 3332 | AM17: 3332 | AP17: 3332 | AQ17: 3332 | AR17: 3332 | AS17: IND | AT17: IND | AW17: 3297 | AX17: 3297 | AY17: 3297 | AZ17: 3332 | BA17: 3332 | BD17: IND | BE17: IND | BF17: IND | BG17: IND | BH17: IND | BK17: 3332 | BL17: 3332 | BM17: 3332 | BN17: 3332 | BO17: IND
A18: 3364 | C18: PTO | D18: PTO | G18: IND | H18: 3332 | I18: 3332 | J18: 3332 | K18: 3332 | N18: 3332 | O18: 3332 | P18: 3332 | Q18: 3332 | R18: 3332 | U18: 3297 | V18: IND | W18: IND | X18: IND | Y18: IND | AB18: 3297 | AC18: 3297 | AD18: IND | AE18: IND | AF18: IND | AI18: HOL | AJ18: 3297 | AK18: 3332 | AL18: 3332 | AM18: 3332 | AP18: 3332 | AQ18: 3332 | AR18: 3332 | AS18: IND | AT18: IND | AW18: 3297 | AX18: 3297 | AY18: 3297 | AZ18: 3332 | BA18: 3332 | BD18: IND | BE18: IND | BF18: IND | BG18: IND | BH18: IND | BK18: 3332 | BL18: 3332 | BM18: 3332 | BN18: 3332 | BO18: IND
A19: 3341 | C19: PTO | D19: PTO | G19: IND | H19: IND | I19: IND | J19: IND | K19: IND | N19: 3332 | O19: 3332 | P19: 3332 | Q19: 3332 | R19: 3332 | U19: 3297 | V19: IND | W19: IND | X19: IND | Y19: IND | AB19: IND | AC19: IND | AD19: IND | AE19: IND | AF19: IND | AI19: HOL | AJ19: 3297 | AK19: 3332 | AL19: 3332 | AM19: 3332 | AP19: 3332 | AQ19: 3332 | AR19: 3332 | AS19: IND | AT19: IND | AW19: 3297 | AX19: 3297 | AY19: 3297 | AZ19: 3332 | BA19: 3332 | BD19: IND | BE19: IND | BF19: IND | BG19: IND | BH19: IND | BK19: 3332 | BL19: 3332 | BM19: 3332 | BN19: 3332 | BO19: IND
A20: 3351 | C20: PTO | D20: PTO | G20: IND | H20: IND | I20: IND | J20: IND | K20: IND | N20: 3332 | O20: 3332 | P20: 3332 | Q20: 3332 | R20: 3332 | U20: 3297 | V20: IND | W20: IND | X20: IND | Y20: IND | AB20: IND | AC20: IND | AD20: IND | AE20: IND | AF20: IND | AI20: HOL | AJ20: 3297 | AK20: 3332 | AL20: 3332 | AM20: 3332 | AP20: 3332 | AQ20: 3332 | AR20: 3332 | AS20: IND | AT20: IND | AW20: 3297 | AX20: 3297 | AY20: 3297 | AZ20: 3332 | BA20: 3332 | BD20: IND | BE20: IND | BF20: IND | BG20: IND | BH20: IND | BK20: 3332 | BL20: 3332 | BM20: 3332 | BN20: 3332 | BO20: IND
A21: 3321 | C21: PTO | D21: PTO | G21: IND | H21: IND | I21: IND | J21: IND | K21: IND | N21: 3332 | O21: 3332 | P21: 3332 | Q21: 3332 | R21: 3332 | U21: 3297 | V21: IND | W21: IND | X21: IND | Y21: IND | AB21: IND | AC21: IND | AD21: IND | AE21: IND | AF21: IND | AI21: HOL | AJ21: 3297 | AK21: 3332 | AL21: 3332 | AM21: 3332 | AP21: 3332 | AQ21: 3332 | AR21: 3332 | AS21: IND | AT21: IND | AW21: 3297 | AX21: 3297 | AY21: 3297 | AZ21: 3332 | BA21: 3332 | BD21: IND | BE21: IND | BF21: IND | BG21: IND | BH21: IND | BK21: 3332 | BL21: 3332 | BM21: 3332 | BN21: IND | BO21: IND
A22: 3297 | C22: PTO | D22: PTO | G22: IND | H22: IND | I22: IND | J22: IND | K22: IND | N22: 3332 | O22: 3332 | P22: 3332 | Q22: 3332 | R22: 3332 | U22: 3297 | V22: IND | W22: IND | X22: IND | Y22: IND | AB22: IND | AC22: IND | AD22: IND | AE22: IND | AF22: IND | AI22: HOL | AJ22: 3297 | AK22: 3332 | AL22: 3332 | AM22: 3332 | AP22: 3332 | AQ22: 3332 | AR22: 3332 | AS22: IND | AT22: IND | AW22: 3297 | AX22: 3297 | AY22: 3297 | AZ22: 3332 | BA22: 3332 | BD22: IND | BE22: IND | BF22: IND | BG22: IND | BH22: IND | BK22: 3332 | BL22: 3332 | BM22: 3332 | BN22: IND | BO22: IND
A23: 3365 | C23: PTO | D23: PTO | G23: IND | H23: IND | I23: IND | J23: IND | K23: IND | N23: 3332 | O23: 3332 | P23: 3332 | Q23: 3332 | R23: 3332 | U23: 3297 | V23: IND | W23: IND | X23: IND | Y23: IND | AB23: IND | AC23: IND | AD23: IND | AE23: IND | AF23: IND | AI23: HOL | AJ23: 3297 | AK23: 3332 | AL23: 3332 | AM23: 3332 | AP23: 3332 | AQ23: 3332 | AR23: 3332 | AS23: IND | AT23: IND | AW23: 3297 | AX23: 3297 | AY23: 3332 | AZ23: 3332 | BA23: 3332 | BD23: IND | BE23: IND | BF23: IND | BG23: IND | BH23: IND | BK23: 3332 | BL23: 3332 | BM23: 3332 | BN23: IND | BO23: IND
C24: PTO | D24: PTO | G24: IND | H24: IND | I24: IND | J24: IND | K24: IND | N24: 3332 | O24: 3332 | P24: 3332 | Q24: 3332 | R24: 3332 | U24: 3297 | V24: IND | W24: IND | X24: IND | Y24: IND | AB24: IND | AC24: IND | AD24: IND | AE24: IND | AF24: IND | AI24: HOL | AJ24: 3332 | AK24: 3332 | AL24: 3332 | AM24: 3332 | AP24: 3332 | AQ24: 3332 | AR24: 3332 | AS24: IND | AT24: IND | AW24: 3297 | AX24: 3297 | AY24: 3332 | AZ24: 3332 | BA24: 3332 | BD24: IND | BE24: IND | BF24: IND | BG24: IND | BH24: IND | BK24: 3332 | BL24: 3332 | BM24: 3332 | BN24: IND | BO24: IND
B28: Hilda Mata | C28: PTO | D28: PTO | G28: IND | H28: IND | I28: IND | J28: IND | K28: IND | N28: 3328 | O28: 3363 | P28: IND | Q28: IND | R28: IND | U28: 3328 | V28: 3363 | W28: IND | X28: IND | Y28: IND | AB28: 3328 | AC28: 3336 | AD28: 3363 | AE28: 3363 | AF28: IND | AI28: HOL | AJ28: 3346 | AK28: IND | AL28: IND | AM28: IND | AP28: 3346 | AQ28: 3363 | AR28: IND | AS28: IND | AT28: IND | AW28: 3346 | AX28: IND | AY28: IND | AZ28: IND | BA28: IND | BD28: 3346 | BE28: 3365 | BF28: 3365 | BG28: 3365 | BH28: IND | BK28: 3346 | BL28: 3365 | BM28: 3272 | BN28: IND | BO28: IND
C29: PTO | D29: PTO | G29: IND | H29: IND | I29: IND | J29: IND | K29: IND | N29: 3336 | O29: 3363 | P29: IND | Q29: IND | R29: IND | U29: 3346 | V29: 3363 | W29: IND | X29: IND | Y29: IND | AB29: 3346 | AC29: 3336 | AD29: 3363 | AE29: 3363 | AF29: IND | AI29: HOL | AJ29: 3364 | AK29: IND | AL29: IND | AM29: IND | AP29: 3363 | AQ29: 3363 | AR29: IND | AS29: IND | AT29: IND | AW29: 3346 | AX29: IND | AY29: IND | AZ29: IND | BA29: IND | BD29: 3365 | BE29: 3365 | BF29: 3365 | BG29: IND | BH29: IND | BK29: 3346 | BL29: 3272 | BM29: 3272 | BN29: IND | BO29: IND
C30: PTO | D30: PTO | G30: IND | H30: IND | I30: IND | J30: IND | K30: IND | N30: 3336 | O30: 3363 | P30: IND | Q30: IND | R30: IND | U30: 3363 | V30: 3363 | W30: IND | X30: IND | Y30: IND | AB30: 3336 | AC30: 3336 | AD30: 3363 | AE30: 3363 | AF30: IND | AI30: HOL | AJ30: IND | AK30: IND | AL30: IND | AM30: IND | AP30: 3363 | AQ30: 3363 | AR30: IND | AS30: IND | AT30: IND | AW30: 3346 | AX30: IND | AY30: IND | AZ30: IND | BA30: IND | BD30: 3365 | BE30: 3365 | BF30: 3365 | BG30: IND | BH30: IND | BK30: 3346 | BL30: 3272 | BM30: 3272 | BN30: IND | BO30: IND
C31: PTO | D31: PTO | G31: IND | H31: IND | I31: IND | J31: IND | K31: IND | N31: 3346 | O31: 3363 | P31: IND | Q31: IND | R31: IND | U31: 3363 | V31: 3363 | W31: IND | X31: IND | Y31: IND | AB31: 3336 | AC31: 3336 | AD31: 3363 | AE31: 3363 | AF31: IND | AI31: HOL | AJ31: IND | AK31: IND | AL31: IND | AM31: IND | AP31: 3363 | AQ31: 3363 | AR31: IND | AS31: IND | AT31: IND | AW31: 3363 | AX31: IND | AY31: IND | AZ31: IND | BA31: IND | BD31: 3365 | BE31: 3365 | BF31: 3365 | BG31: IND | BH31: IND | BK31: 3365 | BL31: 3272 | BM31: 3272 | BN31: IND | BO31: IND
C32: PTO | D32: PTO | G32: IND | H32: IND | I32: IND | J32: IND | K32: IND | N32: 3363 | O32: 3363 | P32: IND | Q32: IND | R32: IND | U32: 3363 | V32: 3363 | W32: IND | X32: IND | Y32: IND | AB32: 3336 | AC32: 3336 | AD32: 3363 | AE32: 3363 | AF32: IND | AI32: HOL | AJ32: IND | AK32: IND | AL32: IND | AM32: IND | AP32: 3363 | AQ32: 3363 | AR32: IND | AS32: IND | AT32: IND | AW32: 3363 | AX32: IND | AY32: IND | AZ32: IND | BA32: IND | BD32: 3365 | BE32: 3365 | BF32: 3365 | BG32: IND | BH32: IND | BK32: 3365 | BL32: 3272 | BM32: 3272 | BN32: IND | BO32: IND
C33: PTO | D33: PTO | G33: IND | H33: IND | I33: IND | J33: IND | K33: IND | N33: 3363 | O33: 3363 | P33: IND | Q33: IND | R33: IND | U33: 3363 | V33: 3363 | W33: IND | X33: IND | Y33: IND | AB33: 3336 | AC33: 3336 | AD33: 3363 | AE33: 3363 | AF33: IND | AI33: HOL | AJ33: IND | AK33: IND | AL33: IND | AM33: IND | AP33: 3363 | AQ33: 3363 | AR33: IND | AS33: IND | AT33: IND | AW33: IND | AX33: IND | AY33: IND | AZ33: IND | BA33: IND | BD33: 3365 | BE33: 3365 | BF33: 3365 | BG33: IND | BH33: IND | BK33: 3365 | BL33: 3272 | BM33: 3272 | BN33: IND | BO33: IND
C34: PTO | D34: PTO | G34: IND | H34: IND | I34: IND | J34: IND | K34: IND | N34: 3363 | O34: 3363 | P34: IND | Q34: IND | R34: IND | U34: 3363 | V34: 3363 | W34: IND | X34: IND | Y34: IND | AB34: 3336 | AC34: 3336 | AD34: 3363 | AE34: IND | AF34: IND | AI34: HOL | AJ34: IND | AK34: IND | AL34: IND | AM34: IND | AP34: 3363 | AQ34: 3363 | AR34: IND | AS34: IND | AT34: IND | AW34: IND | AX34: IND | AY34: IND | AZ34: IND | BA34: IND | BD34: 3365 | BE34: 3365 | BF34: 3365 | BG34: IND | BH34: IND | BK34: 3365 | BL34: 3272 | BM34: 3272 | BN34: IND | BO34: IND
C35: PTO | D35: PTO | G35: IND | H35: IND | I35: IND | J35: IND | K35: IND | N35: 3363 | O35: 3363 | P35: IND | Q35: IND | R35: IND | U35: 3363 | V35: 3363 | W35: IND | X35: IND | Y35: IND | AB35: 3336 | AC35: 3336 | AD35: 3363 | AE35: IND | AF35: IND | AI35: HOL | AJ35: IND | AK35: IND | AL35: IND | AM35: IND | AP35: 3363 | AQ35: IND | AR35: IND | AS35: IND | AT35: IND | AW35: IND | AX35: IND | AY35: IND | AZ35: IND | BA35: IND | BD35: 3365 | BE35: 3365 | BF35: 3365 | BG35: IND | BH35: IND | BK35: 3365 | BL35: 3272 | BM35: 3272 | BN35: IND | BO35: IND
C36: PTO | D36: PTO | G36: IND | H36: IND | I36: IND | J36: IND | K36: IND | N36: 3363 | O36: 3363 | P36: IND | Q36: IND | R36: IND | U36: 3363 | V36: IND | W36: IND | X36: IND | Y36: IND | AB36: 3336 | AC36: 3336 | AD36: 3363 | AE36: IND | AF36: IND | AI36: HOL | AJ36: IND | AK36: IND | AL36: IND | AM36: IND | AP36: 3363 | AQ36: IND | AR36: IND | AS36: IND | AT36: IND | AW36: IND | AX36: IND | AY36: IND | AZ36: IND | BA36: IND | BD36: 3365 | BE36: 3365 | BF36: 3365 | BG36: IND | BH36: IND | BK36: 3365 | BL36: 3272 | BM36: 3272 | BN36: IND | BO36: IND
B40: Adrian C | C40: PTO | D40: PTO | N40: PTO | O40: PTO | P40: PTO | Q40: MNG | R40: MNG | U40: MNG | V40: MNG | W40: MNG | X40: MNG | Y40: MNG | AB40: 3364 | AC40: 3364 | AD40: 3364 | AE40: 3297 | AF40: MNG | AI40: HOL | AJ40: 3364 | AK40: 3364 | AL40: 3364 | AM40: 3297 | AP40: IND | AQ40: IND | AR40: IND | AS40: IND | AT40: IND | AW40: IND | AX40: IND | AY40: IND | AZ40: IND | BA40: IND | BD40: IND | BE40: IND | BF40: IND | BG40: 3297 | BH40: 3332 | BK40: IND | BL40: IND | BM40: IND | BN40: IND | BO40: IND
C41: PTO | D41: PTO | N41: PTO | O41: PTO | P41: PTO | Q41: MNG | R41: MNG | U41: MNG | V41: MNG | W41: MNG | X41: MNG | Y41: MNG | AB41: 3364 | AC41: 3364 | AD41: 3364 | AE41: 3297 | AF41: MNG | AI41: HOL | AJ41: 3364 | AK41: 3364 | AL41: 3364 | AM41: 3297 | AP41: IND | AQ41: IND | AR41: IND | AS41: IND | AT41: IND | AW41: IND | AX41: IND | AY41: IND | AZ41: IND | BA41: IND | BD41: IND | BE41: IND | BF41: IND | BG41: 3297 | BH41: 3332 | BK41: IND | BL41: IND | BM41: IND | BN41: IND | BO41: IND
C42: PTO | D42: PTO | N42: PTO | O42: PTO | P42: PTO | Q42: 3364 | R42: 3364 | U42: MNG | V42: MNG | W42: MNG | X42: MNG | Y42: MNG | AB42: 3364 | AC42: 3364 | AD42: 3364 | AE42: IND | AF42: IND | AI42: HOL | AJ42: 3364 | AK42: 3364 | AL42: 3364 | AM42: 3364 | AP42: IND | AQ42: IND | AR42: IND | AS42: IND | AT42: IND | AW42: IND | AX42: IND | AY42: IND | AZ42: IND | BA42: IND | BD42: IND | BE42: IND | BF42: IND | BG42: IND | BH42: IND | BK42: IND | BL42: IND | BM42: IND | BN42: IND | BO42: IND
C43: PTO | D43: PTO | N43: PTO | O43: PTO | P43: PTO | Q43: 3364 | R43: 3364 | U43: 3364 | V43: 3364 | W43: 3364 | X43: IND | Y43: IND | AB43: 3364 | AC43: 3364 | AD43: 3364 | AE43: IND | AF43: IND | AI43: HOL | AJ43: 3364 | AK43: 3364 | AL43: 3364 | AM43: 3364 | AP43: IND | AQ43: IND | AR43: IND | AS43: IND | AT43: IND | AW43: IND | AX43: IND | AY43: IND | AZ43: IND | BA43: IND | BD43: IND | BE43: IND | BF43: IND | BG43: IND | BH43: IND | BK43: IND | BL43: IND | BM43: IND | BN43: IND | BO43: IND
C44: PTO | D44: PTO | N44: PTO | O44: PTO | P44: PTO | Q44: 3364 | R44: 3364 | U44: 3364 | V44: 3364 | W44: 3364 | X44: IND | Y44: IND | AB44: 3364 | AC44: 3364 | AD44: 3364 | AE44: IND | AF44: IND | AI44: HOL | AJ44: 3364 | AK44: 3364 | AL44: 3364 | AM44: 3364 | AP44: IND | AQ44: IND | AR44: IND | AS44: IND | AT44: IND | AW44: IND | AX44: IND | AY44: IND | AZ44: IND | BA44: IND | BD44: IND | BE44: IND | BF44: IND | BG44: IND | BH44: IND | BK44: IND | BL44: IND | BM44: IND | BN44: IND | BO44: IND
C45: PTO | D45: PTO | N45: PTO | O45: PTO | P45: PTO | Q45: 3364 | R45: 3364 | U45: 3364 | V45: 3364 | W45: 3364 | X45: IND | Y45: IND | AB45: 3364 | AC45: 3364 | AD45: 3364 | AE45: IND | AF45: IND | AI45: HOL | AJ45: 3364 | AK45: 3364 | AL45: 3364 | AM45: IND | AP45: IND | AQ45: IND | AR45: IND | AS45: IND | AT45: IND | AW45: IND | AX45: IND | AY45: IND | AZ45: IND | BA45: IND | BD45: IND | BE45: IND | BF45: IND | BG45: IND | BH45: IND | BK45: IND | BL45: IND | BM45: IND | BN45: IND | BO45: IND
C46: PTO | D46: PTO | N46: PTO | O46: PTO | P46: PTO | Q46: 3364 | R46: 3364 | U46: 3364 | V46: 3364 | W46: 3364 | X46: IND | Y46: IND | AB46: 3364 | AC46: 3364 | AD46: 3364 | AE46: IND | AF46: IND | AI46: HOL | AJ46: 3364 | AK46: 3364 | AL46: 3364 | AM46: IND | AP46: IND | AQ46: IND | AR46: IND | AS46: IND | AT46: IND | AW46: IND | AX46: IND | AY46: IND | AZ46: IND | BA46: IND | BD46: IND | BE46: IND | BF46: IND | BG46: IND | BH46: IND | BK46: IND | BL46: IND | BM46: IND | BN46: IND | BO46: IND
C47: PTO | D47: PTO | N47: PTO | O47: PTO | P47: PTO | Q47: 3364 | R47: 3364 | U47: 3364 | V47: 3364 | W47: 3364 | X47: 3364 | Y47: IND | AB47: 3364 | AC47: 3364 | AD47: 3364 | AE47: IND | AF47: IND | AI47: HOL | AJ47: 3364 | AK47: 3364 | AL47: 3364 | AM47: IND | AP47: IND | AQ47: IND | AR47: IND | AS47: IND | AT47: IND | AW47: IND | AX47: IND | AY47: IND | AZ47: IND | BA47: IND | BD47: IND | BE47: IND | BF47: IND | BG47: IND | BH47: IND | BK47: IND | BL47: IND | BM47: IND | BN47: IND | BO47: IND
C48: PTO | D48: PTO | N48: PTO | O48: PTO | P48: PTO | Q48: 3364 | R48: 3364 | U48: 3364 | V48: 3364 | W48: 3364 | X48: 3364 | Y48: IND | AB48: 3364 | AC48: 3364 | AD48: 3364 | AE48: IND | AF48: IND | AI48: HOL | AJ48: 3364 | AK48: 3364 | AL48: 3364 | AM48: IND | AP48: IND | AQ48: IND | AR48: IND | AS48: IND | AT48: IND | AW48: IND | AX48: IND | AY48: IND | AZ48: IND | BA48: IND | BD48: IND | BE48: IND | BF48: IND | BG48: IND | BH48: IND | BK48: IND | BL48: IND | BM48: IND | BN48: IND | BO48: IND

Sheet Database
A1: LOCATION | B1: STATUS | C1: Customer | D1: DESCRIPTION | E1: Project name: | F1: Project No | G1: JOB | H1: Budget CS | I1: Change Orders Budget | J1: Budget | K1: Labor Spent | L1: Labor Spend on Design errors | M1: Labor Spent Customer changes | N1: % of completion | O1: Weighted advance | P1: Labor Rate from CS | Q1: Budget vs Rate USD | R1: Spent Budget vs Rate USD | S1: Labor Spent % | T1: Sell price | U1: Sell price Additionals | V1: Additionals cost | W1: Elect Mat Budget USD | X1: Elect Mt Used USD | Y1: Elect Mat Used on Design errors | Z1: Elect Mat Used on Customer changes | AA1: COST | AB1: Ext Budget | AC1: Budget Total USD | AD1: Station GP CostSheet | AE1: Project GP Summary | AF1: Station GP Calc | AG1: Initial Date | AH1: Read info | AI1: Read info Status | AJ1: Read Info Progress | AK1: Read Info Contribution | AL1: Read Info Est hrs | AM1: Long lead items | AN1: Long lead items Status | AO1: Long lead items Progress | AP1: Long lead items Contribution | AQ1: Long lead items Est hrs | AR1: Long lead items Target Date | AS1: Long lead items Real Date | AT1: Switch Layout | AU1: Switch Layout Status | AV1: Switch Layout Progress | AW1: Switch Layout Contribution | AX1: Switch Layout Est hrs | AY1: Switch Layout Target Date | AZ1: Switch Layout Real Date | BA1: Create project | BB1: Create porject Status | BC1: Create porject Progress | BD1: Create project Contribution | BE1: Create project Est hrs | BF1: Communication section | BG1: Communication section Status | BH1: Communication section Progress | BI1: Communication section Contribution | BJ1: Communication section Est hrs | BK1: Power Section | BL1: Power Section Status | BM1: Power Section Progress | BN1: Power Section Contribution | BO1: Power Section Est hrs | BP1: Control Section | BQ1: Control Section Status | BR1: Control Section Progress | BS1: Control Section Contribution | BT1: Control Section Est hrs | BU1: Special components | BV1: Special components Status | BW1: Special components Progress | BX1: Special components Contribution | BY1: Special components Est hrs | BZ1: Pneumatic | CA1: Pneumatic Status | CB1: Pneumatic Progress | CC1: Pneumatic Contribution | CD1: Pneumatic Est hrs | CE1: Enclosure | CF1: Eclosure Status | CG1: Eclosure Progress | CH1: Eclosure Contribution | CI1: Eclosure Est hrs | CJ1: Reports | CK1: Reports Status | CL1: Reports Progress | CM1: Reports Contribution | CN1: Reports Est hrs | CO1: Design | CP1: Design Progress | CQ1: Design Contribution | CR1: Design Est hrs | CS1: Desing hrs used | CT1: Design hrs remaining | CU1: Revision | CV1: Revision Status | CW1: Revision Progress | CX1: Revision Contribution | CY1: Revision Est hrs | CZ1: Revision Date | DA1: Revision Real Date | DB1: Costumer Aprvl | DC1: Costumer Aprvl Status | DD1: Costumer Aprvl Progress | DE1: Costumer Aprvl Contribution | DF1: Costumer Aprvl Est hrs | DG1: Costumer Aprvl Date | DH1: Costumer Aprvl Real Date | DI1: Meetings | DJ1: Meetings Status | DK1: Meetings Progress | DL1: Meetings Contribution | DM1: Meetings Est hrs | DN1: Purchasing release | DO1: Purchasing release Status | DP1: Purchasing release Progress | DQ1: Purchasing release Contribution | DR1: Purchasing release Est hrs | DS1: Purchasing release Date | DT1: Purchasing release Real Date | DU1: Handoffs | DV1: Hand offs/Meetings Status | DW1: Hand offs/Meetings Progress | DX1: Hand offs/Meetings Contribution | DY1: Hand offs/Meetings Est hrs | DZ1: Hand offs/Meetings Date | EA1: Hand offs/Meetings Real Date | EB1: Support | EC1: Support Status | ED1: Support Progress | EE1: Support Contribution | EF1: Support Est hrs | EG1: Support Date | EH1: Support Real Date | EI1: Documentation | EJ1: Documentation Status | EK1: Documentation Progress | EL1: Documentation Contribution | EM1: Documentation Est hrs | EN1: Documentation Date | EO1: Documentation Real Date | EP1: Redlines | EQ1: Redlines Status | ER1: Redlines Progress | ES1: Redlines Contribution | ET1: Redlines Est hrs | EU1: Hrs to Finish | EV1: Sr. Designer | EW1: Responsible | EX1: Comments
A2: MX | B2: Close | C2: OP Mobility | D2: STA A Font Assembly Conveyor Line | E2: Font Assembly Conveyor Line | F2: 3300 | G2: 3300 | H2: 180 | J2: =BaseDeDatos[[#This Row],[Budget CS]]+BaseDeDatos[[#This Row],[Change Orders Budget]] -> 180 | K2: =IFERROR(VLOOKUP(G2, DATA!H:I, 2, FALSE), 0)+BaseDeDatos[[#This Row],[Labor Spend on Design errors]]+BaseDeDatos[[#This Row],[Labor Spent Customer changes]] -> 284.5 | N2: =AK2+AP2+AW2+CQ2+CX2+DE2+DL2+DQ2+DX2+EE2+EL2+ES2 -> 1 | O2: =J2*S2 -> 284.5 | P2: 29.7 | Q2: =BaseDeDatos[[#This Row],[Budget]]*BaseDeDatos[[#This Row],[Labor Rate from CS]] -> 5346 | R2: =BaseDeDatos[[#This Row],[Labor Spent]]*BaseDeDatos[[#This Row],[Labor Rate from CS]] -> 8449.65 | S2: =K2/J2 -> 1.5805556 | T2: 496097 | U2: 48903 | V2: 42280.98 | W2: 122365.88 | X2: 122365.88 | AA2: 404454.78 | AB2: =AA2-X2-Q2 -> 276742.9 | AC2: =SUM(AB2,X2,R2,BaseDeDatos[[#This Row],[Additionals cost]]) -> 449839.41 | AD2: 0.1847 | AE2: 0.1821 | AF2: =(T2-SUM(X2,AB2,R2))/T2 -> 0.17847028 | AH2: Finished | AI2: =VLOOKUP(AH2,DATA!$B$13:$C$19,2,0) -> 100 | AJ2: =VLOOKUP($AH$1,DATA!$B$24:$C$45,2,0) -> 0.05 | AK2: =BaseDeDatos[[#This Row],[Read info Status]]*(AJ2)/100 -> 0.05 | AL2: =AJ2*$J2 -> 9 | AM2: Finished | AN2: =VLOOKUP(AM2,DATA!$B$13:$C$19,2,0) -> 100 | AO2: =VLOOKUP($AM$1,DATA!$B$24:$C$45,2,0) -> 0.05 | AP2: =AN2*AO2/100 -> 0.05 | AQ2: =AO2*$J2 -> 9 | AT2: Finished | AU2: =VLOOKUP(AT2,DATA!$B$13:$C$19,2,0) -> 100 | AV2: =VLOOKUP($AT$1,DATA!$B$24:$C$45,2,0) -> 0.01 | AW2: =AU2*AV2/100 -> 0.01 | AX2: =AV2*$J2 -> 1.8 | BA2: Finished | BB2: =VLOOKUP(BA2,DATA!$B$13:$C$19,2,0) -> 100 | BC2: =VLOOKUP($BA$1,DATA!$B$24:$C$45,2,0) -> 0.01 | BD2: =BB2*BC2/100 -> 0.01 | BE2: =BC2*$J2 -> 1.8 | BF2: Finished | BG2: =VLOOKUP(BF2,DATA!$B$13:$C$19,2,0) -> 100 | BH2: =VLOOKUP($BF$1,DATA!$B$24:$C$45,2,0) -> 0.08 | BI2: =BG2*BH2/100 -> 0.08 | BJ2: =BH2*$J2 -> 14.4 | BK2: Finished | BL2: =VLOOKUP(BK2,DATA!$B$13:$C$19,2,0) -> 100 | BM2: =VLOOKUP($BK$1,DATA!$B$24:$C$45,2,0) -> 0.18 | BN2: =BL2*BM2/100 -> 0.18 | BO2: =BM2*$J2 -> 32.4 | BP2: Finished | BQ2: =VLOOKUP(BP2,DATA!$B$13:$C$19,2,0) -> 100 | BR2: =VLOOKUP($BP$1,DATA!$B$24:$C$45,2,0) -> 0.28 | BS2: =BQ2*BR2/100 -> 0.28 | BT2: =BR2*$J2 -> 50.4 | BU2: Finished | BV2: =VLOOKUP(BU2,DATA!$B$13:$C$19,2,0) -> 100 | BW2: =VLOOKUP($BU$1,DATA!$B$24:$C$45,2,0) -> 0.15 | BX2: =BV2*BW2/100 -> 0.15 | BY2: =BW2*$J2 -> 27 | BZ2: Finished | CA2: =VLOOKUP(BZ2,DATA!$B$13:$C$19,2,0) -> 100 | CB2: =VLOOKUP($BZ$1,DATA!$B$24:$C$45,2,0) -> 0.16 | CC2: =CA2*CB2/100 -> 0.16 | CD2: =CB2*$J2 -> 28.8 | CE2: Finished | CF2: =VLOOKUP(CE2,DATA!$B$13:$C$19,2,0) -> 100 | CG2: =VLOOKUP($CE$1,DATA!$B$24:$C$45,2,0) -> 0.13 | CH2: =CF2*CG2/100 -> 0.13 | CI2: =CG2*$J2 -> 23.4 | CJ2: Finished | CK2: =VLOOKUP(CJ2,DATA!$B$13:$C$19,2,0) -> 100 | CL2: =VLOOKUP($CJ$1,DATA!$B$24:$C$45,2,0) -> 0.01 | CM2: =CK2*CL2/100 -> 0.01 | CN2: =CL2*$J2 -> 1.8 | CO2: =CM2+CH2+CC2+BX2+BS2+BN2+BI2+BD2 -> 1 | CP2: =VLOOKUP($CO$1,DATA!$B$24:$C$45,2,0) -> 0.54 | CQ2: =CP2*CO2 -> 0.54 | CR2: =CP2*$J2 -> 97.2 | CS2: =CQ2*$J2 -> 97.2 | CT2: =CR2-CS2 -> 0 | CU2: Finished | CV2: =VLOOKUP(CU2,DATA!$B$13:$C$19,2,0) -> 100 | CW2: =VLOOKUP($CU$1,DATA!$B$24:$C$45,2,0) -> 0.02 | CX2: =CV2*CW2/100 -> 0.02 | CY2: =CW2*$J2 -> 3.6 | DB2: Finished | DC2: =VLOOKUP(DB2,DATA!$B$13:$C$19,2,0) -> 100 | DD2: =VLOOKUP($DB$1,DATA!$B$24:$C$45,2,0) -> 0.01 | DE2: =DC2*DD2/100 -> 0.01 | DF2: =DD2*$J2 -> 1.8 | DI2: Finished | DJ2: =VLOOKUP(DI2,DATA!$B$13:$C$19,2,0) -> 100 | DK2: =VLOOKUP($DI$1,DATA!$B$24:$C$45,2,0) -> 0.03 | DL2: =DJ2*DK2/100 -> 0.03 | DM2: =DK2*$J2 -> 5.4 | DN2: Finished | DO2: =VLOOKUP(DN2,DATA!$B$13:$C$19,2,0) -> 100 | DP2: =VLOOKUP($DN$1,DATA!$B$24:$C$45,2,0) -> 0.07 | DQ2: =DO2*DP2/100 -> 0.07 | DR2: =DP2*$J2 -> 12.6 | DU2: Finished | DV2: =VLOOKUP(DU2,DATA!$B$13:$C$19,2,0) -> 100 | DW2: =VLOOKUP($DU$1,DATA!$B$24:$C$45,2,0) -> 0.04 | DX2: =DV2*DW2/100 -> 0.04 | DY2: =DW2*$J2 -> 7.2 | EB2: Finished | EC2: =VLOOKUP(EB2,DATA!$B$13:$C$19,2,0) -> 100 | ED2: =VLOOKUP($EB$1,DATA!$B$24:$C$45,2,0) -> 0.05 | EE2: =EC2*ED2/100 -> 0.05 | EF2: =ED2*$J2 -> 9 | EI2: Finished | EJ2: =VLOOKUP(EI2,DATA!$B$13:$C$19,2,0) -> 100 | EK2: =VLOOKUP($EI$1,DATA!$B$24:$C$45,2,0) -> 0.1 | EL2: =EJ2*EK2/100 -> 0.1 | EM2: =EK2*$J2 -> 18 | EP2: Finished | EQ2: =VLOOKUP(EP2,DATA!$B$13:$C$19,2,0) -> 100 | ER2: =VLOOKUP($EP$1,DATA!$B$24:$C$45,2,0) -> 0.03 | ES2: =EQ2*ER2/100 -> 0.03 | ET2: =ER2*$J2 -> 5.4 | EU2: =SUM( IF(AH2<>"Finished",AL2,0) + N("READ INFO"), IF(AM2<>"Finished",AQ2,0) + N("LONG LEAD"), IF(AT2<>"Finished",AX2,0) + N("SWITCH LAYOUT"), IF(CJ2<>"Finished",CT2,0) + N("DESIGN"), IF(CU2<>"Finished",CY2,0) + N("REVISION"), IF(DB2<>"Finished",DF2,0) + N("CUST APRVL"), IF(DI2<>"Finished",DM2,0) + N("MEETINGS"), IF(DN2<>"Finished",DR2,0) + N("PURCHASING"), IF(DU2<>"Finished",DY2,0) + N("HANDOFF"), IF(EB2<>"Finished",EF2,0) + N("SUPPORT"), IF(EI2<>"Finished",EM2,0) + N("DOCUMENTATTION"), IF(EP2<>"Finished",ET2,0) + N("REDLINES"), ) -> 0 | EV2: ADRIAN CABELLO | EW2: JUAN ADAME
A3: MI | B3: Follow Up | C3: REHAU | D3: Punch and weld machine | E3: Sonic P&W MX5a Front Grille | F3: 3364 | G3: 3364 | H3: 70 | J3: =BaseDeDatos[[#This Row],[Budget CS]]+BaseDeDatos[[#This Row],[Change Orders Budget]] -> 70 | K3: =IFERROR(VLOOKUP(G3, DATA!H:I, 2, FALSE), 0)+BaseDeDatos[[#This Row],[Labor Spend on Design errors]]+BaseDeDatos[[#This Row],[Labor Spent Customer changes]] -> 68 | N3: =AK3+AP3+AW3+CQ3+CX3+DE3+DL3+DQ3+DX3+EE3+EL3+ES3 -> 0.97 | O3: =J3*S3 -> 68 | P3: 33.43 | Q3: =BaseDeDatos[[#This Row],[Budget]]*BaseDeDatos[[#This Row],[Labor Rate from CS]] -> 2340.1 | R3: =BaseDeDatos[[#This Row],[Labor Spent]]*BaseDeDatos[[#This Row],[Labor Rate from CS]] -> 2273.24 | S3: =K3/J3 -> 0.97142857 | T3: 254842 | W3: 28587.58 | X3: 28587.58 | AA3: 207598.51 | AB3: =AA3-X3-Q3 -> 176670.83 | AC3: =SUM(AB3,X3,R3,BaseDeDatos[[#This Row],[Additionals cost]]) -> 207531.65 | AD3: 0.1854 | AE3: 0.1854 | AF3: =(T3-SUM(X3,AB3,R3))/T3 -> 0.18564581 | AG3: 46009 | AH3: Finished | AI3: =VLOOKUP(AH3,DATA!$B$13:$C$19,2,0) -> 100 | AJ3: =VLOOKUP($AH$1,DATA!$B$24:$C$45,2,0) -> 0.05 | AK3: =BaseDeDatos[[#This Row],[Read info Status]]*(AJ3)/100 -> 0.05 | AL3: =AJ3*$J3 -> 3.5 | AM3: Finished | AN3: =VLOOKUP(AM3,DATA!$B$13:$C$19,2,0) -> 100 | AO3: =VLOOKUP($AM$1,DATA!$B$24:$C$45,2,0) -> 0.05 | AP3: =AN3*AO3/100 -> 0.05 | AQ3: =AO3*$J3 -> 3.5 | AR3: 46034 | AS3: 46034 | AT3: Finished | AU3: =VLOOKUP(AT3,DATA!$B$13:$C$19,2,0) -> 100 | AV3: =VLOOKUP($AT$1,DATA!$B$24:$C$45,2,0) -> 0.01 | AW3: =AU3*AV3/100 -> 0.01 | AX3: =AV3*$J3 -> 0.7 | AY3: 46048 | AZ3: 46051 | BA3: Finished | BB3: =VLOOKUP(BA3,DATA!$B$13:$C$19,2,0) -> 100 | BC3: =VLOOKUP($BA$1,DATA!$B$24:$C$45,2,0) -> 0.01 | BD3: =BB3*BC3/100 -> 0.01 | BE3: =BC3*$J3 -> 0.7 | BF3: Finished | BG3: =VLOOKUP(BF3,DATA!$B$13:$C$19,2,0) -> 100 | BH3: =VLOOKUP($BF$1,DATA!$B$24:$C$45,2,0) -> 0.08 | BI3: =BG3*BH3/100 -> 0.08 | BJ3: =BH3*$J3 -> 5.6 | BK3: Finished | BL3: =VLOOKUP(BK3,DATA!$B$13:$C$19,2,0) -> 100 | BM3: =VLOOKUP($BK$1,DATA!$B$24:$C$45,2,0) -> 0.18 | BN3: =BL3*BM3/100 -> 0.18 | BO3: =BM3*$J3 -> 12.6 | BP3: Finished | BQ3: =VLOOKUP(BP3,DATA!$B$13:$C$19,2,0) -> 100 | BR3: =VLOOKUP($BP$1,DATA!$B$24:$C$45,2,0) -> 0.28 | BS3: =BQ3*BR3/100 -> 0.28 | BT3: =BR3*$J3 -> 19.6 | BU3: Finished | BV3: =VLOOKUP(BU3,DATA!$B$13:$C$19,2,0) -> 100 | BW3: =VLOOKUP($BU$1,DATA!$B$24:$C$45,2,0) -> 0.15 | BX3: =BV3*BW3/100 -> 0.15 | BY3: =BW3*$J3 -> 10.5 | BZ3: Finished | CA3: =VLOOKUP(BZ3,DATA!$B$13:$C$19,2,0) -> 100 | CB3: =VLOOKUP($BZ$1,DATA!$B$24:$C$45,2,0) -> 0.16 | CC3: =CA3*CB3/100 -> 0.16 | CD3: =CB3*$J3 -> 11.2 | CE3: Finished | CF3: =VLOOKUP(CE3,DATA!$B$13:$C$19,2,0) -> 100 | CG3: =VLOOKUP($CE$1,DATA!$B$24:$C$45,2,0) -> 0.13 | CH3: =CF3*CG3/100 -> 0.13 | CI3: =CG3*$J3 -> 9.1 | CJ3: Finished | CK3: =VLOOKUP(CJ3,DATA!$B$13:$C$19,2,0) -> 100 | CL3: =VLOOKUP($CJ$1,DATA!$B$24:$C$45,2,0) -> 0.01 | CM3: =CK3*CL3/100 -> 0.01 | CN3: =CL3*$J3 -> 0.7 | CO3: =CM3+CH3+CC3+BX3+BS3+BN3+BI3+BD3 -> 1 | CP3: =VLOOKUP($CO$1,DATA!$B$24:$C$45,2,0) -> 0.54 | CQ3: =CP3*CO3 -> 0.54 | CR3: =CP3*$J3 -> 37.8 | CS3: =CQ3*$J3 -> 37.8 | CT3: =CR3-CS3 -> 0 | CU3: Finished | CV3: =VLOOKUP(CU3,DATA!$B$13:$C$19,2,0) -> 100 | CW3: =VLOOKUP($CU$1,DATA!$B$24:$C$45,2,0) -> 0.02 | CX3: =CV3*CW3/100 -> 0.02 | CY3: =CW3*$J3 -> 1.4 | DB3: Finished | DC3: =VLOOKUP(DB3,DATA!$B$13:$C$19,2,0) -> 100 | DD3: =VLOOKUP($DB$1,DATA!$B$24:$C$45,2,0) -> 0.01 | DE3: =DC3*DD3/100 -> 0.01 | DF3: =DD3*$J3 -> 0.7 | DI3: Finished | DJ3: =VLOOKUP(DI3,DATA!$B$13:$C$19,2,0) -> 100 | DK3: =VLOOKUP($DI$1,DATA!$B$24:$C$45,2,0) -> 0.03 | DL3: =DJ3*DK3/100 -> 0.03 | DM3: =DK3*$J3 -> 2.1 | DN3: Finished | DO3: =VLOOKUP(DN3,DATA!$B$13:$C$19,2,0) -> 100 | DP3: =VLOOKUP($DN$1,DATA!$B$24:$C$45,2,0) -> 0.07 | DQ3: =DO3*DP3/100 -> 0.07 | DR3: =DP3*$J3 -> 4.9 | DU3: Finished | DV3: =VLOOKUP(DU3,DATA!$B$13:$C$19,2,0) -> 100 | DW3: =VLOOKUP($DU$1,DATA!$B$24:$C$45,2,0) -> 0.04 | DX3: =DV3*DW3/100 -> 0.04 | DY3: =DW3*$J3 -> 2.8 | EB3: Finished | EC3: =VLOOKUP(EB3,DATA!$B$13:$C$19,2,0) -> 100 | ED3: =VLOOKUP($EB$1,DATA!$B$24:$C$45,2,0) -> 0.05 | EE3: =EC3*ED3/100 -> 0.05 | EF3: =ED3*$J3 -> 3.5 | EI3: Finished | EJ3: =VLOOKUP(EI3,DATA!$B$13:$C$19,2,0) -> 100 | EK3: =VLOOKUP($EI$1,DATA!$B$24:$C$45,2,0) -> 0.1 | EL3: =EJ3*EK3/100 -> 0.1 | EM3: =EK3*$J3 -> 7 | EP3: Not started | EQ3: =VLOOKUP(EP3,DATA!$B$13:$C$19,2,0) -> 0 | ER3: =VLOOKUP($EP$1,DATA!$B$24:$C$45,2,0) -> 0.03 | ES3: =EQ3*ER3/100 -> 0 | ET3: =ER3*$J3 -> 2.1 | EU3: =SUM( IF(AH3<>"Finished",AL3,0) + N("READ INFO"), IF(AM3<>"Finished",AQ3,0) + N("LONG LEAD"), IF(AT3<>"Finished",AX3,0) + N("SWITCH LAYOUT"), IF(CJ3<>"Finished",CT3,0) + N("DESIGN"), IF(CU3<>"Finished",CY3,0) + N("REVISION"), IF(DB3<>"Finished",DF3,0) + N("CUST APRVL"), IF(DI3<>"Finished",DM3,0) + N("MEETINGS"), IF(DN3<>"Finished",DR3,0) + N("PURCHASING"), IF(DU3<>"Finished",DY3,0) + N("HANDOFF"), IF(EB3<>"Finished",EF3,0) + N("SUPPORT"), IF(EI3<>"Finished",EM3,0) + N("DOCUMENTATTION"), IF(EP3<>"Finished",ET3,0) + N("REDLINES"), ) -> 2.1 | EV3: JUAN ADAME | EW3: ADRIAN CABELLO
A4: MI | B4: Open | C4: BAXTER | D4: Long Support Standalone Screw Gun Station | E4: Long Support Standalone Screw Gun Station | F4: 3365 | G4: 3365 | H4: 40 | J4: =BaseDeDatos[[#This Row],[Budget CS]]+BaseDeDatos[[#This Row],[Change Orders Budget]] -> 40 | K4: =IFERROR(VLOOKUP(G4, DATA!H:I, 2, FALSE), 0)+BaseDeDatos[[#This Row],[Labor Spend on Design errors]]+BaseDeDatos[[#This Row],[Labor Spent Customer changes]] -> 1 | N4: =AK4+AP4+AW4+CQ4+CX4+DE4+DL4+DQ4+DX4+EE4+EL4+ES4 -> 0 | O4: =J4*S4 -> 1 | P4: 33.43 | Q4: =BaseDeDatos[[#This Row],[Budget]]*BaseDeDatos[[#This Row],[Labor Rate from CS]] -> 1337.2 | R4: =BaseDeDatos[[#This Row],[Labor Spent]]*BaseDeDatos[[#This Row],[Labor Rate from CS]] -> 33.43 | S4: =K4/J4 -> 0.025 | T4: 113384 | W4: 16335 | X4: 16335 | AA4: 91575.64 | AB4: =AA4-X4-Q4 -> 73903.44 | AC4: =SUM(AB4,X4,R4,BaseDeDatos[[#This Row],[Additionals cost]]) -> 90271.87 | AD4: 0.1923 | AF4: =(T4-SUM(X4,AB4,R4))/T4 -> 0.20383943 | AH4: Not started | AI4: =VLOOKUP(AH4,DATA!$B$13:$C$19,2,0) -> 0 | AK4: =BaseDeDatos[[#This Row],[Read info Status]]*(AJ4)/100 -> 0 | AL4: =AJ4*$J4 -> 0 | AM4: Not started | AN4: =VLOOKUP(AM4,DATA!$B$13:$C$19,2,0) -> 0 | AO4: =VLOOKUP($AM$1,DATA!$B$24:$C$45,2,0) -> 0.05 | AP4: =AN4*AO4/100 -> 0 | AQ4: =AO4*$J4 -> 2 | AT4: Not started | AU4: =VLOOKUP(AT4,DATA!$B$13:$C$19,2,0) -> 0 | AV4: =VLOOKUP($AT$1,DATA!$B$24:$C$45,2,0) -> 0.01 | AW4: =AU4*AV4/100 -> 0 | AX4: =AV4*$J4 -> 0.4 | BA4: Not started | BB4: =VLOOKUP(BA4,DATA!$B$13:$C$19,2,0) -> 0 | BC4: =VLOOKUP($BA$1,DATA!$B$24:$C$45,2,0) -> 0.01 | BD4: =BB4*BC4/100 -> 0 | BE4: =BC4*$J4 -> 0.4 | BF4: Not started | BG4: =VLOOKUP(BF4,DATA!$B$13:$C$19,2,0) -> 0 | BH4: =VLOOKUP($BF$1,DATA!$B$24:$C$45,2,0) -> 0.08 | BI4: =BG4*BH4/100 -> 0 | BJ4: =BH4*$J4 -> 3.2 | BK4: Not started | BL4: =VLOOKUP(BK4,DATA!$B$13:$C$19,2,0) -> 0 | BM4: =VLOOKUP($BK$1,DATA!$B$24:$C$45,2,0) -> 0.18 | BN4: =BL4*BM4/100 -> 0 | BO4: =BM4*$J4 -> 7.2 | BP4: Not started | BQ4: =VLOOKUP(BP4,DATA!$B$13:$C$19,2,0) -> 0 | BR4: =VLOOKUP($BP$1,DATA!$B$24:$C$45,2,0) -> 0.28 | BS4: =BQ4*BR4/100 -> 0 | BT4: =BR4*$J4 -> 11.2 | BU4: Not started | BV4: =VLOOKUP(BU4,DATA!$B$13:$C$19,2,0) -> 0 | BW4: =VLOOKUP($BU$1,DATA!$B$24:$C$45,2,0) -> 0.15 | BX4: =BV4*BW4/100 -> 0 | BY4: =BW4*$J4 -> 6 | BZ4: Not started | CA4: =VLOOKUP(BZ4,DATA!$B$13:$C$19,2,0) -> 0 | CB4: =VLOOKUP($BZ$1,DATA!$B$24:$C$45,2,0) -> 0.16 | CC4: =CA4*CB4/100 -> 0 | CD4: =CB4*$J4 -> 6.4 | CE4: Not started | CF4: =VLOOKUP(CE4,DATA!$B$13:$C$19,2,0) -> 0 | CG4: =VLOOKUP($CE$1,DATA!$B$24:$C$45,2,0) -> 0.13 | CH4: =CF4*CG4/100 -> 0 | CI4: =CG4*$J4 -> 5.2 | CJ4: Not started | CK4: =VLOOKUP(CJ4,DATA!$B$13:$C$19,2,0) -> 0 | CL4: =VLOOKUP($CJ$1,DATA!$B$24:$C$45,2,0) -> 0.01 | CM4: =CK4*CL4/100 -> 0 | CN4: =CL4*$J4 -> 0.4 | CO4: =CM4+CH4+CC4+BX4+BS4+BN4+BI4+BD4 -> 0 | CP4: =VLOOKUP($CO$1,DATA!$B$24:$C$45,2,0) -> 0.54 | CQ4: =CP4*CO4 -> 0 | CR4: =CP4*$J4 -> 21.6 | CS4: =CQ4*$J4 -> 0 | CT4: =CR4-CS4 -> 21.6 | CU4: Not started | CV4: =VLOOKUP(CU4,DATA!$B$13:$C$19,2,0) -> 0 | CW4: =VLOOKUP($CU$1,DATA!$B$24:$C$45,2,0) -> 0.02 | CX4: =CV4*CW4/100 -> 0 | CY4: =CW4*$J4 -> 0.8 | DB4: Not started | DC4: =VLOOKUP(DB4,DATA!$B$13:$C$19,2,0) -> 0 | DD4: =VLOOKUP($DB$1,DATA!$B$24:$C$45,2,0) -> 0.01 | DE4: =DC4*DD4/100 -> 0 | DF4: =DD4*$J4 -> 0.4 | DI4: Not started | DJ4: =VLOOKUP(DI4,DATA!$B$13:$C$19,2,0) -> 0 | DK4: =VLOOKUP($DI$1,DATA!$B$24:$C$45,2,0) -> 0.03 | DL4: =DJ4*DK4/100 -> 0 | DM4: =DK4*$J4 -> 1.2 | DN4: Not started | DO4: =VLOOKUP(DN4,DATA!$B$13:$C$19,2,0) -> 0 | DP4: =VLOOKUP($DN$1,DATA!$B$24:$C$45,2,0) -> 0.07 | DQ4: =DO4*DP4/100 -> 0 | DR4: =DP4*$J4 -> 2.8 | DU4: Not started | DV4: =VLOOKUP(DU4,DATA!$B$13:$C$19,2,0) -> 0 | DW4: =VLOOKUP($DU$1,DATA!$B$24:$C$45,2,0) -> 0.04 | DX4: =DV4*DW4/100 -> 0 | DY4: =DW4*$J4 -> 1.6 | EB4: Not started | EC4: =VLOOKUP(EB4,DATA!$B$13:$C$19,2,0) -> 0 | ED4: =VLOOKUP($EB$1,DATA!$B$24:$C$45,2,0) -> 0.05 | EE4: =EC4*ED4/100 -> 0 | EF4: =ED4*$J4 -> 2 | EI4: Not started | EJ4: =VLOOKUP(EI4,DATA!$B$13:$C$19,2,0) -> 0 | EK4: =VLOOKUP($EI$1,DATA!$B$24:$C$45,2,0) -> 0.1 | EL4: =EJ4*EK4/100 -> 0 | EM4: =EK4*$J4 -> 4 | EP4: Not started | EQ4: =VLOOKUP(EP4,DATA!$B$13:$C$19,2,0) -> 0 | ER4: =VLOOKUP($EP$1,DATA!$B$24:$C$45,2,0) -> 0.03 | ES4: =EQ4*ER4/100 -> 0 | ET4: =ER4*$J4 -> 1.2 | EU4: =SUM( IF(AH4<>"Finished",AL4,0) + N("READ INFO"), IF(AM4<>"Finished",AQ4,0) + N("LONG LEAD"), IF(AT4<>"Finished",AX4,0) + N("SWITCH LAYOUT"), IF(CJ4<>"Finished",CT4,0) + N("DESIGN"), IF(CU4<>"Finished",CY4,0) + N("REVISION"), IF(DB4<>"Finished",DF4,0) + N("CUST APRVL"), IF(DI4<>"Finished",DM4,0) + N("MEETINGS"), IF(DN4<>"Finished",DR4,0) + N("PURCHASING"), IF(DU4<>"Finished",DY4,0) + N("HANDOFF"), IF(EB4<>"Finished",EF4,0) + N("SUPPORT"), IF(EI4<>"Finished",EM4,0) + N("DOCUMENTATTION"), IF(EP4<>"Finished",ET4,0) + N("REDLINES"), ) -> 38 | EV4: ADRIAN CABELLO | EW4: HILDA MATA
A5: MI | B5: Close | C5: CEC | D5: Station 5 Automation-Part Gripper | E5: Toyota TMMAL Station 5 Automation | F5: 3366 | G5: 3366 | H5: 24 | J5: =BaseDeDatos[[#This Row],[Budget CS]]+BaseDeDatos[[#This Row],[Change Orders Budget]] -> 24 | K5: =IFERROR(VLOOKUP(G5, DATA!H:I, 2, FALSE), 0)+BaseDeDatos[[#This Row],[Labor Spend on Design errors]]+BaseDeDatos[[#This Row],[Labor Spent Customer changes]] -> 17 | N5: =AK5+AP5+AW5+CQ5+CX5+DE5+DL5+DQ5+DX5+EE5+EL5+ES5 -> 0.8984 | O5: =J5*S5 -> 17 | P5: 33.43 | Q5: =BaseDeDatos[[#This Row],[Budget]]*BaseDeDatos[[#This Row],[Labor Rate from CS]] -> 802.32 | R5: =BaseDeDatos[[#This Row],[Labor Spent]]*BaseDeDatos[[#This Row],[Labor Rate from CS]] -> 568.31 | S5: =K5/J5 -> 0.70833333 | T5: 21035.56 | W5: 2096 | X5: 2096 | AA5: 17200.62 | AB5: =AA5-X5-Q5 -> 14302.3 | AC5: =SUM(AB5,X5,R5,BaseDeDatos[[#This Row],[Additionals cost]]) -> 16966.61 | AD5: 0.1823 | AE5: 0.1823 | AF5: =(T5-SUM(X5,AB5,R5))/T5 -> 0.19343198 | AG5: 46035 | AH5: Finished | AI5: =VLOOKUP(AH5,DATA!$B$13:$C$19,2,0) -> 100 | AK5: =BaseDeDatos[[#This Row],[Read info Status]]*(AJ5)/100 -> 0 | AL5: =AJ5*$J5 -> 0 | AM5: Finished | AN5: =VLOOKUP(AM5,DATA!$B$13:$C$19,2,0) -> 100 | AO5: =VLOOKUP($AM$1,DATA!$B$24:$C$45,2,0) -> 0.05 | AP5: =AN5*AO5/100 -> 0.05 | AQ5: =AO5*$J5 -> 1.2 | AT5: Finished | AU5: =VLOOKUP(AT5,DATA!$B$13:$C$19,2,0) -> 100 | AV5: =VLOOKUP($AT$1,DATA!$B$24:$C$45,2,0) -> 0.01 | AW5: =AU5*AV5/100 -> 0.01 | AX5: =AV5*$J5 -> 0.24 | BA5: Finished | BB5: =VLOOKUP(BA5,DATA!$B$13:$C$19,2,0) -> 100 | BC5: =VLOOKUP($BA$1,DATA!$B$24:$C$45,2,0) -> 0.01 | BD5: =BB5*BC5/100 -> 0.01 | BE5: =BC5*$J5 -> 0.24 | BF5: Finished | BG5: =VLOOKUP(BF5,DATA!$B$13:$C$19,2,0) -> 100 | BH5: =VLOOKUP($BF$1,DATA!$B$24:$C$45,2,0) -> 0.08 | BI5: =BG5*BH5/100 -> 0.08 | BJ5: =BH5*$J5 -> 1.92 | BK5: Finished | BL5: =VLOOKUP(BK5,DATA!$B$13:$C$19,2,0) -> 100 | BM5: =VLOOKUP($BK$1,DATA!$B$24:$C$45,2,0) -> 0.18 | BN5: =BL5*BM5/100 -> 0.18 | BO5: =BM5*$J5 -> 4.32 | BP5: Finished | BQ5: =VLOOKUP(BP5,DATA!$B$13:$C$19,2,0) -> 100 | BR5: =VLOOKUP($BP$1,DATA!$B$24:$C$45,2,0) -> 0.28 | BS5: =BQ5*BR5/100 -> 0.28 | BT5: =BR5*$J5 -> 6.72 | BU5: Finished | BV5: =VLOOKUP(BU5,DATA!$B$13:$C$19,2,0) -> 100 | BW5: =VLOOKUP($BU$1,DATA!$B$24:$C$45,2,0) -> 0.15 | BX5: =BV5*BW5/100 -> 0.15 | BY5: =BW5*$J5 -> 3.6 | BZ5: Almost ready | CA5: =VLOOKUP(BZ5,DATA!$B$13:$C$19,2,0) -> 75 | CB5: =VLOOKUP($BZ$1,DATA!$B$24:$C$45,2,0) -> 0.16 | CC5: =CA5*CB5/100 -> 0.12 | CD5: =CB5*$J5 -> 3.84 | CE5: Finished | CF5: =VLOOKUP(CE5,DATA!$B$13:$C$19,2,0) -> 100 | CG5: =VLOOKUP($CE$1,DATA!$B$24:$C$45,2,0) -> 0.13 | CH5: =CF5*CG5/100 -> 0.13 | CI5: =CG5*$J5 -> 3.12 | CJ5: Finished | CK5: =VLOOKUP(CJ5,DATA!$B$13:$C$19,2,0) -> 100 | CL5: =VLOOKUP($CJ$1,DATA!$B$24:$C$45,2,0) -> 0.01 | CM5: =CK5*CL5/100 -> 0.01 | CN5: =CL5*$J5 -> 0.24 | CO5: =CM5+CH5+CC5+BX5+BS5+BN5+BI5+BD5 -> 0.96 | CP5: =VLOOKUP($CO$1,DATA!$B$24:$C$45,2,0) -> 0.54 | CQ5: =CP5*CO5 -> 0.5184 | CR5: =CP5*$J5 -> 12.96 | CS5: =CQ5*$J5 -> 12.4416 | CT5: =CR5-CS5 -> 0.5184 | CU5: Finished | CV5: =VLOOKUP(CU5,DATA!$B$13:$C$19,2,0) -> 100 | CW5: =VLOOKUP($CU$1,DATA!$B$24:$C$45,2,0) -> 0.02 | CX5: =CV5*CW5/100 -> 0.02 | CY5: =CW5*$J5 -> 0.48 | DB5: Finished | DC5: =VLOOKUP(DB5,DATA!$B$13:$C$19,2,0) -> 100 | DD5: =VLOOKUP($DB$1,DATA!$B$24:$C$45,2,0) -> 0.01 | DE5: =DC5*DD5/100 -> 0.01 | DF5: =DD5*$J5 -> 0.24 | DI5: Finished | DJ5: =VLOOKUP(DI5,DATA!$B$13:$C$19,2,0) -> 100 | DK5: =VLOOKUP($DI$1,DATA!$B$24:$C$45,2,0) -> 0.03 | DL5: =DJ5*DK5/100 -> 0.03 | DM5: =DK5*$J5 -> 0.72 | DN5: Finished | DO5: =VLOOKUP(DN5,DATA!$B$13:$C$19,2,0) -> 100 | DP5: =VLOOKUP($DN$1,DATA!$B$24:$C$45,2,0) -> 0.07 | DQ5: =DO5*DP5/100 -> 0.07 | DR5: =DP5*$J5 -> 1.68 | DU5: Finished | DV5: =VLOOKUP(DU5,DATA!$B$13:$C$19,2,0) -> 100 | DW5: =VLOOKUP($DU$1,DATA!$B$24:$C$45,2,0) -> 0.04 | DX5: =DV5*DW5/100 -> 0.04 | DY5: =DW5*$J5 -> 0.96 | EB5: Finished | EC5: =VLOOKUP(EB5,DATA!$B$13:$C$19,2,0) -> 100 | ED5: =VLOOKUP($EB$1,DATA!$B$24:$C$45,2,0) -> 0.05 | EE5: =EC5*ED5/100 -> 0.05 | EF5: =ED5*$J5 -> 1.2 | EI5: Finished | EJ5: =VLOOKUP(EI5,DATA!$B$13:$C$19,2,0) -> 100 | EK5: =VLOOKUP($EI$1,DATA!$B$24:$C$45,2,0) -> 0.1 | EL5: =EJ5*EK5/100 -> 0.1 | EM5: =EK5*$J5 -> 2.4 | EP5: Not started | EQ5: =VLOOKUP(EP5,DATA!$B$13:$C$19,2,0) -> 0 | ER5: =VLOOKUP($EP$1,DATA!$B$24:$C$45,2,0) -> 0.03 | ES5: =EQ5*ER5/100 -> 0 | ET5: =ER5*$J5 -> 0.72 | EU5: =SUM( IF(AH5<>"Finished",AL5,0) + N("READ INFO"), IF(AM5<>"Finished",AQ5,0) + N("LONG LEAD"), IF(AT5<>"Finished",AX5,0) + N("SWITCH LAYOUT"), IF(CJ5<>"Finished",CT5,0) + N("DESIGN"), IF(CU5<>"Finished",CY5,0) + N("REVISION"), IF(DB5<>"Finished",DF5,0) + N("CUST APRVL"), IF(DI5<>"Finished",DM5,0) + N("MEETINGS"), IF(DN5<>"Finished",DR5,0) + N("PURCHASING"), IF(DU5<>"Finished",DY5,0) + N("HANDOFF"), IF(EB5<>"Finished",EF5,0) + N("SUPPORT"), IF(EI5<>"Finished",EM5,0) + N("DOCUMENTATTION"), IF(EP5<>"Finished",ET5,0) + N("REDLINES"), ) -> 0.72 | EV5: ADRIAN CABELLO | EW5: JUAN ADAME
A6: MX | B6: Follow Up | C6: Inteva | D6: Robotic Welding Cell | E6: Inteva GM L234 Welding Flex Line | F6: 3268 | G6: 3268-A | H6: 300 | J6: =BaseDeDatos[[#This Row],[Budget CS]]+BaseDeDatos[[#This Row],[Change Orders Budget]] -> 300 | K6: =IFERROR(VLOOKUP(G6, DATA!H:I, 2, FALSE), 0)+BaseDeDatos[[#This Row],[Labor Spend on Design errors]]+BaseDeDatos[[#This Row],[Labor Spent Customer changes]] -> 544.5 | N6: =AK6+AP6+AW6+CQ6+CX6+DE6+DL6+DQ6+DX6+EE6+EL6+ES6 -> 1 | O6: =J6*S6 -> 544.5 | P6: 31.45 | Q6: =BaseDeDatos[[#This Row],[Budget]]*BaseDeDatos[[#This Row],[Labor Rate from CS]] -> 9435 | R6: =BaseDeDatos[[#This Row],[Labor Spent]]*BaseDeDatos[[#This Row],[Labor Rate from CS]] -> 17124.525 | S6: =K6/J6 -> 1.815 | T6: 1377200 | U6: 83640 | V6: 68146.28 | W6: 111874.65 | X6: 111874.65 | AA6: 1135731.1 | AB6: =AA6-X6-Q6 -> 1014421.5 | AC6: =SUM(AB6,X6,R6,BaseDeDatos[[#This Row],[Additionals cost]]) -> 1211566.9 | AD6: 0.1753 | AE6: 0.1756 | AF6: =(T6-SUM(X6,AB6,R6))/T6 -> 0.16974975 | AH6: Finished | AI6: =VLOOKUP(AH6,DATA!$B$13:$C$19,2,0) -> 100 | AJ6: =VLOOKUP($AH$1,DATA!$B$24:$C$45,2,0) -> 0.05 | AK6: =BaseDeDatos[[#This Row],[Read info Status]]*(AJ6)/100 -> 0.05 | AL6: =AJ6*$J6 -> 15 | AM6: Finished | AN6: =VLOOKUP(AM6,DATA!$B$13:$C$19,2,0) -> 100 | AO6: =VLOOKUP($AM$1,DATA!$B$24:$C$45,2,0) -> 0.05 | AP6: =AN6*AO6/100 -> 0.05 | AQ6: =AO6*$J6 -> 15 | AT6: Finished | AU6: =VLOOKUP(AT6,DATA!$B$13:$C$19,2,0) -> 100 | AV6: =VLOOKUP($AT$1,DATA!$B$24:$C$45,2,0) -> 0.01 | AW6: =AU6*AV6/100 -> 0.01 | AX6: =AV6*$J6 -> 3 | BA6: Finished | BB6: =VLOOKUP(BA6,DATA!$B$13:$C$19,2,0) -> 100 | BC6: =VLOOKUP($BA$1,DATA!$B$24:$C$45,2,0) -> 0.01 | BD6: =BB6*BC6/100 -> 0.01 | BE6: =BC6*$J6 -> 3 | BF6: Finished | BG6: =VLOOKUP(BF6,DATA!$B$13:$C$19,2,0) -> 100 | BH6: =VLOOKUP($BF$1,DATA!$B$24:$C$45,2,0) -> 0.08 | BI6: =BG6*BH6/100 -> 0.08 | BJ6: =BH6*$J6 -> 24 | BK6: Finished | BL6: =VLOOKUP(BK6,DATA!$B$13:$C$19,2,0) -> 100 | BM6: =VLOOKUP($BK$1,DATA!$B$24:$C$45,2,0) -> 0.18 | BN6: =BL6*BM6/100 -> 0.18 | BO6: =BM6*$J6 -> 54 | BP6: Finished | BQ6: =VLOOKUP(BP6,DATA!$B$13:$C$19,2,0) -> 100 | BR6: =VLOOKUP($BP$1,DATA!$B$24:$C$45,2,0) -> 0.28 | BS6: =BQ6*BR6/100 -> 0.28 | BT6: =BR6*$J6 -> 84 | BU6: Finished | BV6: =VLOOKUP(BU6,DATA!$B$13:$C$19,2,0) -> 100 | BW6: =VLOOKUP($BU$1,DATA!$B$24:$C$45,2,0) -> 0.15 | BX6: =BV6*BW6/100 -> 0.15 | BY6: =BW6*$J6 -> 45 | BZ6: Finished | CA6: =VLOOKUP(BZ6,DATA!$B$13:$C$19,2,0) -> 100 | CB6: =VLOOKUP($BZ$1,DATA!$B$24:$C$45,2,0) -> 0.16 | CC6: =CA6*CB6/100 -> 0.16 | CD6: =CB6*$J6 -> 48 | CE6: Finished | CF6: =VLOOKUP(CE6,DATA!$B$13:$C$19,2,0) -> 100 | CG6: =VLOOKUP($CE$1,DATA!$B$24:$C$45,2,0) -> 0.13 | CH6: =CF6*CG6/100 -> 0.13 | CI6: =CG6*$J6 -> 39 | CJ6: Finished | CK6: =VLOOKUP(CJ6,DATA!$B$13:$C$19,2,0) -> 100 | CL6: =VLOOKUP($CJ$1,DATA!$B$24:$C$45,2,0) -> 0.01 | CM6: =CK6*CL6/100 -> 0.01 | CN6: =CL6*$J6 -> 3 | CO6: =CM6+CH6+CC6+BX6+BS6+BN6+BI6+BD6 -> 1 | CP6: =VLOOKUP($CO$1,DATA!$B$24:$C$45,2,0) -> 0.54 | CQ6: =CP6*CO6 -> 0.54 | CR6: =CP6*$J6 -> 162 | CS6: =CQ6*$J6 -> 162 | CT6: =CR6-CS6 -> 0 | CU6: Finished | CV6: =VLOOKUP(CU6,DATA!$B$13:$C$19,2,0) -> 100 | CW6: =VLOOKUP($CU$1,DATA!$B$24:$C$45,2,0) -> 0.02 | CX6: =CV6*CW6/100 -> 0.02 | CY6: =CW6*$J6 -> 6 | DB6: Finished | DC6: =VLOOKUP(DB6,DATA!$B$13:$C$19,2,0) -> 100 | DD6: =VLOOKUP($DB$1,DATA!$B$24:$C$45,2,0) -> 0.01 | DE6: =DC6*DD6/100 -> 0.01 | DF6: =DD6*$J6 -> 3 | DI6: Finished | DJ6: =VLOOKUP(DI6,DATA!$B$13:$C$19,2,0) -> 100 | DK6: =VLOOKUP($DI$1,DATA!$B$24:$C$45,2,0) -> 0.03 | DL6: =DJ6*DK6/100 -> 0.03 | DM6: =DK6*$J6 -> 9 | DN6: Finished | DO6: =VLOOKUP(DN6,DATA!$B$13:$C$19,2,0) -> 100 | DP6: =VLOOKUP($DN$1,DATA!$B$24:$C$45,2,0) -> 0.07 | DQ6: =DO6*DP6/100 -> 0.07 | DR6: =DP6*$J6 -> 21 | DU6: Finished | DV6: =VLOOKUP(DU6,DATA!$B$13:$C$19,2,0) -> 100 | DW6: =VLOOKUP($DU$1,DATA!$B$24:$C$45,2,0) -> 0.04 | DX6: =DV6*DW6/100 -> 0.04 | DY6: =DW6*$J6 -> 12 | EB6: Finished | EC6: =VLOOKUP(EB6,DATA!$B$13:$C$19,2,0) -> 100 | ED6: =VLOOKUP($EB$1,DATA!$B$24:$C$45,2,0) -> 0.05 | EE6: =EC6*ED6/100 -> 0.05 | EF6: =ED6*$J6 -> 15 | EI6: Finished | EJ6: =VLOOKUP(EI6,DATA!$B$13:$C$19,2,0) -> 100 | EK6: =VLOOKUP($EI$1,DATA!$B$24:$C$45,2,0) -> 0.1 | EL6: =EJ6*EK6/100 -> 0.1 | EM6: =EK6*$J6 -> 30 | EP6: Finished | EQ6: =VLOOKUP(EP6,DATA!$B$13:$C$19,2,0) -> 100 | ER6: =VLOOKUP($EP$1,DATA!$B$24:$C$45,2,0) -> 0.03 | ES6: =EQ6*ER6/100 -> 0.03 | ET6: =ER6*$J6 -> 9 | EU6: =SUM( IF(AH6<>"Finished",AL6,0) + N("READ INFO"), IF(AM6<>"Finished",AQ6,0) + N("LONG LEAD"), IF(AT6<>"Finished",AX6,0) + N("SWITCH LAYOUT"), IF(CJ6<>"Finished",CT6,0) + N("DESIGN"), IF(CU6<>"Finished",CY6,0) + N("REVISION"), IF(DB6<>"Finished",DF6,0) + N("CUST APRVL"), IF(DI6<>"Finished",DM6,0) + N("MEETINGS"), IF(DN6<>"Finished",DR6,0) + N("PURCHASING"), IF(DU6<>"Finished",DY6,0) + N("HANDOFF"), IF(EB6<>"Finished",EF6,0) + N("SUPPORT"), IF(EI6<>"Finished",EM6,0) + N("DOCUMENTATTION"), IF(EP6<>"Finished",ET6,0) + N("REDLINES"), ) -> 0 | EV6: ADRIAN CABELLO | EW6: JUAN ADAME
A7: MX | B7: Follow Up | C7: Inteva | D7: Rework Station | E7: Inteva GM L234 Welding Flex Line | F7: 3268 | G7: 3268-C | H7: 30 | J7: =BaseDeDatos[[#This Row],[Budget CS]]+BaseDeDatos[[#This Row],[Change Orders Budget]] -> 30 | K7: =IFERROR(VLOOKUP(G7, DATA!H:I, 2, FALSE), 0)+BaseDeDatos[[#This Row],[Labor Spend on Design errors]]+BaseDeDatos[[#This Row],[Labor Spent Customer changes]] -> 31.5 | N7: =AK7+AP7+AW7+CQ7+CX7+DE7+DL7+DQ7+DX7+EE7+EL7+ES7 -> 1 | O7: =J7*S7 -> 31.5 | P7: 31.45 | Q7: =BaseDeDatos[[#This Row],[Budget]]*BaseDeDatos[[#This Row],[Labor Rate from CS]] -> 943.5 | R7: =BaseDeDatos[[#This Row],[Labor Spent]]*BaseDeDatos[[#This Row],[Labor Rate from CS]] -> 990.675 | S7: =K7/J7 -> 1.05 | T7: 70125 | U7: 83640 | V7: 68146.28 | W7: 25830.64 | X7: 25830.64 | AA7: 59000.45 | AB7: =AA7-X7-Q7 -> 32226.31 | AC7: =SUM(AB7,X7,R7,BaseDeDatos[[#This Row],[Additionals cost]]) -> 127193.9 | AD7: 0.1586 | AE7: 0.1756 | AF7: =(T7-SUM(X7,AB7,R7))/T7 -> 0.15796613 | AH7: Finished | AI7: =VLOOKUP(AH7,DATA!$B$13:$C$19,2,0) -> 100 | AJ7: =VLOOKUP($AH$1,DATA!$B$24:$C$45,2,0) -> 0.05 | AK7: =BaseDeDatos[[#This Row],[Read info Status]]*(AJ7)/100 -> 0.05 | AL7: =AJ7*$J7 -> 1.5 | AM7: Finished | AN7: =VLOOKUP(AM7,DATA!$B$13:$C$19,2,0) -> 100 | AO7: =VLOOKUP($AM$1,DATA!$B$24:$C$45,2,0) -> 0.05 | AP7: =AN7*AO7/100 -> 0.05 | AQ7: =AO7*$J7 -> 1.5 | AT7: Finished | AU7: =VLOOKUP(AT7,DATA!$B$13:$C$19,2,0) -> 100 | AV7: =VLOOKUP($AT$1,DATA!$B$24:$C$45,2,0) -> 0.01 | AW7: =AU7*AV7/100 -> 0.01 | AX7: =AV7*$J7 -> 0.3 | BA7: Finished | BB7: =VLOOKUP(BA7,DATA!$B$13:$C$19,2,0) -> 100 | BC7: =VLOOKUP($BA$1,DATA!$B$24:$C$45,2,0) -> 0.01 | BD7: =BB7*BC7/100 -> 0.01 | BE7: =BC7*$J7 -> 0.3 | BF7: Finished | BG7: =VLOOKUP(BF7,DATA!$B$13:$C$19,2,0) -> 100 | BH7: =VLOOKUP($BF$1,DATA!$B$24:$C$45,2,0) -> 0.08 | BI7: =BG7*BH7/100 -> 0.08 | BJ7: =BH7*$J7 -> 2.4 | BK7: Finished | BL7: =VLOOKUP(BK7,DATA!$B$13:$C$19,2,0) -> 100 | BM7: =VLOOKUP($BK$1,DATA!$B$24:$C$45,2,0) -> 0.18 | BN7: =BL7*BM7/100 -> 0.18 | BO7: =BM7*$J7 -> 5.4 | BP7: Finished | BQ7: =VLOOKUP(BP7,DATA!$B$13:$C$19,2,0) -> 100 | BR7: =VLOOKUP($BP$1,DATA!$B$24:$C$45,2,0) -> 0.28 | BS7: =BQ7*BR7/100 -> 0.28 | BT7: =BR7*$J7 -> 8.4 | BU7: Finished | BV7: =VLOOKUP(BU7,DATA!$B$13:$C$19,2,0) -> 100 | BW7: =VLOOKUP($BU$1,DATA!$B$24:$C$45,2,0) -> 0.15 | BX7: =BV7*BW7/100 -> 0.15 | BY7: =BW7*$J7 -> 4.5 | BZ7: Finished | CA7: =VLOOKUP(BZ7,DATA!$B$13:$C$19,2,0) -> 100 | CB7: =VLOOKUP($BZ$1,DATA!$B$24:$C$45,2,0) -> 0.16 | CC7: =CA7*CB7/100 -> 0.16 | CD7: =CB7*$J7 -> 4.8 | CE7: Finished | CF7: =VLOOKUP(CE7,DATA!$B$13:$C$19,2,0) -> 100 | CG7: =VLOOKUP($CE$1,DATA!$B$24:$C$45,2,0) -> 0.13 | CH7: =CF7*CG7/100 -> 0.13 | CI7: =CG7*$J7 -> 3.9 | CJ7: Finished | CK7: =VLOOKUP(CJ7,DATA!$B$13:$C$19,2,0) -> 100 | CL7: =VLOOKUP($CJ$1,DATA!$B$24:$C$45,2,0) -> 0.01 | CM7: =CK7*CL7/100 -> 0.01 | CN7: =CL7*$J7 -> 0.3 | CO7: =CM7+CH7+CC7+BX7+BS7+BN7+BI7+BD7 -> 1 | CP7: =VLOOKUP($CO$1,DATA!$B$24:$C$45,2,0) -> 0.54 | CQ7: =CP7*CO7 -> 0.54 | CR7: =CP7*$J7 -> 16.2 | CS7: =CQ7*$J7 -> 16.2 | CT7: =CR7-CS7 -> 0 | CU7: Finished | CV7: =VLOOKUP(CU7,DATA!$B$13:$C$19,2,0) -> 100 | CW7: =VLOOKUP($CU$1,DATA!$B$24:$C$45,2,0) -> 0.02 | CX7: =CV7*CW7/100 -> 0.02 | CY7: =CW7*$J7 -> 0.6 | DB7: Finished | DC7: =VLOOKUP(DB7,DATA!$B$13:$C$19,2,0) -> 100 | DD7: =VLOOKUP($DB$1,DATA!$B$24:$C$45,2,0) -> 0.01 | DE7: =DC7*DD7/100 -> 0.01 | DF7: =DD7*$J7 -> 0.3 | DI7: Finished | DJ7: =VLOOKUP(DI7,DATA!$B$13:$C$19,2,0) -> 100 | DK7: =VLOOKUP($DI$1,DATA!$B$24:$C$45,2,0) -> 0.03 | DL7: =DJ7*DK7/100 -> 0.03 | DM7: =DK7*$J7 -> 0.9 | DN7: Finished | DO7: =VLOOKUP(DN7,DATA!$B$13:$C$19,2,0) -> 100 | DP7: =VLOOKUP($DN$1,DATA!$B$24:$C$45,2,0) -> 0.07 | DQ7: =DO7*DP7/100 -> 0.07 | DR7: =DP7*$J7 -> 2.1 | DU7: Finished | DV7: =VLOOKUP(DU7,DATA!$B$13:$C$19,2,0) -> 100 | DW7: =VLOOKUP($DU$1,DATA!$B$24:$C$45,2,0) -> 0.04 | DX7: =DV7*DW7/100 -> 0.04 | DY7: =DW7*$J7 -> 1.2 | EB7: Finished | EC7: =VLOOKUP(EB7,DATA!$B$13:$C$19,2,0) -> 100 | ED7: =VLOOKUP($EB$1,DATA!$B$24:$C$45,2,0) -> 0.05 | EE7: =EC7*ED7/100 -> 0.05 | EF7: =ED7*$J7 -> 1.5 | EI7: Finished | EJ7: =VLOOKUP(EI7,DATA!$B$13:$C$19,2,0) -> 100 | EK7: =VLOOKUP($EI$1,DATA!$B$24:$C$45,2,0) -> 0.1 | EL7: =EJ7*EK7/100 -> 0.1 | EM7: =EK7*$J7 -> 3 | EP7: Finished | EQ7: =VLOOKUP(EP7,DATA!$B$13:$C$19,2,0) -> 100 | ER7: =VLOOKUP($EP$1,DATA!$B$24:$C$45,2,0) -> 0.03 | ES7: =EQ7*ER7/100 -> 0.03 | ET7: =ER7*$J7 -> 0.9 | EU7: =SUM( IF(AH7<>"Finished",AL7,0) + N("READ INFO"), IF(AM7<>"Finished",AQ7,0) + N("LONG LEAD"), IF(AT7<>"Finished",AX7,0) + N("SWITCH LAYOUT"), IF(CJ7<>"Finished",CT7,0) + N("DESIGN"), IF(CU7<>"Finished",CY7,0) + N("REVISION"), IF(DB7<>"Finished",DF7,0) + N("CUST APRVL"), IF(DI7<>"Finished",DM7,0) + N("MEETINGS"), IF(DN7<>"Finished",DR7,0) + N("PURCHASING"), IF(DU7<>"Finished",DY7,0) + N("HANDOFF"), IF(EB7<>"Finished",EF7,0) + N("SUPPORT"), IF(EI7<>"Finished",EM7,0) + N("DOCUMENTATTION"), IF(EP7<>"Finished",ET7,0) + N("REDLINES"), ) -> 0 | EV7: ADRIAN CABELLO | EW7: JUAN ADAME
A8: MX | B8: Close | C8: OP Mobility | D8: Rocker Panel Assembly Station LH - H50 | F8: 3272 | G8: 3272-A | H8: 104 | J8: =BaseDeDatos[[#This Row],[Budget CS]]+BaseDeDatos[[#This Row],[Change Orders Budget]] -> 104 | K8: =IFERROR(VLOOKUP(G8, DATA!H:I, 2, FALSE), 0)+BaseDeDatos[[#This Row],[Labor Spend on Design errors]]+BaseDeDatos[[#This Row],[Labor Spent Customer changes]] -> 173 | N8: =AK8+AP8+AW8+CQ8+CX8+DE8+DL8+DQ8+DX8+EE8+EL8+ES8 -> 1 | O8: =J8*S8 -> 173 | P8: 31.45 | Q8: =BaseDeDatos[[#This Row],[Budget]]*BaseDeDatos[[#This Row],[Labor Rate from CS]] -> 3270.8 | R8: =BaseDeDatos[[#This Row],[Labor Spent]]*BaseDeDatos[[#This Row],[Labor Rate from CS]] -> 5440.85 | S8: =K8/J8 -> 1.6634615 | T8: 452146 | U8: 37083.33 | V8: 29631.85 | W8: 114791.78 | X8: 114791.78 | AA8: 362409.1 | AB8: =AA8-X8-Q8 -> 244346.52 | AC8: =SUM(AB8,X8,R8,BaseDeDatos[[#This Row],[Additionals cost]]) -> 394211 | AD8: 0.1985 | AE8: 0.1985 | AF8: =(T8-SUM(X8,AB8,R8))/T8 -> 0.19366941 | AH8: Finished | AI8: =VLOOKUP(AH8,DATA!$B$13:$C$19,2,0) -> 100 | AJ8: =VLOOKUP($AH$1,DATA!$B$24:$C$45,2,0) -> 0.05 | AK8: =BaseDeDatos[[#This Row],[Read info Status]]*(AJ8)/100 -> 0.05 | AL8: =AJ8*$J8 -> 5.2 | AM8: Finished | AN8: =VLOOKUP(AM8,DATA!$B$13:$C$19,2,0) -> 100 | AO8: =VLOOKUP($AM$1,DATA!$B$24:$C$45,2,0) -> 0.05 | AP8: =AN8*AO8/100 -> 0.05 | AQ8: =AO8*$J8 -> 5.2 | AT8: Finished | AU8: =VLOOKUP(AT8,DATA!$B$13:$C$19,2,0) -> 100 | AV8: =VLOOKUP($AT$1,DATA!$B$24:$C$45,2,0) -> 0.01 | AW8: =AU8*AV8/100 -> 0.01 | AX8: =AV8*$J8 -> 1.04 | BA8: Finished | BB8: =VLOOKUP(BA8,DATA!$B$13:$C$19,2,0) -> 100 | BC8: =VLOOKUP($BA$1,DATA!$B$24:$C$45,2,0) -> 0.01 | BD8: =BB8*BC8/100 -> 0.01 | BE8: =BC8*$J8 -> 1.04 | BF8: Finished | BG8: =VLOOKUP(BF8,DATA!$B$13:$C$19,2,0) -> 100 | BH8: =VLOOKUP($BF$1,DATA!$B$24:$C$45,2,0) -> 0.08 | BI8: =BG8*BH8/100 -> 0.08 | BJ8: =BH8*$J8 -> 8.32 | BK8: Finished | BL8: =VLOOKUP(BK8,DATA!$B$13:$C$19,2,0) -> 100 | BM8: =VLOOKUP($BK$1,DATA!$B$24:$C$45,2,0) -> 0.18 | BN8: =BL8*BM8/100 -> 0.18 | BO8: =BM8*$J8 -> 18.72 | BP8: Finished | BQ8: =VLOOKUP(BP8,DATA!$B$13:$C$19,2,0) -> 100 | BR8: =VLOOKUP($BP$1,DATA!$B$24:$C$45,2,0) -> 0.28 | BS8: =BQ8*BR8/100 -> 0.28 | BT8: =BR8*$J8 -> 29.12 | BU8: Finished | BV8: =VLOOKUP(BU8,DATA!$B$13:$C$19,2,0) -> 100 | BW8: =VLOOKUP($BU$1,DATA!$B$24:$C$45,2,0) -> 0.15 | BX8: =BV8*BW8/100 -> 0.15 | BY8: =BW8*$J8 -> 15.6 | BZ8: Finished | CA8: =VLOOKUP(BZ8,DATA!$B$13:$C$19,2,0) -> 100 | CB8: =VLOOKUP($BZ$1,DATA!$B$24:$C$45,2,0) -> 0.16 | CC8: =CA8*CB8/100 -> 0.16 | CD8: =CB8*$J8 -> 16.64 | CE8: Finished | CF8: =VLOOKUP(CE8,DATA!$B$13:$C$19,2,0) -> 100 | CG8: =VLOOKUP($CE$1,DATA!$B$24:$C$45,2,0) -> 0.13 | CH8: =CF8*CG8/100 -> 0.13 | CI8: =CG8*$J8 -> 13.52 | CJ8: Finished | CK8: =VLOOKUP(CJ8,DATA!$B$13:$C$19,2,0) -> 100 | CL8: =VLOOKUP($CJ$1,DATA!$B$24:$C$45,2,0) -> 0.01 | CM8: =CK8*CL8/100 -> 0.01 | CN8: =CL8*$J8 -> 1.04 | CO8: =CM8+CH8+CC8+BX8+BS8+BN8+BI8+BD8 -> 1 | CP8: =VLOOKUP($CO$1,DATA!$B$24:$C$45,2,0) -> 0.54 | CQ8: =CP8*CO8 -> 0.54 | CR8: =CP8*$J8 -> 56.16 | CS8: =CQ8*$J8 -> 56.16 | CT8: =CR8-CS8 -> 0 | CU8: Finished | CV8: =VLOOKUP(CU8,DATA!$B$13:$C$19,2,0) -> 100 | CW8: =VLOOKUP($CU$1,DATA!$B$24:$C$45,2,0) -> 0.02 | CX8: =CV8*CW8/100 -> 0.02 | CY8: =CW8*$J8 -> 2.08 | DB8: Finished | DC8: =VLOOKUP(DB8,DATA!$B$13:$C$19,2,0) -> 100 | DD8: =VLOOKUP($DB$1,DATA!$B$24:$C$45,2,0) -> 0.01 | DE8: =DC8*DD8/100 -> 0.01 | DF8: =DD8*$J8 -> 1.04 | DI8: Finished | DJ8: =VLOOKUP(DI8,DATA!$B$13:$C$19,2,0) -> 100 | DK8: =VLOOKUP($DI$1,DATA!$B$24:$C$45,2,0) -> 0.03 | DL8: =DJ8*DK8/100 -> 0.03 | DM8: =DK8*$J8 -> 3.12 | DN8: Finished | DO8: =VLOOKUP(DN8,DATA!$B$13:$C$19,2,0) -> 100 | DP8: =VLOOKUP($DN$1,DATA!$B$24:$C$45,2,0) -> 0.07 | DQ8: =DO8*DP8/100 -> 0.07 | DR8: =DP8*$J8 -> 7.28 | DU8: Finished | DV8: =VLOOKUP(DU8,DATA!$B$13:$C$19,2,0) -> 100 | DW8: =VLOOKUP($DU$1,DATA!$B$24:$C$45,2,0) -> 0.04 | DX8: =DV8*DW8/100 -> 0.04 | DY8: =DW8*$J8 -> 4.16 | EB8: Finished | EC8: =VLOOKUP(EB8,DATA!$B$13:$C$19,2,0) -> 100 | ED8: =VLOOKUP($EB$1,DATA!$B$24:$C$45,2,0) -> 0.05 | EE8: =EC8*ED8/100 -> 0.05 | EF8: =ED8*$J8 -> 5.2 | EI8: Finished | EJ8: =VLOOKUP(EI8,DATA!$B$13:$C$19,2,0) -> 100 | EK8: =VLOOKUP($EI$1,DATA!$B$24:$C$45,2,0) -> 0.1 | EL8: =EJ8*EK8/100 -> 0.1 | EM8: =EK8*$J8 -> 10.4 | EP8: Finished | EQ8: =VLOOKUP(EP8,DATA!$B$13:$C$19,2,0) -> 100 | ER8: =VLOOKUP($EP$1,DATA!$B$24:$C$45,2,0) -> 0.03 | ES8: =EQ8*ER8/100 -> 0.03 | ET8: =ER8*$J8 -> 3.12 | EU8: =SUM( IF(AH8<>"Finished",AL8,0) + N("READ INFO"), IF(AM8<>"Finished",AQ8,0) + N("LONG LEAD"), IF(AT8<>"Finished",AX8,0) + N("SWITCH LAYOUT"), IF(CJ8<>"Finished",CT8,0) + N("DESIGN"), IF(CU8<>"Finished",CY8,0) + N("REVISION"), IF(DB8<>"Finished",DF8,0) + N("CUST APRVL"), IF(DI8<>"Finished",DM8,0) + N("MEETINGS"), IF(DN8<>"Finished",DR8,0) + N("PURCHASING"), IF(DU8<>"Finished",DY8,0) + N("HANDOFF"), IF(EB8<>"Finished",EF8,0) + N("SUPPORT"), IF(EI8<>"Finished",EM8,0) + N("DOCUMENTATTION"), IF(EP8<>"Finished",ET8,0) + N("REDLINES"), ) -> 0 | EV8: ADRIAN CABELLO | EW8: JUAN ADAME
A9: MX | B9: Close | C9: OP Mobility | D9: Rocker Panel Assembly Station RH - H50 | F9: 3272 | G9: 3272-B | H9: 103 | J9: =BaseDeDatos[[#This Row],[Budget CS]]+BaseDeDatos[[#This Row],[Change Orders Budget]] -> 103 | K9: =IFERROR(VLOOKUP(G9, DATA!H:I, 2, FALSE), 0)+BaseDeDatos[[#This Row],[Labor Spend on Design errors]]+BaseDeDatos[[#This Row],[Labor Spent Customer changes]] -> 183 | N9: =AK9+AP9+AW9+CQ9+CX9+DE9+DL9+DQ9+DX9+EE9+EL9+ES9 -> 1 | O9: =J9*S9 -> 183 | P9: 31.45 | Q9: =BaseDeDatos[[#This Row],[Budget]]*BaseDeDatos[[#This Row],[Labor Rate from CS]] -> 3239.35 | R9: =BaseDeDatos[[#This Row],[Labor Spent]]*BaseDeDatos[[#This Row],[Labor Rate from CS]] -> 5755.35 | S9: =K9/J9 -> 1.776699 | T9: 452146 | U9: 37083.33 | V9: 29631.85 | W9: 114791.78 | X9: 114791.78 | AA9: 362409.1 | AB9: =AA9-X9-Q9 -> 244377.97 | AC9: =SUM(AB9,X9,R9,BaseDeDatos[[#This Row],[Additionals cost]]) -> 394556.95 | AD9: 0.1985 | AE9: 0.1985 | AF9: =(T9-SUM(X9,AB9,R9))/T9 -> 0.19290428 | AH9: Finished | AI9: =VLOOKUP(AH9,DATA!$B$13:$C$19,2,0) -> 100 | AJ9: =VLOOKUP($AH$1,DATA!$B$24:$C$45,2,0) -> 0.05 | AK9: =BaseDeDatos[[#This Row],[Read info Status]]*(AJ9)/100 -> 0.05 | AL9: =AJ9*$J9 -> 5.15 | AM9: Finished | AN9: =VLOOKUP(AM9,DATA!$B$13:$C$19,2,0) -> 100 | AO9: =VLOOKUP($AM$1,DATA!$B$24:$C$45,2,0) -> 0.05 | AP9: =AN9*AO9/100 -> 0.05 | AQ9: =AO9*$J9 -> 5.15 | AT9: Finished | AU9: =VLOOKUP(AT9,DATA!$B$13:$C$19,2,0) -> 100 | AV9: =VLOOKUP($AT$1,DATA!$B$24:$C$45,2,0) -> 0.01 | AW9: =AU9*AV9/100 -> 0.01 | AX9: =AV9*$J9 -> 1.03 | BA9: Finished | BB9: =VLOOKUP(BA9,DATA!$B$13:$C$19,2,0) -> 100 | BC9: =VLOOKUP($BA$1,DATA!$B$24:$C$45,2,0) -> 0.01 | BD9: =BB9*BC9/100 -> 0.01 | BE9: =BC9*$J9 -> 1.03 | BF9: Finished | BG9: =VLOOKUP(BF9,DATA!$B$13:$C$19,2,0) -> 100 | BH9: =VLOOKUP($BF$1,DATA!$B$24:$C$45,2,0) -> 0.08 | BI9: =BG9*BH9/100 -> 0.08 | BJ9: =BH9*$J9 -> 8.24 | BK9: Finished | BL9: =VLOOKUP(BK9,DATA!$B$13:$C$19,2,0) -> 100 | BM9: =VLOOKUP($BK$1,DATA!$B$24:$C$45,2,0) -> 0.18 | BN9: =BL9*BM9/100 -> 0.18 | BO9: =BM9*$J9 -> 18.54 | BP9: Finished | BQ9: =VLOOKUP(BP9,DATA!$B$13:$C$19,2,0) -> 100 | BR9: =VLOOKUP($BP$1,DATA!$B$24:$C$45,2,0) -> 0.28 | BS9: =BQ9*BR9/100 -> 0.28 | BT9: =BR9*$J9 -> 28.84 | BU9: Finished | BV9: =VLOOKUP(BU9,DATA!$B$13:$C$19,2,0) -> 100 | BW9: =VLOOKUP($BU$1,DATA!$B$24:$C$45,2,0) -> 0.15 | BX9: =BV9*BW9/100 -> 0.15 | BY9: =BW9*$J9 -> 15.45 | BZ9: Finished | CA9: =VLOOKUP(BZ9,DATA!$B$13:$C$19,2,0) -> 100 | CB9: =VLOOKUP($BZ$1,DATA!$B$24:$C$45,2,0) -> 0.16 | CC9: =CA9*CB9/100 -> 0.16 | CD9: =CB9*$J9 -> 16.48 | CE9: Finished | CF9: =VLOOKUP(CE9,DATA!$B$13:$C$19,2,0) -> 100 | CG9: =VLOOKUP($CE$1,DATA!$B$24:$C$45,2,0) -> 0.13 | CH9: =CF9*CG9/100 -> 0.13 | CI9: =CG9*$J9 -> 13.39 | CJ9: Finished | CK9: =VLOOKUP(CJ9,DATA!$B$13:$C$19,2,0) -> 100 | CL9: =VLOOKUP($CJ$1,DATA!$B$24:$C$45,2,0) -> 0.01 | CM9: =CK9*CL9/100 -> 0.01 | CN9: =CL9*$J9 -> 1.03 | CO9: =CM9+CH9+CC9+BX9+BS9+BN9+BI9+BD9 -> 1 | CP9: =VLOOKUP($CO$1,DATA!$B$24:$C$45,2,0) -> 0.54 | CQ9: =CP9*CO9 -> 0.54 | CR9: =CP9*$J9 -> 55.62 | CS9: =CQ9*$J9 -> 55.62 | CT9: =CR9-CS9 -> 0 | CU9: Finished | CV9: =VLOOKUP(CU9,DATA!$B$13:$C$19,2,0) -> 100 | CW9: =VLOOKUP($CU$1,DATA!$B$24:$C$45,2,0) -> 0.02 | CX9: =CV9*CW9/100 -> 0.02 | CY9: =CW9*$J9 -> 2.06 | DB9: Finished | DC9: =VLOOKUP(DB9,DATA!$B$13:$C$19,2,0) -> 100 | DD9: =VLOOKUP($DB$1,DATA!$B$24:$C$45,2,0) -> 0.01 | DE9: =DC9*DD9/100 -> 0.01 | DF9: =DD9*$J9 -> 1.03 | DI9: Finished | DJ9: =VLOOKUP(DI9,DATA!$B$13:$C$19,2,0) -> 100 | DK9: =VLOOKUP($DI$1,DATA!$B$24:$C$45,2,0) -> 0.03 | DL9: =DJ9*DK9/100 -> 0.03 | DM9: =DK9*$J9 -> 3.09 | DN9: Finished | DO9: =VLOOKUP(DN9,DATA!$B$13:$C$19,2,0) -> 100 | DP9: =VLOOKUP($DN$1,DATA!$B$24:$C$45,2,0) -> 0.07 | DQ9: =DO9*DP9/100 -> 0.07 | DR9: =DP9*$J9 -> 7.21 | DU9: Finished | DV9: =VLOOKUP(DU9,DATA!$B$13:$C$19,2,0) -> 100 | DW9: =VLOOKUP($DU$1,DATA!$B$24:$C$45,2,0) -> 0.04 | DX9: =DV9*DW9/100 -> 0.04 | DY9: =DW9*$J9 -> 4.12 | EB9: Finished | EC9: =VLOOKUP(EB9,DATA!$B$13:$C$19,2,0) -> 100 | ED9: =VLOOKUP($EB$1,DATA!$B$24:$C$45,2,0) -> 0.05 | EE9: =EC9*ED9/100 -> 0.05 | EF9: =ED9*$J9 -> 5.15 | EI9: Finished | EJ9: =VLOOKUP(EI9,DATA!$B$13:$C$19,2,0) -> 100 | EK9: =VLOOKUP($EI$1,DATA!$B$24:$C$45,2,0) -> 0.1 | EL9: =EJ9*EK9/100 -> 0.1 | EM9: =EK9*$J9 -> 10.3 | EP9: Finished | EQ9: =VLOOKUP(EP9,DATA!$B$13:$C$19,2,0) -> 100 | ER9: =VLOOKUP($EP$1,DATA!$B$24:$C$45,2,0) -> 0.03 | ES9: =EQ9*ER9/100 -> 0.03 | ET9: =ER9*$J9 -> 3.09 | EU9: =SUM( IF(AH9<>"Finished",AL9,0) + N("READ INFO"), IF(AM9<>"Finished",AQ9,0) + N("LONG LEAD"), IF(AT9<>"Finished",AX9,0) + N("SWITCH LAYOUT"), IF(CJ9<>"Finished",CT9,0) + N("DESIGN"), IF(CU9<>"Finished",CY9,0) + N("REVISION"), IF(DB9<>"Finished",DF9,0) + N("CUST APRVL"), IF(DI9<>"Finished",DM9,0) + N("MEETINGS"), IF(DN9<>"Finished",DR9,0) + N("PURCHASING"), IF(DU9<>"Finished",DY9,0) + N("HANDOFF"), IF(EB9<>"Finished",EF9,0) + N("SUPPORT"), IF(EI9<>"Finished",EM9,0) + N("DOCUMENTATTION"), IF(EP9<>"Finished",ET9,0) + N("REDLINES"), ) -> 0 | EV9: ADRIAN CABELLO | EW9: JUAN ADAME
A10: MX | B10: Close | C10: OP Mobility | D10: Brackets Assembly Station - H50 | F10: 3272 | G10: 3272-C | H10: 123 | J10: =BaseDeDatos[[#This Row],[Budget CS]]+BaseDeDatos[[#This Row],[Change Orders Budget]] -> 123 | K10: =IFERROR(VLOOKUP(G10, DATA!H:I, 2, FALSE), 0)+BaseDeDatos[[#This Row],[Labor Spend on Design errors]]+BaseDeDatos[[#This Row],[Labor Spent Customer changes]] -> 206 | N10: =AK10+AP10+AW10+CQ10+CX10+DE10+DL10+DQ10+DX10+EE10+EL10+ES10 -> 1 | O10: =J10*S10 -> 206 | P10: 31.45 | Q10: =BaseDeDatos[[#This Row],[Budget]]*BaseDeDatos[[#This Row],[Labor Rate from CS]] -> 3868.35 | R10: =BaseDeDatos[[#This Row],[Labor Spent]]*BaseDeDatos[[#This Row],[Labor Rate from CS]] -> 6478.7 | S10: =K10/J10 -> 1.6747967 | T10: 653494 | U10: 37083.33 | V10: 29631.85 | W10: 101212.59 | X10: 101212.59 | AA10: 523795.55 | AB10: =AA10-X10-Q10 -> 418714.61 | AC10: =SUM(AB10,X10,R10,BaseDeDatos[[#This Row],[Additionals cost]]) -> 556037.75 | AD10: 0.1985 | AE10: 0.1985 | AF10: =(T10-SUM(X10,AB10,R10))/T10 -> 0.19447478 | AH10: Finished | AI10: =VLOOKUP(AH10,DATA!$B$13:$C$19,2,0) -> 100 | AJ10: =VLOOKUP($AH$1,DATA!$B$24:$C$45,2,0) -> 0.05 | AK10: =BaseDeDatos[[#This Row],[Read info Status]]*(AJ10)/100 -> 0.05 | AL10: =AJ10*$J10 -> 6.15 | AM10: Finished | AN10: =VLOOKUP(AM10,DATA!$B$13:$C$19,2,0) -> 100 | AO10: =VLOOKUP($AM$1,DATA!$B$24:$C$45,2,0) -> 0.05 | AP10: =AN10*AO10/100 -> 0.05 | AQ10: =AO10*$J10 -> 6.15 | AT10: Finished | AU10: =VLOOKUP(AT10,DATA!$B$13:$C$19,2,0) -> 100 | AV10: =VLOOKUP($AT$1,DATA!$B$24:$C$45,2,0) -> 0.01 | AW10: =AU10*AV10/100 -> 0.01 | AX10: =AV10*$J10 -> 1.23 | BA10: Finished | BB10: =VLOOKUP(BA10,DATA!$B$13:$C$19,2,0) -> 100 | BC10: =VLOOKUP($BA$1,DATA!$B$24:$C$45,2,0) -> 0.01 | BD10: =BB10*BC10/100 -> 0.01 | BE10: =BC10*$J10 -> 1.23 | BF10: Finished | BG10: =VLOOKUP(BF10,DATA!$B$13:$C$19,2,0) -> 100 | BH10: =VLOOKUP($BF$1,DATA!$B$24:$C$45,2,0) -> 0.08 | BI10: =BG10*BH10/100 -> 0.08 | BJ10: =BH10*$J10 -> 9.84 | BK10: Finished | BL10: =VLOOKUP(BK10,DATA!$B$13:$C$19,2,0) -> 100 | BM10: =VLOOKUP($BK$1,DATA!$B$24:$C$45,2,0) -> 0.18 | BN10: =BL10*BM10/100 -> 0.18 | BO10: =BM10*$J10 -> 22.14 | BP10: Finished | BQ10: =VLOOKUP(BP10,DATA!$B$13:$C$19,2,0) -> 100 | BR10: =VLOOKUP($BP$1,DATA!$B$24:$C$45,2,0) -> 0.28 | BS10: =BQ10*BR10/100 -> 0.28 | BT10: =BR10*$J10 -> 34.44 | BU10: Finished | BV10: =VLOOKUP(BU10,DATA!$B$13:$C$19,2,0) -> 100 | BW10: =VLOOKUP($BU$1,DATA!$B$24:$C$45,2,0) -> 0.15 | BX10: =BV10*BW10/100 -> 0.15 | BY10: =BW10*$J10 -> 18.45 | BZ10: Finished | CA10: =VLOOKUP(BZ10,DATA!$B$13:$C$19,2,0) -> 100 | CB10: =VLOOKUP($BZ$1,DATA!$B$24:$C$45,2,0) -> 0.16 | CC10: =CA10*CB10/100 -> 0.16 | CD10: =CB10*$J10 -> 19.68 | CE10: Finished | CF10: =VLOOKUP(CE10,DATA!$B$13:$C$19,2,0) -> 100 | CG10: =VLOOKUP($CE$1,DATA!$B$24:$C$45,2,0) -> 0.13 | CH10: =CF10*CG10/100 -> 0.13 | CI10: =CG10*$J10 -> 15.99 | CJ10: Finished | CK10: =VLOOKUP(CJ10,DATA!$B$13:$C$19,2,0) -> 100 | CL10: =VLOOKUP($CJ$1,DATA!$B$24:$C$45,2,0) -> 0.01 | CM10: =CK10*CL10/100 -> 0.01 | CN10: =CL10*$J10 -> 1.23 | CO10: =CM10+CH10+CC10+BX10+BS10+BN10+BI10+BD10 -> 1 | CP10: =VLOOKUP($CO$1,DATA!$B$24:$C$45,2,0) -> 0.54 | CQ10: =CP10*CO10 -> 0.54 | CR10: =CP10*$J10 -> 66.42 | CS10: =CQ10*$J10 -> 66.42 | CT10: =CR10-CS10 -> 0 | CU10: Finished | CV10: =VLOOKUP(CU10,DATA!$B$13:$C$19,2,0) -> 100 | CW10: =VLOOKUP($CU$1,DATA!$B$24:$C$45,2,0) -> 0.02 | CX10: =CV10*CW10/100 -> 0.02 | CY10: =CW10*$J10 -> 2.46 | DB10: Finished | DC10: =VLOOKUP(DB10,DATA!$B$13:$C$19,2,0) -> 100 | DD10: =VLOOKUP($DB$1,DATA!$B$24:$C$45,2,0) -> 0.01 | DE10: =DC10*DD10/100 -> 0.01 | DF10: =DD10*$J10 -> 1.23 | DI10: Finished | DJ10: =VLOOKUP(DI10,DATA!$B$13:$C$19,2,0) -> 100 | DK10: =VLOOKUP($DI$1,DATA!$B$24:$C$45,2,0) -> 0.03 | DL10: =DJ10*DK10/100 -> 0.03 | DM10: =DK10*$J10 -> 3.69 | DN10: Finished | DO10: =VLOOKUP(DN10,DATA!$B$13:$C$19,2,0) -> 100 | DP10: =VLOOKUP($DN$1,DATA!$B$24:$C$45,2,0) -> 0.07 | DQ10: =DO10*DP10/100 -> 0.07 | DR10: =DP10*$J10 -> 8.61 | DU10: Finished | DV10: =VLOOKUP(DU10,DATA!$B$13:$C$19,2,0) -> 100 | DW10: =VLOOKUP($DU$1,DATA!$B$24:$C$45,2,0) -> 0.04 | DX10: =DV10*DW10/100 -> 0.04 | DY10: =DW10*$J10 -> 4.92 | EB10: Finished | EC10: =VLOOKUP(EB10,DATA!$B$13:$C$19,2,0) -> 100 | ED10: =VLOOKUP($EB$1,DATA!$B$24:$C$45,2,0) -> 0.05 | EE10: =EC10*ED10/100 -> 0.05 | EF10: =ED10*$J10 -> 6.15 | EI10: Finished | EJ10: =VLOOKUP(EI10,DATA!$B$13:$C$19,2,0) -> 100 | EK10: =VLOOKUP($EI$1,DATA!$B$24:$C$45,2,0) -> 0.1 | EL10: =EJ10*EK10/100 -> 0.1 | EM10: =EK10*$J10 -> 12.3 | EP10: Finished | EQ10: =VLOOKUP(EP10,DATA!$B$13:$C$19,2,0) -> 100 | ER10: =VLOOKUP($EP$1,DATA!$B$24:$C$45,2,0) -> 0.03 | ES10: =EQ10*ER10/100 -> 0.03 | ET10: =ER10*$J10 -> 3.69 | EU10: =SUM( IF(AH10<>"Finished",AL10,0) + N("READ INFO"), IF(AM10<>"Finished",AQ10,0) + N("LONG LEAD"), IF(AT10<>"Finished",AX10,0) + N("SWITCH LAYOUT"), IF(CJ10<>"Finished",CT10,0) + N("DESIGN"), IF(CU10<>"Finished",CY10,0) + N("REVISION"), IF(DB10<>"Finished",DF10,0) + N("CUST APRVL"), IF(DI10<>"Finished",DM10,0) + N("MEETINGS"), IF(DN10<>"Finished",DR10,0) + N("PURCHASING"), IF(DU10<>"Finished",DY10,0) + N("HANDOFF"), IF(EB10<>"Finished",EF10,0) + N("SUPPORT"), IF(EI10<>"Finished",EM10,0) + N("DOCUMENTATTION"), IF(EP10<>"Finished",ET10,0) + N("REDLINES"), ) -> 0 | EV10: ADRIAN CABELLO | EW10: JUAN ADAME
A11: MX | B11: Open | C11: OP Mobility | D11: CO06 - Scan to Pack | E11: G65 & G67 Scan to Pack | F11: 3272-CO06 | G11: 3272-CO06 | H11: 20 | J11: =BaseDeDatos[[#This Row],[Budget CS]]+BaseDeDatos[[#This Row],[Change Orders Budget]] -> 20 | K11: =IFERROR(VLOOKUP(G11, DATA!H:I, 2, FALSE), 0)+BaseDeDatos[[#This Row],[Labor Spend on Design errors]]+BaseDeDatos[[#This Row],[Labor Spent Customer changes]] -> 0 | N11: =AK11+AP11+AW11+CQ11+CX11+DE11+DL11+DQ11+DX11+EE11+EL11+ES11 -> 0 | O11: =J11*S11 -> 0 | P11: 26.73 | Q11: =BaseDeDatos[[#This Row],[Budget]]*BaseDeDatos[[#This Row],[Labor Rate from CS]] -> 534.6 | R11: =BaseDeDatos[[#This Row],[Labor Spent]]*BaseDeDatos[[#This Row],[Labor Rate from CS]] -> 0 | S11: =K11/J11 -> 0 | T11: 111000 | W11: 30648 | X11: 30648 | AA11: 86785.5 | AB11: =AA11-X11-Q11 -> 55602.9 | AC11: =SUM(AB11,X11,R11,BaseDeDatos[[#This Row],[Additionals cost]]) -> 86250.9 | AD11: 0.2181 | AF11: =(T11-SUM(X11,AB11,R11))/T11 -> 0.22296486 | AH11: Not started | AI11: =VLOOKUP(AH11,DATA!$B$13:$C$19,2,0) -> 0 | AK11: =BaseDeDatos[[#This Row],[Read info Status]]*(AJ11)/100 -> 0 | AL11: =AJ11*$J11 -> 0 | AM11: Not started | AN11: =VLOOKUP(AM11,DATA!$B$13:$C$19,2,0) -> 0 | AO11: =VLOOKUP($AM$1,DATA!$B$24:$C$45,2,0) -> 0.05 | AP11: =AN11*AO11/100 -> 0 | AQ11: =AO11*$J11 -> 1 | AT11: Not started | AU11: =VLOOKUP(AT11,DATA!$B$13:$C$19,2,0) -> 0 | AV11: =VLOOKUP($AT$1,DATA!$B$24:$C$45,2,0) -> 0.01 | AW11: =AU11*AV11/100 -> 0 | AX11: =AV11*$J11 -> 0.2 | BA11: Not started | BB11: =VLOOKUP(BA11,DATA!$B$13:$C$19,2,0) -> 0 | BC11: =VLOOKUP($BA$1,DATA!$B$24:$C$45,2,0) -> 0.01 | BD11: =BB11*BC11/100 -> 0 | BE11: =BC11*$J11 -> 0.2 | BF11: Not started | BG11: =VLOOKUP(BF11,DATA!$B$13:$C$19,2,0) -> 0 | BH11: =VLOOKUP($BF$1,DATA!$B$24:$C$45,2,0) -> 0.08 | BI11: =BG11*BH11/100 -> 0 | BJ11: =BH11*$J11 -> 1.6 | BK11: Not started | BL11: =VLOOKUP(BK11,DATA!$B$13:$C$19,2,0) -> 0 | BM11: =VLOOKUP($BK$1,DATA!$B$24:$C$45,2,0) -> 0.18 | BN11: =BL11*BM11/100 -> 0 | BO11: =BM11*$J11 -> 3.6 | BP11: Not started | BQ11: =VLOOKUP(BP11,DATA!$B$13:$C$19,2,0) -> 0 | BR11: =VLOOKUP($BP$1,DATA!$B$24:$C$45,2,0) -> 0.28 | BS11: =BQ11*BR11/100 -> 0 | BT11: =BR11*$J11 -> 5.6 | BU11: Not started | BV11: =VLOOKUP(BU11,DATA!$B$13:$C$19,2,0) -> 0 | BW11: =VLOOKUP($BU$1,DATA!$B$24:$C$45,2,0) -> 0.15 | BX11: =BV11*BW11/100 -> 0 | BY11: =BW11*$J11 -> 3 | BZ11: Not started | CA11: =VLOOKUP(BZ11,DATA!$B$13:$C$19,2,0) -> 0 | CB11: =VLOOKUP($BZ$1,DATA!$B$24:$C$45,2,0) -> 0.16 | CC11: =CA11*CB11/100 -> 0 | CD11: =CB11*$J11 -> 3.2 | CE11: Not started | CF11: =VLOOKUP(CE11,DATA!$B$13:$C$19,2,0) -> 0 | CG11: =VLOOKUP($CE$1,DATA!$B$24:$C$45,2,0) -> 0.13 | CH11: =CF11*CG11/100 -> 0 | CI11: =CG11*$J11 -> 2.6 | CJ11: Not started | CK11: =VLOOKUP(CJ11,DATA!$B$13:$C$19,2,0) -> 0 | CL11: =VLOOKUP($CJ$1,DATA!$B$24:$C$45,2,0) -> 0.01 | CM11: =CK11*CL11/100 -> 0 | CN11: =CL11*$J11 -> 0.2 | CO11: =CM11+CH11+CC11+BX11+BS11+BN11+BI11+BD11 -> 0 | CP11: =VLOOKUP($CO$1,DATA!$B$24:$C$45,2,0) -> 0.54 | CQ11: =CP11*CO11 -> 0 | CR11: =CP11*$J11 -> 10.8 | CS11: =CQ11*$J11 -> 0 | CT11: =CR11-CS11 -> 10.8 | CU11: Not started | CV11: =VLOOKUP(CU11,DATA!$B$13:$C$19,2,0) -> 0 | CW11: =VLOOKUP($CU$1,DATA!$B$24:$C$45,2,0) -> 0.02 | CX11: =CV11*CW11/100 -> 0 | CY11: =CW11*$J11 -> 0.4 | DB11: Not started | DC11: =VLOOKUP(DB11,DATA!$B$13:$C$19,2,0) -> 0 | DD11: =VLOOKUP($DB$1,DATA!$B$24:$C$45,2,0) -> 0.01 | DE11: =DC11*DD11/100 -> 0 | DF11: =DD11*$J11 -> 0.2 | DI11: Not started | DJ11: =VLOOKUP(DI11,DATA!$B$13:$C$19,2,0) -> 0 | DK11: =VLOOKUP($DI$1,DATA!$B$24:$C$45,2,0) -> 0.03 | DL11: =DJ11*DK11/100 -> 0 | DM11: =DK11*$J11 -> 0.6 | DN11: Not started | DO11: =VLOOKUP(DN11,DATA!$B$13:$C$19,2,0) -> 0 | DP11: =VLOOKUP($DN$1,DATA!$B$24:$C$45,2,0) -> 0.07 | DQ11: =DO11*DP11/100 -> 0 | DR11: =DP11*$J11 -> 1.4 | DU11: Not started | DV11: =VLOOKUP(DU11,DATA!$B$13:$C$19,2,0) -> 0 | DW11: =VLOOKUP($DU$1,DATA!$B$24:$C$45,2,0) -> 0.04 | DX11: =DV11*DW11/100 -> 0 | DY11: =DW11*$J11 -> 0.8 | EB11: Not started | EC11: =VLOOKUP(EB11,DATA!$B$13:$C$19,2,0) -> 0 | ED11: =VLOOKUP($EB$1,DATA!$B$24:$C$45,2,0) -> 0.05 | EE11: =EC11*ED11/100 -> 0 | EF11: =ED11*$J11 -> 1 | EI11: Not started | EJ11: =VLOOKUP(EI11,DATA!$B$13:$C$19,2,0) -> 0 | EK11: =VLOOKUP($EI$1,DATA!$B$24:$C$45,2,0) -> 0.1 | EL11: =EJ11*EK11/100 -> 0 | EM11: =EK11*$J11 -> 2 | EP11: Not started | EQ11: =VLOOKUP(EP11,DATA!$B$13:$C$19,2,0) -> 0 | ER11: =VLOOKUP($EP$1,DATA!$B$24:$C$45,2,0) -> 0.03 | ES11: =EQ11*ER11/100 -> 0 | ET11: =ER11*$J11 -> 0.6 | EU11: =SUM( IF(AH11<>"Finished",AL11,0) + N("READ INFO"), IF(AM11<>"Finished",AQ11,0) + N("LONG LEAD"), IF(AT11<>"Finished",AX11,0) + N("SWITCH LAYOUT"), IF(CJ11<>"Finished",CT11,0) + N("DESIGN"), IF(CU11<>"Finished",CY11,0) + N("REVISION"), IF(DB11<>"Finished",DF11,0) + N("CUST APRVL"), IF(DI11<>"Finished",DM11,0) + N("MEETINGS"), IF(DN11<>"Finished",DR11,0) + N("PURCHASING"), IF(DU11<>"Finished",DY11,0) + N("HANDOFF"), IF(EB11<>"Finished",EF11,0) + N("SUPPORT"), IF(EI11<>"Finished",EM11,0) + N("DOCUMENTATTION"), IF(EP11<>"Finished",ET11,0) + N("REDLINES"), ) -> 19
A12: MX | B12: Follow Up | C12: OP Mobility | D12: Rocker Panel Assembly Station LH - H52 | E12: BMW Rockers Assembly Stations | F12: 3272 | G12: 3272-H | H12: 26 | J12: =BaseDeDatos[[#This Row],[Budget CS]]+BaseDeDatos[[#This Row],[Change Orders Budget]] -> 26 | K12: =IFERROR(VLOOKUP(G12, DATA!H:I, 2, FALSE), 0)+BaseDeDatos[[#This Row],[Labor Spend on Design errors]]+BaseDeDatos[[#This Row],[Labor Spent Customer changes]] -> 48 | N12: =AK12+AP12+AW12+CQ12+CX12+DE12+DL12+DQ12+DX12+EE12+EL12+ES12 -> 0.96 | O12: =J12*S12 -> 48 | P12: 31.45 | Q12: =BaseDeDatos[[#This Row],[Budget]]*BaseDeDatos[[#This Row],[Labor Rate from CS]] -> 817.7 | R12: =BaseDeDatos[[#This Row],[Labor Spent]]*BaseDeDatos[[#This Row],[Labor Rate from CS]] -> 1509.6 | S12: =K12/J12 -> 1.8461538 | T12: 431200 | U12: 37083.33 | V12: 29631.85 | W12: 114791.78 | X12: 114791.78 | AA12: 345620.81 | AB12: =AA12-X12-Q12 -> 230011.33 | AC12: =SUM(AB12,X12,R12,BaseDeDatos[[#This Row],[Additionals cost]]) -> 375944.56 | AD12: 0.1985 | AE12: 0.1985 | AF12: =(T12-SUM(X12,AB12,R12))/T12 -> 0.19686292 | AH12: Finished | AI12: =VLOOKUP(AH12,DATA!$B$13:$C$19,2,0) -> 100 | AJ12: =VLOOKUP($AH$1,DATA!$B$24:$C$45,2,0) -> 0.05 | AK12: =BaseDeDatos[[#This Row],[Read info Status]]*(AJ12)/100 -> 0.05 | AL12: =AJ12*$J12 -> 1.3 | AM12: Finished | AN12: =VLOOKUP(AM12,DATA!$B$13:$C$19,2,0) -> 100 | AO12: =VLOOKUP($AM$1,DATA!$B$24:$C$45,2,0) -> 0.05 | AP12: =AN12*AO12/100 -> 0.05 | AQ12: =AO12*$J12 -> 1.3 | AT12: Finished | AU12: =VLOOKUP(AT12,DATA!$B$13:$C$19,2,0) -> 100 | AV12: =VLOOKUP($AT$1,DATA!$B$24:$C$45,2,0) -> 0.01 | AW12: =AU12*AV12/100 -> 0.01 | AX12: =AV12*$J12 -> 0.26 | BA12: Finished | BB12: =VLOOKUP(BA12,DATA!$B$13:$C$19,2,0) -> 100 | BC12: =VLOOKUP($BA$1,DATA!$B$24:$C$45,2,0) -> 0.01 | BD12: =BB12*BC12/100 -> 0.01 | BE12: =BC12*$J12 -> 0.26 | BF12: Finished | BG12: =VLOOKUP(BF12,DATA!$B$13:$C$19,2,0) -> 100 | BH12: =VLOOKUP($BF$1,DATA!$B$24:$C$45,2,0) -> 0.08 | BI12: =BG12*BH12/100 -> 0.08 | BJ12: =BH12*$J12 -> 2.08 | BK12: Finished | BL12: =VLOOKUP(BK12,DATA!$B$13:$C$19,2,0) -> 100 | BM12: =VLOOKUP($BK$1,DATA!$B$24:$C$45,2,0) -> 0.18 | BN12: =BL12*BM12/100 -> 0.18 | BO12: =BM12*$J12 -> 4.68 | BP12: Finished | BQ12: =VLOOKUP(BP12,DATA!$B$13:$C$19,2,0) -> 100 | BR12: =VLOOKUP($BP$1,DATA!$B$24:$C$45,2,0) -> 0.28 | BS12: =BQ12*BR12/100 -> 0.28 | BT12: =BR12*$J12 -> 7.28 | BU12: Finished | BV12: =VLOOKUP(BU12,DATA!$B$13:$C$19,2,0) -> 100 | BW12: =VLOOKUP($BU$1,DATA!$B$24:$C$45,2,0) -> 0.15 | BX12: =BV12*BW12/100 -> 0.15 | BY12: =BW12*$J12 -> 3.9 | BZ12: Finished | CA12: =VLOOKUP(BZ12,DATA!$B$13:$C$19,2,0) -> 100 | CB12: =VLOOKUP($BZ$1,DATA!$B$24:$C$45,2,0) -> 0.16 | CC12: =CA12*CB12/100 -> 0.16 | CD12: =CB12*$J12 -> 4.16 | CE12: Finished | CF12: =VLOOKUP(CE12,DATA!$B$13:$C$19,2,0) -> 100 | CG12: =VLOOKUP($CE$1,DATA!$B$24:$C$45,2,0) -> 0.13 | CH12: =CF12*CG12/100 -> 0.13 | CI12: =CG12*$J12 -> 3.38 | CJ12: Finished | CK12: =VLOOKUP(CJ12,DATA!$B$13:$C$19,2,0) -> 100 | CL12: =VLOOKUP($CJ$1,DATA!$B$24:$C$45,2,0) -> 0.01 | CM12: =CK12*CL12/100 -> 0.01 | CN12: =CL12*$J12 -> 0.26 | CO12: =CM12+CH12+CC12+BX12+BS12+BN12+BI12+BD12 -> 1 | CP12: =VLOOKUP($CO$1,DATA!$B$24:$C$45,2,0) -> 0.54 | CQ12: =CP12*CO12 -> 0.54 | CR12: =CP12*$J12 -> 14.04 | CS12: =CQ12*$J12 -> 14.04 | CT12: =CR12-CS12 -> 0 | CU12: Finished | CV12: =VLOOKUP(CU12,DATA!$B$13:$C$19,2,0) -> 100 | CW12: =VLOOKUP($CU$1,DATA!$B$24:$C$45,2,0) -> 0.02 | CX12: =CV12*CW12/100 -> 0.02 | CY12: =CW12*$J12 -> 0.52 | DB12: Finished | DC12: =VLOOKUP(DB12,DATA!$B$13:$C$19,2,0) -> 100 | DD12: =VLOOKUP($DB$1,DATA!$B$24:$C$45,2,0) -> 0.01 | DE12: =DC12*DD12/100 -> 0.01 | DF12: =DD12*$J12 -> 0.26 | DI12: Finished | DJ12: =VLOOKUP(DI12,DATA!$B$13:$C$19,2,0) -> 100 | DK12: =VLOOKUP($DI$1,DATA!$B$24:$C$45,2,0) -> 0.03 | DL12: =DJ12*DK12/100 -> 0.03 | DM12: =DK12*$J12 -> 0.78 | DN12: Finished | DO12: =VLOOKUP(DN12,DATA!$B$13:$C$19,2,0) -> 100 | DP12: =VLOOKUP($DN$1,DATA!$B$24:$C$45,2,0) -> 0.07 | DQ12: =DO12*DP12/100 -> 0.07 | DR12: =DP12*$J12 -> 1.82 | DU12: Finished | DV12: =VLOOKUP(DU12,DATA!$B$13:$C$19,2,0) -> 100 | DW12: =VLOOKUP($DU$1,DATA!$B$24:$C$45,2,0) -> 0.04 | DX12: =DV12*DW12/100 -> 0.04 | DY12: =DW12*$J12 -> 1.04 | EB12: In process | EC12: =VLOOKUP(EB12,DATA!$B$13:$C$19,2,0) -> 50 | ED12: =VLOOKUP($EB$1,DATA!$B$24:$C$45,2,0) -> 0.05 | EE12: =EC12*ED12/100 -> 0.025 | EF12: =ED12*$J12 -> 1.3 | EI12: Finished | EJ12: =VLOOKUP(EI12,DATA!$B$13:$C$19,2,0) -> 100 | EK12: =VLOOKUP($EI$1,DATA!$B$24:$C$45,2,0) -> 0.1 | EL12: =EJ12*EK12/100 -> 0.1 | EM12: =EK12*$J12 -> 2.6 | EP12: In process | EQ12: =VLOOKUP(EP12,DATA!$B$13:$C$19,2,0) -> 50 | ER12: =VLOOKUP($EP$1,DATA!$B$24:$C$45,2,0) -> 0.03 | ES12: =EQ12*ER12/100 -> 0.015 | ET12: =ER12*$J12 -> 0.78 | EU12: =SUM( IF(AH12<>"Finished",AL12,0) + N("READ INFO"), IF(AM12<>"Finished",AQ12,0) + N("LONG LEAD"), IF(AT12<>"Finished",AX12,0) + N("SWITCH LAYOUT"), IF(CJ12<>"Finished",CT12,0) + N("DESIGN"), IF(CU12<>"Finished",CY12,0) + N("REVISION"), IF(DB12<>"Finished",DF12,0) + N("CUST APRVL"), IF(DI12<>"Finished",DM12,0) + N("MEETINGS"), IF(DN12<>"Finished",DR12,0) + N("PURCHASING"), IF(DU12<>"Finished",DY12,0) + N("HANDOFF"), IF(EB12<>"Finished",EF12,0) + N("SUPPORT"), IF(EI12<>"Finished",EM12,0) + N("DOCUMENTATTION"), IF(EP12<>"Finished",ET12,0) + N("REDLINES"), ) -> 2.08 | EV12: JUAN ADAME | EW12: JUAN ADAME
A13: MX | B13: Follow Up | C13: OP Mobility | D13: Rocker Panel Assembly Station RH - H52 | E13: BMW Rockers Assembly Stations | F13: 3272 | G13: 3272-I | H13: 25 | J13: =BaseDeDatos[[#This Row],[Budget CS]]+BaseDeDatos[[#This Row],[Change Orders Budget]] -> 25 | K13: =IFERROR(VLOOKUP(G13, DATA!H:I, 2, FALSE), 0)+BaseDeDatos[[#This Row],[Labor Spend on Design errors]]+BaseDeDatos[[#This Row],[Labor Spent Customer changes]] -> 43.5 | N13: =AK13+AP13+AW13+CQ13+CX13+DE13+DL13+DQ13+DX13+EE13+EL13+ES13 -> 0.96 | O13: =J13*S13 -> 43.5 | P13: 31.45 | Q13: =BaseDeDatos[[#This Row],[Budget]]*BaseDeDatos[[#This Row],[Labor Rate from CS]] -> 786.25 | R13: =BaseDeDatos[[#This Row],[Labor Spent]]*BaseDeDatos[[#This Row],[Labor Rate from CS]] -> 1368.075 | S13: =K13/J13 -> 1.74 | T13: 431200 | U13: 37083.33 | V13: 29631.85 | W13: 114791.78 | X13: 114791.78 | AA13: 345620.81 | AB13: =AA13-X13-Q13 -> 230042.78 | AC13: =SUM(AB13,X13,R13,BaseDeDatos[[#This Row],[Additionals cost]]) -> 375834.48 | AD13: 0.1985 | AE13: 0.1985 | AF13: =(T13-SUM(X13,AB13,R13))/T13 -> 0.19711819 | AH13: Finished | AI13: =VLOOKUP(AH13,DATA!$B$13:$C$19,2,0) -> 100 | AJ13: =VLOOKUP($AH$1,DATA!$B$24:$C$45,2,0) -> 0.05 | AK13: =BaseDeDatos[[#This Row],[Read info Status]]*(AJ13)/100 -> 0.05 | AL13: =AJ13*$J13 -> 1.25 | AM13: Finished | AN13: =VLOOKUP(AM13,DATA!$B$13:$C$19,2,0) -> 100 | AO13: =VLOOKUP($AM$1,DATA!$B$24:$C$45,2,0) -> 0.05 | AP13: =AN13*AO13/100 -> 0.05 | AQ13: =AO13*$J13 -> 1.25 | AT13: Finished | AU13: =VLOOKUP(AT13,DATA!$B$13:$C$19,2,0) -> 100 | AV13: =VLOOKUP($AT$1,DATA!$B$24:$C$45,2,0) -> 0.01 | AW13: =AU13*AV13/100 -> 0.01 | AX13: =AV13*$J13 -> 0.25 | BA13: Finished | BB13: =VLOOKUP(BA13,DATA!$B$13:$C$19,2,0) -> 100 | BC13: =VLOOKUP($BA$1,DATA!$B$24:$C$45,2,0) -> 0.01 | BD13: =BB13*BC13/100 -> 0.01 | BE13: =BC13*$J13 -> 0.25 | BF13: Finished | BG13: =VLOOKUP(BF13,DATA!$B$13:$C$19,2,0) -> 100 | BH13: =VLOOKUP($BF$1,DATA!$B$24:$C$45,2,0) -> 0.08 | BI13: =BG13*BH13/100 -> 0.08 | BJ13: =BH13*$J13 -> 2 | BK13: Finished | BL13: =VLOOKUP(BK13,DATA!$B$13:$C$19,2,0) -> 100 | BM13: =VLOOKUP($BK$1,DATA!$B$24:$C$45,2,0) -> 0.18 | BN13: =BL13*BM13/100 -> 0.18 | BO13: =BM13*$J13 -> 4.5 | BP13: Finished | BQ13: =VLOOKUP(BP13,DATA!$B$13:$C$19,2,0) -> 100 | BR13: =VLOOKUP($BP$1,DATA!$B$24:$C$45,2,0) -> 0.28 | BS13: =BQ13*BR13/100 -> 0.28 | BT13: =BR13*$J13 -> 7 | BU13: Finished | BV13: =VLOOKUP(BU13,DATA!$B$13:$C$19,2,0) -> 100 | BW13: =VLOOKUP($BU$1,DATA!$B$24:$C$45,2,0) -> 0.15 | BX13: =BV13*BW13/100 -> 0.15 | BY13: =BW13*$J13 -> 3.75 | BZ13: Finished | CA13: =VLOOKUP(BZ13,DATA!$B$13:$C$19,2,0) -> 100 | CB13: =VLOOKUP($BZ$1,DATA!$B$24:$C$45,2,0) -> 0.16 | CC13: =CA13*CB13/100 -> 0.16 | CD13: =CB13*$J13 -> 4 | CE13: Finished | CF13: =VLOOKUP(CE13,DATA!$B$13:$C$19,2,0) -> 100 | CG13: =VLOOKUP($CE$1,DATA!$B$24:$C$45,2,0) -> 0.13 | CH13: =CF13*CG13/100 -> 0.13 | CI13: =CG13*$J13 -> 3.25 | CJ13: Finished | CK13: =VLOOKUP(CJ13,DATA!$B$13:$C$19,2,0) -> 100 | CL13: =VLOOKUP($CJ$1,DATA!$B$24:$C$45,2,0) -> 0.01 | CM13: =CK13*CL13/100 -> 0.01 | CN13: =CL13*$J13 -> 0.25 | CO13: =CM13+CH13+CC13+BX13+BS13+BN13+BI13+BD13 -> 1 | CP13: =VLOOKUP($CO$1,DATA!$B$24:$C$45,2,0) -> 0.54 | CQ13: =CP13*CO13 -> 0.54 | CR13: =CP13*$J13 -> 13.5 | CS13: =CQ13*$J13 -> 13.5 | CT13: =CR13-CS13 -> 0 | CU13: Finished | CV13: =VLOOKUP(CU13,DATA!$B$13:$C$19,2,0) -> 100 | CW13: =VLOOKUP($CU$1,DATA!$B$24:$C$45,2,0) -> 0.02 | CX13: =CV13*CW13/100 -> 0.02 | CY13: =CW13*$J13 -> 0.5 | DB13: Finished | DC13: =VLOOKUP(DB13,DATA!$B$13:$C$19,2,0) -> 100 | DD13: =VLOOKUP($DB$1,DATA!$B$24:$C$45,2,0) -> 0.01 | DE13: =DC13*DD13/100 -> 0.01 | DF13: =DD13*$J13 -> 0.25 | DI13: Finished | DJ13: =VLOOKUP(DI13,DATA!$B$13:$C$19,2,0) -> 100 | DK13: =VLOOKUP($DI$1,DATA!$B$24:$C$45,2,0) -> 0.03 | DL13: =DJ13*DK13/100 -> 0.03 | DM13: =DK13*$J13 -> 0.75 | DN13: Finished | DO13: =VLOOKUP(DN13,DATA!$B$13:$C$19,2,0) -> 100 | DP13: =VLOOKUP($DN$1,DATA!$B$24:$C$45,2,0) -> 0.07 | DQ13: =DO13*DP13/100 -> 0.07 | DR13: =DP13*$J13 -> 1.75 | DU13: Finished | DV13: =VLOOKUP(DU13,DATA!$B$13:$C$19,2,0) -> 100 | DW13: =VLOOKUP($DU$1,DATA!$B$24:$C$45,2,0) -> 0.04 | DX13: =DV13*DW13/100 -> 0.04 | DY13: =DW13*$J13 -> 1 | EB13: In process | EC13: =VLOOKUP(EB13,DATA!$B$13:$C$19,2,0) -> 50 | ED13: =VLOOKUP($EB$1,DATA!$B$24:$C$45,2,0) -> 0.05 | EE13: =EC13*ED13/100 -> 0.025 | EF13: =ED13*$J13 -> 1.25 | EI13: Finished | EJ13: =VLOOKUP(EI13,DATA!$B$13:$C$19,2,0) -> 100 | EK13: =VLOOKUP($EI$1,DATA!$B$24:$C$45,2,0) -> 0.1 | EL13: =EJ13*EK13/100 -> 0.1 | EM13: =EK13*$J13 -> 2.5 | EP13: In process | EQ13: =VLOOKUP(EP13,DATA!$B$13:$C$19,2,0) -> 50 | ER13: =VLOOKUP($EP$1,DATA!$B$24:$C$45,2,0) -> 0.03 | ES13: =EQ13*ER13/100 -> 0.015 | ET13: =ER13*$J13 -> 0.75 | EU13: =SUM( IF(AH13<>"Finished",AL13,0) + N("READ INFO"), IF(AM13<>"Finished",AQ13,0) + N("LONG LEAD"), IF(AT13<>"Finished",AX13,0) + N("SWITCH LAYOUT"), IF(CJ13<>"Finished",CT13,0) + N("DESIGN"), IF(CU13<>"Finished",CY13,0) + N("REVISION"), IF(DB13<>"Finished",DF13,0) + N("CUST APRVL"), IF(DI13<>"Finished",DM13,0) + N("MEETINGS"), IF(DN13<>"Finished",DR13,0) + N("PURCHASING"), IF(DU13<>"Finished",DY13,0) + N("HANDOFF"), IF(EB13<>"Finished",EF13,0) + N("SUPPORT"), IF(EI13<>"Finished",EM13,0) + N("DOCUMENTATTION"), IF(EP13<>"Finished",ET13,0) + N("REDLINES"), ) -> 2 | EV13: JUAN ADAME | EW13: JUAN ADAME
A14: MX | B14: Follow Up | C14: OP Mobility | D14: Brackets Assembly Station - H52 | E14: BMW Rockers Assembly Stations | F14: 3272 | G14: 3272-J | H14: 30 | J14: =BaseDeDatos[[#This Row],[Budget CS]]+BaseDeDatos[[#This Row],[Change Orders Budget]] -> 30 | K14: =IFERROR(VLOOKUP(G14, DATA!H:I, 2, FALSE), 0)+BaseDeDatos[[#This Row],[Labor Spend on Design errors]]+BaseDeDatos[[#This Row],[Labor Spent Customer changes]] -> 75 | N14: =AK14+AP14+AW14+CQ14+CX14+DE14+DL14+DQ14+DX14+EE14+EL14+ES14 -> 0.96 | O14: =J14*S14 -> 75 | P14: 31.45 | Q14: =BaseDeDatos[[#This Row],[Budget]]*BaseDeDatos[[#This Row],[Labor Rate from CS]] -> 943.5 | R14: =BaseDeDatos[[#This Row],[Labor Spent]]*BaseDeDatos[[#This Row],[Labor Rate from CS]] -> 2358.75 | S14: =K14/J14 -> 2.5 | T14: 644314 | U14: 37083.33 | V14: 29631.85 | W14: 105847.59 | X14: 105847.59 | AA14: 516436.87 | AB14: =AA14-X14-Q14 -> 409645.78 | AC14: =SUM(AB14,X14,R14,BaseDeDatos[[#This Row],[Additionals cost]]) -> 547483.97 | AD14: 0.1985 | AE14: 0.1985 | AF14: =(T14-SUM(X14,AB14,R14))/T14 -> 0.19627368 | AH14: Finished | AI14: =VLOOKUP(AH14,DATA!$B$13:$C$19,2,0) -> 100 | AJ14: =VLOOKUP($AH$1,DATA!$B$24:$C$45,2,0) -> 0.05 | AK14: =BaseDeDatos[[#This Row],[Read info Status]]*(AJ14)/100 -> 0.05 | AL14: =AJ14*$J14 -> 1.5 | AM14: Finished | AN14: =VLOOKUP(AM14,DATA!$B$13:$C$19,2,0) -> 100 | AO14: =VLOOKUP($AM$1,DATA!$B$24:$C$45,2,0) -> 0.05 | AP14: =AN14*AO14/100 -> 0.05 | AQ14: =AO14*$J14 -> 1.5 | AT14: Finished | AU14: =VLOOKUP(AT14,DATA!$B$13:$C$19,2,0) -> 100 | AV14: =VLOOKUP($AT$1,DATA!$B$24:$C$45,2,0) -> 0.01 | AW14: =AU14*AV14/100 -> 0.01 | AX14: =AV14*$J14 -> 0.3 | BA14: Finished | BB14: =VLOOKUP(BA14,DATA!$B$13:$C$19,2,0) -> 100 | BC14: =VLOOKUP($BA$1,DATA!$B$24:$C$45,2,0) -> 0.01 | BD14: =BB14*BC14/100 -> 0.01 | BE14: =BC14*$J14 -> 0.3 | BF14: Finished | BG14: =VLOOKUP(BF14,DATA!$B$13:$C$19,2,0) -> 100 | BH14: =VLOOKUP($BF$1,DATA!$B$24:$C$45,2,0) -> 0.08 | BI14: =BG14*BH14/100 -> 0.08 | BJ14: =BH14*$J14 -> 2.4 | BK14: Finished | BL14: =VLOOKUP(BK14,DATA!$B$13:$C$19,2,0) -> 100 | BM14: =VLOOKUP($BK$1,DATA!$B$24:$C$45,2,0) -> 0.18 | BN14: =BL14*BM14/100 -> 0.18 | BO14: =BM14*$J14 -> 5.4 | BP14: Finished | BQ14: =VLOOKUP(BP14,DATA!$B$13:$C$19,2,0) -> 100 | BR14: =VLOOKUP($BP$1,DATA!$B$24:$C$45,2,0) -> 0.28 | BS14: =BQ14*BR14/100 -> 0.28 | BT14: =BR14*$J14 -> 8.4 | BU14: Finished | BV14: =VLOOKUP(BU14,DATA!$B$13:$C$19,2,0) -> 100 | BW14: =VLOOKUP($BU$1,DATA!$B$24:$C$45,2,0) -> 0.15 | BX14: =BV14*BW14/100 -> 0.15 | BY14: =BW14*$J14 -> 4.5 | BZ14: Finished | CA14: =VLOOKUP(BZ14,DATA!$B$13:$C$19,2,0) -> 100 | CB14: =VLOOKUP($BZ$1,DATA!$B$24:$C$45,2,0) -> 0.16 | CC14: =CA14*CB14/100 -> 0.16 | CD14: =CB14*$J14 -> 4.8 | CE14: Finished | CF14: =VLOOKUP(CE14,DATA!$B$13:$C$19,2,0) -> 100 | CG14: =VLOOKUP($CE$1,DATA!$B$24:$C$45,2,0) -> 0.13 | CH14: =CF14*CG14/100 -> 0.13 | CI14: =CG14*$J14 -> 3.9 | CJ14: Finished | CK14: =VLOOKUP(CJ14,DATA!$B$13:$C$19,2,0) -> 100 | CL14: =VLOOKUP($CJ$1,DATA!$B$24:$C$45,2,0) -> 0.01 | CM14: =CK14*CL14/100 -> 0.01 | CN14: =CL14*$J14 -> 0.3 | CO14: =CM14+CH14+CC14+BX14+BS14+BN14+BI14+BD14 -> 1 | CP14: =VLOOKUP($CO$1,DATA!$B$24:$C$45,2,0) -> 0.54 | CQ14: =CP14*CO14 -> 0.54 | CR14: =CP14*$J14 -> 16.2 | CS14: =CQ14*$J14 -> 16.2 | CT14: =CR14-CS14 -> 0 | CU14: Finished | CV14: =VLOOKUP(CU14,DATA!$B$13:$C$19,2,0) -> 100 | CW14: =VLOOKUP($CU$1,DATA!$B$24:$C$45,2,0) -> 0.02 | CX14: =CV14*CW14/100 -> 0.02 | CY14: =CW14*$J14 -> 0.6 | DB14: Finished | DC14: =VLOOKUP(DB14,DATA!$B$13:$C$19,2,0) -> 100 | DD14: =VLOOKUP($DB$1,DATA!$B$24:$C$45,2,0) -> 0.01 | DE14: =DC14*DD14/100 -> 0.01 | DF14: =DD14*$J14 -> 0.3 | DI14: Finished | DJ14: =VLOOKUP(DI14,DATA!$B$13:$C$19,2,0) -> 100 | DK14: =VLOOKUP($DI$1,DATA!$B$24:$C$45,2,0) -> 0.03 | DL14: =DJ14*DK14/100 -> 0.03 | DM14: =DK14*$J14 -> 0.9 | DN14: Finished | DO14: =VLOOKUP(DN14,DATA!$B$13:$C$19,2,0) -> 100 | DP14: =VLOOKUP($DN$1,DATA!$B$24:$C$45,2,0) -> 0.07 | DQ14: =DO14*DP14/100 -> 0.07 | DR14: =DP14*$J14 -> 2.1 | DU14: Finished | DV14: =VLOOKUP(DU14,DATA!$B$13:$C$19,2,0) -> 100 | DW14: =VLOOKUP($DU$1,DATA!$B$24:$C$45,2,0) -> 0.04 | DX14: =DV14*DW14/100 -> 0.04 | DY14: =DW14*$J14 -> 1.2 | EB14: In process | EC14: =VLOOKUP(EB14,DATA!$B$13:$C$19,2,0) -> 50 | ED14: =VLOOKUP($EB$1,DATA!$B$24:$C$45,2,0) -> 0.05 | EE14: =EC14*ED14/100 -> 0.025 | EF14: =ED14*$J14 -> 1.5 | EI14: Finished | EJ14: =VLOOKUP(EI14,DATA!$B$13:$C$19,2,0) -> 100 | EK14: =VLOOKUP($EI$1,DATA!$B$24:$C$45,2,0) -> 0.1 | EL14: =EJ14*EK14/100 -> 0.1 | EM14: =EK14*$J14 -> 3 | EP14: In process | EQ14: =VLOOKUP(EP14,DATA!$B$13:$C$19,2,0) -> 50 | ER14: =VLOOKUP($EP$1,DATA!$B$24:$C$45,2,0) -> 0.03 | ES14: =EQ14*ER14/100 -> 0.015 | ET14: =ER14*$J14 -> 0.9 | EU14: =SUM( IF(AH14<>"Finished",AL14,0) + N("READ INFO"), IF(AM14<>"Finished",AQ14,0) + N("LONG LEAD"), IF(AT14<>"Finished",AX14,0) + N("SWITCH LAYOUT"), IF(CJ14<>"Finished",CT14,0) + N("DESIGN"), IF(CU14<>"Finished",CY14,0) + N("REVISION"), IF(DB14<>"Finished",DF14,0) + N("CUST APRVL"), IF(DI14<>"Finished",DM14,0) + N("MEETINGS"), IF(DN14<>"Finished",DR14,0) + N("PURCHASING"), IF(DU14<>"Finished",DY14,0) + N("HANDOFF"), IF(EB14<>"Finished",EF14,0) + N("SUPPORT"), IF(EI14<>"Finished",EM14,0) + N("DOCUMENTATTION"), IF(EP14<>"Finished",ET14,0) + N("REDLINES"), ) -> 2.4 | EV14: JUAN ADAME | EW14: HILDA MATA
A15: MX | B15: Close | C15: Continental | D15: ID917 Automatic Screw Driving Station KW & PB | F15: 3278 | G15: 3278-A | H15: 50 | J15: =BaseDeDatos[[#This Row],[Budget CS]]+BaseDeDatos[[#This Row],[Change Orders Budget]] -> 50 | K15: =IFERROR(VLOOKUP(G15, DATA!H:I, 2, FALSE), 0)+BaseDeDatos[[#This Row],[Labor Spend on Design errors]]+BaseDeDatos[[#This Row],[Labor Spent Customer changes]] -> 69.5 | N15: =AK15+AP15+AW15+CQ15+CX15+DE15+DL15+DQ15+DX15+EE15+EL15+ES15 -> 1 | O15: =J15*S15 -> 69.5 | P15: 29.7 | Q15: =BaseDeDatos[[#This Row],[Budget]]*BaseDeDatos[[#This Row],[Labor Rate from CS]] -> 1485 | R15: =BaseDeDatos[[#This Row],[Labor Spent]]*BaseDeDatos[[#This Row],[Labor Rate from CS]] -> 2064.15 | S15: =K15/J15 -> 1.39 | T15: 297389 | U15: 3698 | V15: 3147.18 | W15: 51744.74 | X15: 51744.74 | AA15: 245730.98 | AB15: =AA15-X15-Q15 -> 192501.24 | AC15: =SUM(AB15,X15,R15,BaseDeDatos[[#This Row],[Additionals cost]]) -> 249457.31 | AD15: 0.1674 | AE15: 0.1811 | AF15: =(T15-SUM(X15,AB15,R15))/T15 -> 0.17175777 | AH15: Finished | AI15: =VLOOKUP(AH15,DATA!$B$13:$C$19,2,0) -> 100 | AJ15: =VLOOKUP($AH$1,DATA!$B$24:$C$45,2,0) -> 0.05 | AK15: =BaseDeDatos[[#This Row],[Read info Status]]*(AJ15)/100 -> 0.05 | AL15: =AJ15*$J15 -> 2.5 | AM15: Finished | AN15: =VLOOKUP(AM15,DATA!$B$13:$C$19,2,0) -> 100 | AO15: =VLOOKUP($AM$1,DATA!$B$24:$C$45,2,0) -> 0.05 | AP15: =AN15*AO15/100 -> 0.05 | AQ15: =AO15*$J15 -> 2.5 | AT15: Finished | AU15: =VLOOKUP(AT15,DATA!$B$13:$C$19,2,0) -> 100 | AV15: =VLOOKUP($AT$1,DATA!$B$24:$C$45,2,0) -> 0.01 | AW15: =AU15*AV15/100 -> 0.01 | AX15: =AV15*$J15 -> 0.5 | BA15: Finished | BB15: =VLOOKUP(BA15,DATA!$B$13:$C$19,2,0) -> 100 | BC15: =VLOOKUP($BA$1,DATA!$B$24:$C$45,2,0) -> 0.01 | BD15: =BB15*BC15/100 -> 0.01 | BE15: =BC15*$J15 -> 0.5 | BF15: Finished | BG15: =VLOOKUP(BF15,DATA!$B$13:$C$19,2,0) -> 100 | BH15: =VLOOKUP($BF$1,DATA!$B$24:$C$45,2,0) -> 0.08 | BI15: =BG15*BH15/100 -> 0.08 | BJ15: =BH15*$J15 -> 4 | BK15: Finished | BL15: =VLOOKUP(BK15,DATA!$B$13:$C$19,2,0) -> 100 | BM15: =VLOOKUP($BK$1,DATA!$B$24:$C$45,2,0) -> 0.18 | BN15: =BL15*BM15/100 -> 0.18 | BO15: =BM15*$J15 -> 9 | BP15: Finished | BQ15: =VLOOKUP(BP15,DATA!$B$13:$C$19,2,0) -> 100 | BR15: =VLOOKUP($BP$1,DATA!$B$24:$C$45,2,0) -> 0.28 | BS15: =BQ15*BR15/100 -> 0.28 | BT15: =BR15*$J15 -> 14 | BU15: Finished | BV15: =VLOOKUP(BU15,DATA!$B$13:$C$19,2,0) -> 100 | BW15: =VLOOKUP($BU$1,DATA!$B$24:$C$45,2,0) -> 0.15 | BX15: =BV15*BW15/100 -> 0.15 | BY15: =BW15*$J15 -> 7.5 | BZ15: Finished | CA15: =VLOOKUP(BZ15,DATA!$B$13:$C$19,2,0) -> 100 | CB15: =VLOOKUP($BZ$1,DATA!$B$24:$C$45,2,0) -> 0.16 | CC15: =CA15*CB15/100 -> 0.16 | CD15: =CB15*$J15 -> 8 | CE15: Finished | CF15: =VLOOKUP(CE15,DATA!$B$13:$C$19,2,0) -> 100 | CG15: =VLOOKUP($CE$1,DATA!$B$24:$C$45,2,0) -> 0.13 | CH15: =CF15*CG15/100 -> 0.13 | CI15: =CG15*$J15 -> 6.5 | CJ15: Finished | CK15: =VLOOKUP(CJ15,DATA!$B$13:$C$19,2,0) -> 100 | CL15: =VLOOKUP($CJ$1,DATA!$B$24:$C$45,2,0) -> 0.01 | CM15: =CK15*CL15/100 -> 0.01 | CN15: =CL15*$J15 -> 0.5 | CO15: =CM15+CH15+CC15+BX15+BS15+BN15+BI15+BD15 -> 1 | CP15: =VLOOKUP($CO$1,DATA!$B$24:$C$45,2,0) -> 0.54 | CQ15: =CP15*CO15 -> 0.54 | CR15: =CP15*$J15 -> 27 | CS15: =CQ15*$J15 -> 27 | CT15: =CR15-CS15 -> 0 | CU15: Finished | CV15: =VLOOKUP(CU15,DATA!$B$13:$C$19,2,0) -> 100 | CW15: =VLOOKUP($CU$1,DATA!$B$24:$C$45,2,0) -> 0.02 | CX15: =CV15*CW15/100 -> 0.02 | CY15: =CW15*$J15 -> 1 | DB15: Finished | DC15: =VLOOKUP(DB15,DATA!$B$13:$C$19,2,0) -> 100 | DD15: =VLOOKUP($DB$1,DATA!$B$24:$C$45,2,0) -> 0.01 | DE15: =DC15*DD15/100 -> 0.01 | DF15: =DD15*$J15 -> 0.5 | DI15: Finished | DJ15: =VLOOKUP(DI15,DATA!$B$13:$C$19,2,0) -> 100 | DK15: =VLOOKUP($DI$1,DATA!$B$24:$C$45,2,0) -> 0.03 | DL15: =DJ15*DK15/100 -> 0.03 | DM15: =DK15*$J15 -> 1.5 | DN15: Finished | DO15: =VLOOKUP(DN15,DATA!$B$13:$C$19,2,0) -> 100 | DP15: =VLOOKUP($DN$1,DATA!$B$24:$C$45,2,0) -> 0.07 | DQ15: =DO15*DP15/100 -> 0.07 | DR15: =DP15*$J15 -> 3.5 | DU15: Finished | DV15: =VLOOKUP(DU15,DATA!$B$13:$C$19,2,0) -> 100 | DW15: =VLOOKUP($DU$1,DATA!$B$24:$C$45,2,0) -> 0.04 | DX15: =DV15*DW15/100 -> 0.04 | DY15: =DW15*$J15 -> 2 | EB15: Finished | EC15: =VLOOKUP(EB15,DATA!$B$13:$C$19,2,0) -> 100 | ED15: =VLOOKUP($EB$1,DATA!$B$24:$C$45,2,0) -> 0.05 | EE15: =EC15*ED15/100 -> 0.05 | EF15: =ED15*$J15 -> 2.5 | EI15: Finished | EJ15: =VLOOKUP(EI15,DATA!$B$13:$C$19,2,0) -> 100 | EK15: =VLOOKUP($EI$1,DATA!$B$24:$C$45,2,0) -> 0.1 | EL15: =EJ15*EK15/100 -> 0.1 | EM15: =EK15*$J15 -> 5 | EP15: Finished | EQ15: =VLOOKUP(EP15,DATA!$B$13:$C$19,2,0) -> 100 | ER15: =VLOOKUP($EP$1,DATA!$B$24:$C$45,2,0) -> 0.03 | ES15: =EQ15*ER15/100 -> 0.03 | ET15: =ER15*$J15 -> 1.5 | EU15: =SUM( IF(AH15<>"Finished",AL15,0) + N("READ INFO"), IF(AM15<>"Finished",AQ15,0) + N("LONG LEAD"), IF(AT15<>"Finished",AX15,0) + N("SWITCH LAYOUT"), IF(CJ15<>"Finished",CT15,0) + N("DESIGN"), IF(CU15<>"Finished",CY15,0) + N("REVISION"), IF(DB15<>"Finished",DF15,0) + N("CUST APRVL"), IF(DI15<>"Finished",DM15,0) + N("MEETINGS"), IF(DN15<>"Finished",DR15,0) + N("PURCHASING"), IF(DU15<>"Finished",DY15,0) + N("HANDOFF"), IF(EB15<>"Finished",EF15,0) + N("SUPPORT"), IF(EI15<>"Finished",EM15,0) + N("DOCUMENTATTION"), IF(EP15<>"Finished",ET15,0) + N("REDLINES"), ) -> 0 | EV15: ADRIAN CABELLO | EW15: ADRIAN CABELLO
A16: MX | B16: Close | C16: Continental | D16: ID925 Automatic Screw Driving Station Silver Box | F16: 3278 | G16: 3278-B | H16: 50 | J16: =BaseDeDatos[[#This Row],[Budget CS]]+BaseDeDatos[[#This Row],[Change Orders Budget]] -> 50 | K16: =IFERROR(VLOOKUP(G16, DATA!H:I, 2, FALSE), 0)+BaseDeDatos[[#This Row],[Labor Spend on Design errors]]+BaseDeDatos[[#This Row],[Labor Spent Customer changes]] -> 53.5 | N16: =AK16+AP16+AW16+CQ16+CX16+DE16+DL16+DQ16+DX16+EE16+EL16+ES16 -> 1 | O16: =J16*S16 -> 53.5 | P16: 29.7 | Q16: =BaseDeDatos[[#This Row],[Budget]]*BaseDeDatos[[#This Row],[Labor Rate from CS]] -> 1485 | R16: =BaseDeDatos[[#This Row],[Labor Spent]]*BaseDeDatos[[#This Row],[Labor Rate from CS]] -> 1588.95 | S16: =K16/J16 -> 1.07 | T16: 286501 | U16: 3698 | V16: 3147.18 | W16: 51744.74 | X16: 51744.74 | AA16: 238140.82 | AB16: =AA16-X16-Q16 -> 184911.08 | AC16: =SUM(AB16,X16,R16,BaseDeDatos[[#This Row],[Additionals cost]]) -> 241391.95 | AD16: 0.1688 | AE16: 0.1811 | AF16: =(T16-SUM(X16,AB16,R16))/T16 -> 0.16843302 | AH16: Finished | AI16: =VLOOKUP(AH16,DATA!$B$13:$C$19,2,0) -> 100 | AJ16: =VLOOKUP($AH$1,DATA!$B$24:$C$45,2,0) -> 0.05 | AK16: =BaseDeDatos[[#This Row],[Read info Status]]*(AJ16)/100 -> 0.05 | AL16: =AJ16*$J16 -> 2.5 | AM16: Finished | AN16: =VLOOKUP(AM16,DATA!$B$13:$C$19,2,0) -> 100 | AO16: =VLOOKUP($AM$1,DATA!$B$24:$C$45,2,0) -> 0.05 | AP16: =AN16*AO16/100 -> 0.05 | AQ16: =AO16*$J16 -> 2.5 | AT16: Finished | AU16: =VLOOKUP(AT16,DATA!$B$13:$C$19,2,0) -> 100 | AV16: =VLOOKUP($AT$1,DATA!$B$24:$C$45,2,0) -> 0.01 | AW16: =AU16*AV16/100 -> 0.01 | AX16: =AV16*$J16 -> 0.5 | BA16: Finished | BB16: =VLOOKUP(BA16,DATA!$B$13:$C$19,2,0) -> 100 | BC16: =VLOOKUP($BA$1,DATA!$B$24:$C$45,2,0) -> 0.01 | BD16: =BB16*BC16/100 -> 0.01 | BE16: =BC16*$J16 -> 0.5 | BF16: Finished | BG16: =VLOOKUP(BF16,DATA!$B$13:$C$19,2,0) -> 100 | BH16: =VLOOKUP($BF$1,DATA!$B$24:$C$45,2,0) -> 0.08 | BI16: =BG16*BH16/100 -> 0.08 | BJ16: =BH16*$J16 -> 4 | BK16: Finished | BL16: =VLOOKUP(BK16,DATA!$B$13:$C$19,2,0) -> 100 | BM16: =VLOOKUP($BK$1,DATA!$B$24:$C$45,2,0) -> 0.18 | BN16: =BL16*BM16/100 -> 0.18 | BO16: =BM16*$J16 -> 9 | BP16: Finished | BQ16: =VLOOKUP(BP16,DATA!$B$13:$C$19,2,0) -> 100 | BR16: =VLOOKUP($BP$1,DATA!$B$24:$C$45,2,0) -> 0.28 | BS16: =BQ16*BR16/100 -> 0.28 | BT16: =BR16*$J16 -> 14 | BU16: Finished | BV16: =VLOOKUP(BU16,DATA!$B$13:$C$19,2,0) -> 100 | BW16: =VLOOKUP($BU$1,DATA!$B$24:$C$45,2,0) -> 0.15 | BX16: =BV16*BW16/100 -> 0.15 | BY16: =BW16*$J16 -> 7.5 | BZ16: Finished | CA16: =VLOOKUP(BZ16,DATA!$B$13:$C$19,2,0) -> 100 | CB16: =VLOOKUP($BZ$1,DATA!$B$24:$C$45,2,0) -> 0.16 | CC16: =CA16*CB16/100 -> 0.16 | CD16: =CB16*$J16 -> 8 | CE16: Finished | CF16: =VLOOKUP(CE16,DATA!$B$13:$C$19,2,0) -> 100 | CG16: =VLOOKUP($CE$1,DATA!$B$24:$C$45,2,0) -> 0.13 | CH16: =CF16*CG16/100 -> 0.13 | CI16: =CG16*$J16 -> 6.5 | CJ16: Finished | CK16: =VLOOKUP(CJ16,DATA!$B$13:$C$19,2,0) -> 100 | CL16: =VLOOKUP($CJ$1,DATA!$B$24:$C$45,2,0) -> 0.01 | CM16: =CK16*CL16/100 -> 0.01 | CN16: =CL16*$J16 -> 0.5 | CO16: =CM16+CH16+CC16+BX16+BS16+BN16+BI16+BD16 -> 1 | CP16: =VLOOKUP($CO$1,DATA!$B$24:$C$45,2,0) -> 0.54 | CQ16: =CP16*CO16 -> 0.54 | CR16: =CP16*$J16 -> 27 | CS16: =CQ16*$J16 -> 27 | CT16: =CR16-CS16 -> 0 | CU16: Finished | CV16: =VLOOKUP(CU16,DATA!$B$13:$C$19,2,0) -> 100 | CW16: =VLOOKUP($CU$1,DATA!$B$24:$C$45,2,0) -> 0.02 | CX16: =CV16*CW16/100 -> 0.02 | CY16: =CW16*$J16 -> 1 | DB16: Finished | DC16: =VLOOKUP(DB16,DATA!$B$13:$C$19,2,0) -> 100 | DD16: =VLOOKUP($DB$1,DATA!$B$24:$C$45,2,0) -> 0.01 | DE16: =DC16*DD16/100 -> 0.01 | DF16: =DD16*$J16 -> 0.5 | DI16: Finished | DJ16: =VLOOKUP(DI16,DATA!$B$13:$C$19,2,0) -> 100 | DK16: =VLOOKUP($DI$1,DATA!$B$24:$C$45,2,0) -> 0.03 | DL16: =DJ16*DK16/100 -> 0.03 | DM16: =DK16*$J16 -> 1.5 | DN16: Finished | DO16: =VLOOKUP(DN16,DATA!$B$13:$C$19,2,0) -> 100 | DP16: =VLOOKUP($DN$1,DATA!$B$24:$C$45,2,0) -> 0.07 | DQ16: =DO16*DP16/100 -> 0.07 | DR16: =DP16*$J16 -> 3.5 | DU16: Finished | DV16: =VLOOKUP(DU16,DATA!$B$13:$C$19,2,0) -> 100 | DW16: =VLOOKUP($DU$1,DATA!$B$24:$C$45,2,0) -> 0.04 | DX16: =DV16*DW16/100 -> 0.04 | DY16: =DW16*$J16 -> 2 | EB16: Finished | EC16: =VLOOKUP(EB16,DATA!$B$13:$C$19,2,0) -> 100 | ED16: =VLOOKUP($EB$1,DATA!$B$24:$C$45,2,0) -> 0.05 | EE16: =EC16*ED16/100 -> 0.05 | EF16: =ED16*$J16 -> 2.5 | EI16: Finished | EJ16: =VLOOKUP(EI16,DATA!$B$13:$C$19,2,0) -> 100 | EK16: =VLOOKUP($EI$1,DATA!$B$24:$C$45,2,0) -> 0.1 | EL16: =EJ16*EK16/100 -> 0.1 | EM16: =EK16*$J16 -> 5 | EP16: Finished | EQ16: =VLOOKUP(EP16,DATA!$B$13:$C$19,2,0) -> 100 | ER16: =VLOOKUP($EP$1,DATA!$B$24:$C$45,2,0) -> 0.03 | ES16: =EQ16*ER16/100 -> 0.03 | ET16: =ER16*$J16 -> 1.5 | EU16: =SUM( IF(AH16<>"Finished",AL16,0) + N("READ INFO"), IF(AM16<>"Finished",AQ16,0) + N("LONG LEAD"), IF(AT16<>"Finished",AX16,0) + N("SWITCH LAYOUT"), IF(CJ16<>"Finished",CT16,0) + N("DESIGN"), IF(CU16<>"Finished",CY16,0) + N("REVISION"), IF(DB16<>"Finished",DF16,0) + N("CUST APRVL"), IF(DI16<>"Finished",DM16,0) + N("MEETINGS"), IF(DN16<>"Finished",DR16,0) + N("PURCHASING"), IF(DU16<>"Finished",DY16,0) + N("HANDOFF"), IF(EB16<>"Finished",EF16,0) + N("SUPPORT"), IF(EI16<>"Finished",EM16,0) + N("DOCUMENTATTION"), IF(EP16<>"Finished",ET16,0) + N("REDLINES"), ) -> 0 | EV16: ADRIAN CABELLO | EW16: ADRIAN CABELLO
A17: MX | B17: Close | C17: Continental | D17: ID926 Automatic Screw Driving Station Silver Box | F17: 3278 | G17: 3278-C | H17: 50 | J17: =BaseDeDatos[[#This Row],[Budget CS]]+BaseDeDatos[[#This Row],[Change Orders Budget]] -> 50 | K17: =IFERROR(VLOOKUP(G17, DATA!H:I, 2, FALSE), 0)+BaseDeDatos[[#This Row],[Labor Spend on Design errors]]+BaseDeDatos[[#This Row],[Labor Spent Customer changes]] -> 84.5 | N17: =AK17+AP17+AW17+CQ17+CX17+DE17+DL17+DQ17+DX17+EE17+EL17+ES17 -> 1 | O17: =J17*S17 -> 84.5 | P17: 29.7 | Q17: =BaseDeDatos[[#This Row],[Budget]]*BaseDeDatos[[#This Row],[Labor Rate from CS]] -> 1485 | R17: =BaseDeDatos[[#This Row],[Labor Spent]]*BaseDeDatos[[#This Row],[Labor Rate from CS]] -> 2509.65 | S17: =K17/J17 -> 1.69 | T17: 292555 | U17: 3698 | V17: 3147.18 | W17: 51744.74 | X17: 51744.74 | AA17: 243193.32 | AB17: =AA17-X17-Q17 -> 189963.58 | AC17: =SUM(AB17,X17,R17,BaseDeDatos[[#This Row],[Additionals cost]]) -> 247365.15 | AD17: 0.1684 | AE17: 0.1811 | AF17: =(T17-SUM(X17,AB17,R17))/T17 -> 0.16522374 | AH17: Finished | AI17: =VLOOKUP(AH17,DATA!$B$13:$C$19,2,0) -> 100 | AJ17: =VLOOKUP($AH$1,DATA!$B$24:$C$45,2,0) -> 0.05 | AK17: =BaseDeDatos[[#This Row],[Read info Status]]*(AJ17)/100 -> 0.05 | AL17: =AJ17*$J17 -> 2.5 | AM17: Finished | AN17: =VLOOKUP(AM17,DATA!$B$13:$C$19,2,0) -> 100 | AO17: =VLOOKUP($AM$1,DATA!$B$24:$C$45,2,0) -> 0.05 | AP17: =AN17*AO17/100 -> 0.05 | AQ17: =AO17*$J17 -> 2.5 | AT17: Finished | AU17: =VLOOKUP(AT17,DATA!$B$13:$C$19,2,0) -> 100 | AV17: =VLOOKUP($AT$1,DATA!$B$24:$C$45,2,0) -> 0.01 | AW17: =AU17*AV17/100 -> 0.01 | AX17: =AV17*$J17 -> 0.5 | BA17: Finished | BB17: =VLOOKUP(BA17,DATA!$B$13:$C$19,2,0) -> 100 | BC17: =VLOOKUP($BA$1,DATA!$B$24:$C$45,2,0) -> 0.01 | BD17: =BB17*BC17/100 -> 0.01 | BE17: =BC17*$J17 -> 0.5 | BF17: Finished | BG17: =VLOOKUP(BF17,DATA!$B$13:$C$19,2,0) -> 100 | BH17: =VLOOKUP($BF$1,DATA!$B$24:$C$45,2,0) -> 0.08 | BI17: =BG17*BH17/100 -> 0.08 | BJ17: =BH17*$J17 -> 4 | BK17: Finished | BL17: =VLOOKUP(BK17,DATA!$B$13:$C$19,2,0) -> 100 | BM17: =VLOOKUP($BK$1,DATA!$B$24:$C$45,2,0) -> 0.18 | BN17: =BL17*BM17/100 -> 0.18 | BO17: =BM17*$J17 -> 9 | BP17: Finished | BQ17: =VLOOKUP(BP17,DATA!$B$13:$C$19,2,0) -> 100 | BR17: =VLOOKUP($BP$1,DATA!$B$24:$C$45,2,0) -> 0.28 | BS17: =BQ17*BR17/100 -> 0.28 | BT17: =BR17*$J17 -> 14 | BU17: Finished | BV17: =VLOOKUP(BU17,DATA!$B$13:$C$19,2,0) -> 100 | BW17: =VLOOKUP($BU$1,DATA!$B$24:$C$45,2,0) -> 0.15 | BX17: =BV17*BW17/100 -> 0.15 | BY17: =BW17*$J17 -> 7.5 | BZ17: Finished | CA17: =VLOOKUP(BZ17,DATA!$B$13:$C$19,2,0) -> 100 | CB17: =VLOOKUP($BZ$1,DATA!$B$24:$C$45,2,0) -> 0.16 | CC17: =CA17*CB17/100 -> 0.16 | CD17: =CB17*$J17 -> 8 | CE17: Finished | CF17: =VLOOKUP(CE17,DATA!$B$13:$C$19,2,0) -> 100 | CG17: =VLOOKUP($CE$1,DATA!$B$24:$C$45,2,0) -> 0.13 | CH17: =CF17*CG17/100 -> 0.13 | CI17: =CG17*$J17 -> 6.5 | CJ17: Finished | CK17: =VLOOKUP(CJ17,DATA!$B$13:$C$19,2,0) -> 100 | CL17: =VLOOKUP($CJ$1,DATA!$B$24:$C$45,2,0) -> 0.01 | CM17: =CK17*CL17/100 -> 0.01 | CN17: =CL17*$J17 -> 0.5 | CO17: =CM17+CH17+CC17+BX17+BS17+BN17+BI17+BD17 -> 1 | CP17: =VLOOKUP($CO$1,DATA!$B$24:$C$45,2,0) -> 0.54 | CQ17: =CP17*CO17 -> 0.54 | CR17: =CP17*$J17 -> 27 | CS17: =CQ17*$J17 -> 27 | CT17: =CR17-CS17 -> 0 | CU17: Finished | CV17: =VLOOKUP(CU17,DATA!$B$13:$C$19,2,0) -> 100 | CW17: =VLOOKUP($CU$1,DATA!$B$24:$C$45,2,0) -> 0.02 | CX17: =CV17*CW17/100 -> 0.02 | CY17: =CW17*$J17 -> 1 | DB17: Finished | DC17: =VLOOKUP(DB17,DATA!$B$13:$C$19,2,0) -> 100 | DD17: =VLOOKUP($DB$1,DATA!$B$24:$C$45,2,0) -> 0.01 | DE17: =DC17*DD17/100 -> 0.01 | DF17: =DD17*$J17 -> 0.5 | DI17: Finished | DJ17: =VLOOKUP(DI17,DATA!$B$13:$C$19,2,0) -> 100 | DK17: =VLOOKUP($DI$1,DATA!$B$24:$C$45,2,0) -> 0.03 | DL17: =DJ17*DK17/100 -> 0.03 | DM17: =DK17*$J17 -> 1.5 | DN17: Finished | DO17: =VLOOKUP(DN17,DATA!$B$13:$C$19,2,0) -> 100 | DP17: =VLOOKUP($DN$1,DATA!$B$24:$C$45,2,0) -> 0.07 | DQ17: =DO17*DP17/100 -> 0.07 | DR17: =DP17*$J17 -> 3.5 | DU17: Finished | DV17: =VLOOKUP(DU17,DATA!$B$13:$C$19,2,0) -> 100 | DW17: =VLOOKUP($DU$1,DATA!$B$24:$C$45,2,0) -> 0.04 | DX17: =DV17*DW17/100 -> 0.04 | DY17: =DW17*$J17 -> 2 | EB17: Finished | EC17: =VLOOKUP(EB17,DATA!$B$13:$C$19,2,0) -> 100 | ED17: =VLOOKUP($EB$1,DATA!$B$24:$C$45,2,0) -> 0.05 | EE17: =EC17*ED17/100 -> 0.05 | EF17: =ED17*$J17 -> 2.5 | EI17: Finished | EJ17: =VLOOKUP(EI17,DATA!$B$13:$C$19,2,0) -> 100 | EK17: =VLOOKUP($EI$1,DATA!$B$24:$C$45,2,0) -> 0.1 | EL17: =EJ17*EK17/100 -> 0.1 | EM17: =EK17*$J17 -> 5 | EP17: Finished | EQ17: =VLOOKUP(EP17,DATA!$B$13:$C$19,2,0) -> 100 | ER17: =VLOOKUP($EP$1,DATA!$B$24:$C$45,2,0) -> 0.03 | ES17: =EQ17*ER17/100 -> 0.03 | ET17: =ER17*$J17 -> 1.5 | EU17: =SUM( IF(AH17<>"Finished",AL17,0) + N("READ INFO"), IF(AM17<>"Finished",AQ17,0) + N("LONG LEAD"), IF(AT17<>"Finished",AX17,0) + N("SWITCH LAYOUT"), IF(CJ17<>"Finished",CT17,0) + N("DESIGN"), IF(CU17<>"Finished",CY17,0) + N("REVISION"), IF(DB17<>"Finished",DF17,0) + N("CUST APRVL"), IF(DI17<>"Finished",DM17,0) + N("MEETINGS"), IF(DN17<>"Finished",DR17,0) + N("PURCHASING"), IF(DU17<>"Finished",DY17,0) + N("HANDOFF"), IF(EB17<>"Finished",EF17,0) + N("SUPPORT"), IF(EI17<>"Finished",EM17,0) + N("DOCUMENTATTION"), IF(EP17<>"Finished",ET17,0) + N("REDLINES"), ) -> 0 | EV17: ADRIAN CABELLO | EW17: ADRIAN CABELLO
A18: MX | B18: Close | C18: Continental | D18: ID931 Manual Screw Driving Station & Assy Light conduct KW-PB | F18: 3278 | G18: 3278-D | H18: 60 | J18: =BaseDeDatos[[#This Row],[Budget CS]]+BaseDeDatos[[#This Row],[Change Orders Budget]] -> 60 | K18: =IFERROR(VLOOKUP(G18, DATA!H:I, 2, FALSE), 0)+BaseDeDatos[[#This Row],[Labor Spend on Design errors]]+BaseDeDatos[[#This Row],[Labor Spent Customer changes]] -> 75 | N18: =AK18+AP18+AW18+CQ18+CX18+DE18+DL18+DQ18+DX18+EE18+EL18+ES18 -> 1 | O18: =J18*S18 -> 75 | P18: 29.7 | Q18: =BaseDeDatos[[#This Row],[Budget]]*BaseDeDatos[[#This Row],[Labor Rate from CS]] -> 1782 | R18: =BaseDeDatos[[#This Row],[Labor Spent]]*BaseDeDatos[[#This Row],[Labor Rate from CS]] -> 2227.5 | S18: =K18/J18 -> 1.25 | T18: 190230 | U18: 3698 | V18: 3147.18 | W18: 45193.56 | X18: 45193.56 | AA18: 149464.36 | AB18: =AA18-X18-Q18 -> 102488.8 | AC18: =SUM(AB18,X18,R18,BaseDeDatos[[#This Row],[Additionals cost]]) -> 153057.04 | AD18: 0.2897 | AE18: 0.1811 | AF18: =(T18-SUM(X18,AB18,R18))/T18 -> 0.21195469 | AH18: Finished | AI18: =VLOOKUP(AH18,DATA!$B$13:$C$19,2,0) -> 100 | AJ18: =VLOOKUP($AH$1,DATA!$B$24:$C$45,2,0) -> 0.05 | AK18: =BaseDeDatos[[#This Row],[Read info Status]]*(AJ18)/100 -> 0.05 | AL18: =AJ18*$J18 -> 3 | AM18: Finished | AN18: =VLOOKUP(AM18,DATA!$B$13:$C$19,2,0) -> 100 | AO18: =VLOOKUP($AM$1,DATA!$B$24:$C$45,2,0) -> 0.05 | AP18: =AN18*AO18/100 -> 0.05 | AQ18: =AO18*$J18 -> 3 | AT18: Finished | AU18: =VLOOKUP(AT18,DATA!$B$13:$C$19,2,0) -> 100 | AV18: =VLOOKUP($AT$1,DATA!$B$24:$C$45,2,0) -> 0.01 | AW18: =AU18*AV18/100 -> 0.01 | AX18: =AV18*$J18 -> 0.6 | BA18: Finished | BB18: =VLOOKUP(BA18,DATA!$B$13:$C$19,2,0) -> 100 | BC18: =VLOOKUP($BA$1,DATA!$B$24:$C$45,2,0) -> 0.01 | BD18: =BB18*BC18/100 -> 0.01 | BE18: =BC18*$J18 -> 0.6 | BF18: Finished | BG18: =VLOOKUP(BF18,DATA!$B$13:$C$19,2,0) -> 100 | BH18: =VLOOKUP($BF$1,DATA!$B$24:$C$45,2,0) -> 0.08 | BI18: =BG18*BH18/100 -> 0.08 | BJ18: =BH18*$J18 -> 4.8 | BK18: Finished | BL18: =VLOOKUP(BK18,DATA!$B$13:$C$19,2,0) -> 100 | BM18: =VLOOKUP($BK$1,DATA!$B$24:$C$45,2,0) -> 0.18 | BN18: =BL18*BM18/100 -> 0.18 | BO18: =BM18*$J18 -> 10.8 | BP18: Finished | BQ18: =VLOOKUP(BP18,DATA!$B$13:$C$19,2,0) -> 100 | BR18: =VLOOKUP($BP$1,DATA!$B$24:$C$45,2,0) -> 0.28 | BS18: =BQ18*BR18/100 -> 0.28 | BT18: =BR18*$J18 -> 16.8 | BU18: Finished | BV18: =VLOOKUP(BU18,DATA!$B$13:$C$19,2,0) -> 100 | BW18: =VLOOKUP($BU$1,DATA!$B$24:$C$45,2,0) -> 0.15 | BX18: =BV18*BW18/100 -> 0.15 | BY18: =BW18*$J18 -> 9 | BZ18: Finished | CA18: =VLOOKUP(BZ18,DATA!$B$13:$C$19,2,0) -> 100 | CB18: =VLOOKUP($BZ$1,DATA!$B$24:$C$45,2,0) -> 0.16 | CC18: =CA18*CB18/100 -> 0.16 | CD18: =CB18*$J18 -> 9.6 | CE18: Finished | CF18: =VLOOKUP(CE18,DATA!$B$13:$C$19,2,0) -> 100 | CG18: =VLOOKUP($CE$1,DATA!$B$24:$C$45,2,0) -> 0.13 | CH18: =CF18*CG18/100 -> 0.13 | CI18: =CG18*$J18 -> 7.8 | CJ18: Finished | CK18: =VLOOKUP(CJ18,DATA!$B$13:$C$19,2,0) -> 100 | CL18: =VLOOKUP($CJ$1,DATA!$B$24:$C$45,2,0) -> 0.01 | CM18: =CK18*CL18/100 -> 0.01 | CN18: =CL18*$J18 -> 0.6 | CO18: =CM18+CH18+CC18+BX18+BS18+BN18+BI18+BD18 -> 1 | CP18: =VLOOKUP($CO$1,DATA!$B$24:$C$45,2,0) -> 0.54 | CQ18: =CP18*CO18 -> 0.54 | CR18: =CP18*$J18 -> 32.4 | CS18: =CQ18*$J18 -> 32.4 | CT18: =CR18-CS18 -> 0 | CU18: Finished | CV18: =VLOOKUP(CU18,DATA!$B$13:$C$19,2,0) -> 100 | CW18: =VLOOKUP($CU$1,DATA!$B$24:$C$45,2,0) -> 0.02 | CX18: =CV18*CW18/100 -> 0.02 | CY18: =CW18*$J18 -> 1.2 | DB18: Finished | DC18: =VLOOKUP(DB18,DATA!$B$13:$C$19,2,0) -> 100 | DD18: =VLOOKUP($DB$1,DATA!$B$24:$C$45,2,0) -> 0.01 | DE18: =DC18*DD18/100 -> 0.01 | DF18: =DD18*$J18 -> 0.6 | DI18: Finished | DJ18: =VLOOKUP(DI18,DATA!$B$13:$C$19,2,0) -> 100 | DK18: =VLOOKUP($DI$1,DATA!$B$24:$C$45,2,0) -> 0.03 | DL18: =DJ18*DK18/100 -> 0.03 | DM18: =DK18*$J18 -> 1.8 | DN18: Finished | DO18: =VLOOKUP(DN18,DATA!$B$13:$C$19,2,0) -> 100 | DP18: =VLOOKUP($DN$1,DATA!$B$24:$C$45,2,0) -> 0.07 | DQ18: =DO18*DP18/100 -> 0.07 | DR18: =DP18*$J18 -> 4.2 | DU18: Finished | DV18: =VLOOKUP(DU18,DATA!$B$13:$C$19,2,0) -> 100 | DW18: =VLOOKUP($DU$1,DATA!$B$24:$C$45,2,0) -> 0.04 | DX18: =DV18*DW18/100 -> 0.04 | DY18: =DW18*$J18 -> 2.4 | EB18: Finished | EC18: =VLOOKUP(EB18,DATA!$B$13:$C$19,2,0) -> 100 | ED18: =VLOOKUP($EB$1,DATA!$B$24:$C$45,2,0) -> 0.05 | EE18: =EC18*ED18/100 -> 0.05 | EF18: =ED18*$J18 -> 3 | EI18: Finished | EJ18: =VLOOKUP(EI18,DATA!$B$13:$C$19,2,0) -> 100 | EK18: =VLOOKUP($EI$1,DATA!$B$24:$C$45,2,0) -> 0.1 | EL18: =EJ18*EK18/100 -> 0.1 | EM18: =EK18*$J18 -> 6 | EP18: Finished | EQ18: =VLOOKUP(EP18,DATA!$B$13:$C$19,2,0) -> 100 | ER18: =VLOOKUP($EP$1,DATA!$B$24:$C$45,2,0) -> 0.03 | ES18: =EQ18*ER18/100 -> 0.03 | ET18: =ER18*$J18 -> 1.8 | EU18: =SUM( IF(AH18<>"Finished",AL18,0) + N("READ INFO"), IF(AM18<>"Finished",AQ18,0) + N("LONG LEAD"), IF(AT18<>"Finished",AX18,0) + N("SWITCH LAYOUT"), IF(CJ18<>"Finished",CT18,0) + N("DESIGN"), IF(CU18<>"Finished",CY18,0) + N("REVISION"), IF(DB18<>"Finished",DF18,0) + N("CUST APRVL"), IF(DI18<>"Finished",DM18,0) + N("MEETINGS"), IF(DN18<>"Finished",DR18,0) + N("PURCHASING"), IF(DU18<>"Finished",DY18,0) + N("HANDOFF"), IF(EB18<>"Finished",EF18,0) + N("SUPPORT"), IF(EI18<>"Finished",EM18,0) + N("DOCUMENTATTION"), IF(EP18<>"Finished",ET18,0) + N("REDLINES"), ) -> 0 | EV18: ADRIAN CABELLO | EW18: ADRIAN CABELLO
A19: MX | B19: Open | C19: OP Mobility | D19: Spoiler punch & Stick Assembly | E19: Jeep J4U Complex Machines | F19: 3297 | G19: 3297-A | H19: 60 | J19: =BaseDeDatos[[#This Row],[Budget CS]]+BaseDeDatos[[#This Row],[Change Orders Budget]] -> 60 | K19: =IFERROR(VLOOKUP(G19, DATA!H:I, 2, FALSE), 0)+BaseDeDatos[[#This Row],[Labor Spend on Design errors]]+BaseDeDatos[[#This Row],[Labor Spent Customer changes]] -> 9 | N19: =AK19+AP19+AW19+CQ19+CX19+DE19+DL19+DQ19+DX19+EE19+EL19+ES19 -> 0.374 | O19: =J19*S19 -> 9 | P19: 29.7 | Q19: =BaseDeDatos[[#This Row],[Budget]]*BaseDeDatos[[#This Row],[Labor Rate from CS]] -> 1782 | R19: =BaseDeDatos[[#This Row],[Labor Spent]]*BaseDeDatos[[#This Row],[Labor Rate from CS]] -> 267.3 | S19: =K19/J19 -> 0.15 | T19: 136797 | U19: 14706.66 | V19: 12259.64 | W19: 35639.11 | X19: 35639.11 | AA19: 112384.96 | AB19: =AA19-X19-Q19 -> 74963.85 | AC19: =SUM(AB19,X19,R19,BaseDeDatos[[#This Row],[Additionals cost]]) -> 123129.9 | AD19: 0.1785 | AE19: 0.1821 | AF19: =(T19-SUM(X19,AB19,R19))/T19 -> 0.18952711 | AH19: Finished | AI19: =VLOOKUP(AH19,DATA!$B$13:$C$19,2,0) -> 100 | AK19: =BaseDeDatos[[#This Row],[Read info Status]]*(AJ19)/100 -> 0 | AL19: =AJ19*$J19 -> 0 | AM19: Finished | AN19: =VLOOKUP(AM19,DATA!$B$13:$C$19,2,0) -> 100 | AO19: =VLOOKUP($AM$1,DATA!$B$24:$C$45,2,0) -> 0.05 | AP19: =AN19*AO19/100 -> 0.05 | AQ19: =AO19*$J19 -> 3 | AR19: 46044 | AT19: Not started | AU19: =VLOOKUP(AT19,DATA!$B$13:$C$19,2,0) -> 0 | AV19: =VLOOKUP($AT$1,DATA!$B$24:$C$45,2,0) -> 0.01 | AW19: =AU19*AV19/100 -> 0 | AX19: =AV19*$J19 -> 0.6 | AY19: 46083 | BA19: In process | BB19: =VLOOKUP(BA19,DATA!$B$13:$C$19,2,0) -> 50 | BC19: =VLOOKUP($BA$1,DATA!$B$24:$C$45,2,0) -> 0.01 | BD19: =BB19*BC19/100 -> 0.005 | BE19: =BC19*$J19 -> 0.6 | BF19: In process | BG19: =VLOOKUP(BF19,DATA!$B$13:$C$19,2,0) -> 50 | BH19: =VLOOKUP($BF$1,DATA!$B$24:$C$45,2,0) -> 0.08 | BI19: =BG19*BH19/100 -> 0.04 | BJ19: =BH19*$J19 -> 4.8 | BK19: In process | BL19: =VLOOKUP(BK19,DATA!$B$13:$C$19,2,0) -> 50 | BM19: =VLOOKUP($BK$1,DATA!$B$24:$C$45,2,0) -> 0.18 | BN19: =BL19*BM19/100 -> 0.09 | BO19: =BM19*$J19 -> 10.8 | BP19: In process | BQ19: =VLOOKUP(BP19,DATA!$B$13:$C$19,2,0) -> 50 | BR19: =VLOOKUP($BP$1,DATA!$B$24:$C$45,2,0) -> 0.28 | BS19: =BQ19*BR19/100 -> 0.14 | BT19: =BR19*$J19 -> 16.8 | BU19: In process | BV19: =VLOOKUP(BU19,DATA!$B$13:$C$19,2,0) -> 50 | BW19: =VLOOKUP($BU$1,DATA!$B$24:$C$45,2,0) -> 0.15 | BX19: =BV19*BW19/100 -> 0.075 | BY19: =BW19*$J19 -> 9 | BZ19: In process | CA19: =VLOOKUP(BZ19,DATA!$B$13:$C$19,2,0) -> 50 | CB19: =VLOOKUP($BZ$1,DATA!$B$24:$C$45,2,0) -> 0.16 | CC19: =CA19*CB19/100 -> 0.08 | CD19: =CB19*$J19 -> 9.6 | CE19: In process | CF19: =VLOOKUP(CE19,DATA!$B$13:$C$19,2,0) -> 50 | CG19: =VLOOKUP($CE$1,DATA!$B$24:$C$45,2,0) -> 0.13 | CH19: =CF19*CG19/100 -> 0.065 | CI19: =CG19*$J19 -> 7.8 | CJ19: In process | CK19: =VLOOKUP(CJ19,DATA!$B$13:$C$19,2,0) -> 50 | CL19: =VLOOKUP($CJ$1,DATA!$B$24:$C$45,2,0) -> 0.01 | CM19: =CK19*CL19/100 -> 0.005 | CN19: =CL19*$J19 -> 0.6 | CO19: =CM19+CH19+CC19+BX19+BS19+BN19+BI19+BD19 -> 0.5 | CP19: =VLOOKUP($CO$1,DATA!$B$24:$C$45,2,0) -> 0.54 | CQ19: =CP19*CO19 -> 0.27 | CR19: =CP19*$J19 -> 32.4 | CS19: =CQ19*$J19 -> 16.2 | CT19: =CR19-CS19 -> 16.2 | CU19: Draft | CV19: =VLOOKUP(CU19,DATA!$B$13:$C$19,2,0) -> 25 | CW19: =VLOOKUP($CU$1,DATA!$B$24:$C$45,2,0) -> 0.02 | CX19: =CV19*CW19/100 -> 0.005 | CY19: =CW19*$J19 -> 1.2 | CZ19: 46094 | DB19: Under review | DC19: =VLOOKUP(DB19,DATA!$B$13:$C$19,2,0) -> 90 | DD19: =VLOOKUP($DB$1,DATA!$B$24:$C$45,2,0) -> 0.01 | DE19: =DC19*DD19/100 -> 0.009 | DF19: =DD19*$J19 -> 0.6 | DG19: 46098 | DI19: Almost ready | DJ19: =VLOOKUP(DI19,DATA!$B$13:$C$19,2,0) -> 75 | DK19: =VLOOKUP($DI$1,DATA!$B$24:$C$45,2,0) -> 0.03 | DL19: =DJ19*DK19/100 -> 0.0225 | DM19: =DK19*$J19 -> 1.8 | DN19: Draft | DO19: =VLOOKUP(DN19,DATA!$B$13:$C$19,2,0) -> 25 | DP19: =VLOOKUP($DN$1,DATA!$B$24:$C$45,2,0) -> 0.07 | DQ19: =DO19*DP19/100 -> 0.0175 | DR19: =DP19*$J19 -> 4.2 | DS19: 46099 | DU19: Not started | DV19: =VLOOKUP(DU19,DATA!$B$13:$C$19,2,0) -> 0 | DW19: =VLOOKUP($DU$1,DATA!$B$24:$C$45,2,0) -> 0.04 | DX19: =DV19*DW19/100 -> 0 | DY19: =DW19*$J19 -> 2.4 | DZ19: 46101 | EB19: Not started | EC19: =VLOOKUP(EB19,DATA!$B$13:$C$19,2,0) -> 0 | ED19: =VLOOKUP($EB$1,DATA!$B$24:$C$45,2,0) -> 0.05 | EE19: =EC19*ED19/100 -> 0 | EF19: =ED19*$J19 -> 3 | EG19: 46122 | EI19: Not started | EJ19: =VLOOKUP(EI19,DATA!$B$13:$C$19,2,0) -> 0 | EK19: =VLOOKUP($EI$1,DATA!$B$24:$C$45,2,0) -> 0.1 | EL19: =EJ19*EK19/100 -> 0 | EM19: =EK19*$J19 -> 6 | EN19: 46104 | EP19: Not started | EQ19: =VLOOKUP(EP19,DATA!$B$13:$C$19,2,0) -> 0 | ER19: =VLOOKUP($EP$1,DATA!$B$24:$C$45,2,0) -> 0.03 | ES19: =EQ19*ER19/100 -> 0 | ET19: =ER19*$J19 -> 1.8 | EU19: =SUM( IF(AH19<>"Finished",AL19,0) + N("READ INFO"), IF(AM19<>"Finished",AQ19,0) + N("LONG LEAD"), IF(AT19<>"Finished",AX19,0) + N("SWITCH LAYOUT"), IF(CJ19<>"Finished",CT19,0) + N("DESIGN"), IF(CU19<>"Finished",CY19,0) + N("REVISION"), IF(DB19<>"Finished",DF19,0) + N("CUST APRVL"), IF(DI19<>"Finished",DM19,0) + N("MEETINGS"), IF(DN19<>"Finished",DR19,0) + N("PURCHASING"), IF(DU19<>"Finished",DY19,0) + N("HANDOFF"), IF(EB19<>"Finished",EF19,0) + N("SUPPORT"), IF(EI19<>"Finished",EM19,0) + N("DOCUMENTATTION"), IF(EP19<>"Finished",ET19,0) + N("REDLINES"), ) -> 37.8 | EV19: ADRIAN CABELLO | EW19: FIDEL MALDONADO
A20: MX | B20: Open | C20: OP Mobility | D20: Masking cell | E20: Jeep J4U Complex Machines | F20: 3297 | G20: 3297-B | H20: 120 | J20: =BaseDeDatos[[#This Row],[Budget CS]]+BaseDeDatos[[#This Row],[Change Orders Budget]] -> 120 | K20: =IFERROR(VLOOKUP(G20, DATA!H:I, 2, FALSE), 0)+BaseDeDatos[[#This Row],[Labor Spend on Design errors]]+BaseDeDatos[[#This Row],[Labor Spent Customer changes]] -> 77.5 | N20: =AK20+AP20+AW20+CQ20+CX20+DE20+DL20+DQ20+DX20+EE20+EL20+ES20 -> 0.8189 | O20: =J20*S20 -> 77.5 | P20: 29.7 | Q20: =BaseDeDatos[[#This Row],[Budget]]*BaseDeDatos[[#This Row],[Labor Rate from CS]] -> 3564 | R20: =BaseDeDatos[[#This Row],[Labor Spent]]*BaseDeDatos[[#This Row],[Labor Rate from CS]] -> 2301.75 | S20: =K20/J20 -> 0.64583333 | T20: 203035 | U20: 14706.66 | V20: 12259.64 | W20: 52586.21 | X20: 52586.21 | AA20: 165616.77 | AB20: =AA20-X20-Q20 -> 109466.56 | AC20: =SUM(AB20,X20,R20,BaseDeDatos[[#This Row],[Additionals cost]]) -> 176614.16 | AD20: 0.1843 | AE20: 0.1821 | AF20: =(T20-SUM(X20,AB20,R20))/T20 -> 0.19051139 | AH20: Finished | AI20: =VLOOKUP(AH20,DATA!$B$13:$C$19,2,0) -> 100 | AK20: =BaseDeDatos[[#This Row],[Read info Status]]*(AJ20)/100 -> 0 | AL20: =AJ20*$J20 -> 0 | AM20: Finished | AN20: =VLOOKUP(AM20,DATA!$B$13:$C$19,2,0) -> 100 | AO20: =VLOOKUP($AM$1,DATA!$B$24:$C$45,2,0) -> 0.05 | AP20: =AN20*AO20/100 -> 0.05 | AQ20: =AO20*$J20 -> 6 | AR20: 46044 | AT20: Finished | AU20: =VLOOKUP(AT20,DATA!$B$13:$C$19,2,0) -> 100 | AV20: =VLOOKUP($AT$1,DATA!$B$24:$C$45,2,0) -> 0.01 | AW20: =AU20*AV20/100 -> 0.01 | AX20: =AV20*$J20 -> 1.2 | AY20: 46083 | BA20: Finished | BB20: =VLOOKUP(BA20,DATA!$B$13:$C$19,2,0) -> 100 | BC20: =VLOOKUP($BA$1,DATA!$B$24:$C$45,2,0) -> 0.01 | BD20: =BB20*BC20/100 -> 0.01 | BE20: =BC20*$J20 -> 1.2 | BF20: Finished | BG20: =VLOOKUP(BF20,DATA!$B$13:$C$19,2,0) -> 100 | BH20: =VLOOKUP($BF$1,DATA!$B$24:$C$45,2,0) -> 0.08 | BI20: =BG20*BH20/100 -> 0.08 | BJ20: =BH20*$J20 -> 9.6 | BK20: Finished | BL20: =VLOOKUP(BK20,DATA!$B$13:$C$19,2,0) -> 100 | BM20: =VLOOKUP($BK$1,DATA!$B$24:$C$45,2,0) -> 0.18 | BN20: =BL20*BM20/100 -> 0.18 | BO20: =BM20*$J20 -> 21.6 | BP20: Finished | BQ20: =VLOOKUP(BP20,DATA!$B$13:$C$19,2,0) -> 100 | BR20: =VLOOKUP($BP$1,DATA!$B$24:$C$45,2,0) -> 0.28 | BS20: =BQ20*BR20/100 -> 0.28 | BT20: =BR20*$J20 -> 33.6 | BU20: Under review | BV20: =VLOOKUP(BU20,DATA!$B$13:$C$19,2,0) -> 90 | BW20: =VLOOKUP($BU$1,DATA!$B$24:$C$45,2,0) -> 0.15 | BX20: =BV20*BW20/100 -> 0.135 | BY20: =BW20*$J20 -> 18 | BZ20: Finished | CA20: =VLOOKUP(BZ20,DATA!$B$13:$C$19,2,0) -> 100 | CB20: =VLOOKUP($BZ$1,DATA!$B$24:$C$45,2,0) -> 0.16 | CC20: =CA20*CB20/100 -> 0.16 | CD20: =CB20*$J20 -> 19.2 | CE20: Finished | CF20: =VLOOKUP(CE20,DATA!$B$13:$C$19,2,0) -> 100 | CG20: =VLOOKUP($CE$1,DATA!$B$24:$C$45,2,0) -> 0.13 | CH20: =CF20*CG20/100 -> 0.13 | CI20: =CG20*$J20 -> 15.6 | CJ20: Finished | CK20: =VLOOKUP(CJ20,DATA!$B$13:$C$19,2,0) -> 100 | CL20: =VLOOKUP($CJ$1,DATA!$B$24:$C$45,2,0) -> 0.01 | CM20: =CK20*CL20/100 -> 0.01 | CN20: =CL20*$J20 -> 1.2 | CO20: =CM20+CH20+CC20+BX20+BS20+BN20+BI20+BD20 -> 0.985 | CP20: =VLOOKUP($CO$1,DATA!$B$24:$C$45,2,0) -> 0.54 | CQ20: =CP20*CO20 -> 0.5319 | CR20: =CP20*$J20 -> 64.8 | CS20: =CQ20*$J20 -> 63.828 | CT20: =CR20-CS20 -> 0.972 | CU20: Finished | CV20: =VLOOKUP(CU20,DATA!$B$13:$C$19,2,0) -> 100 | CW20: =VLOOKUP($CU$1,DATA!$B$24:$C$45,2,0) -> 0.02 | CX20: =CV20*CW20/100 -> 0.02 | CY20: =CW20*$J20 -> 2.4 | CZ20: 46094 | DB20: Under review | DC20: =VLOOKUP(DB20,DATA!$B$13:$C$19,2,0) -> 90 | DD20: =VLOOKUP($DB$1,DATA!$B$24:$C$45,2,0) -> 0.01 | DE20: =DC20*DD20/100 -> 0.009 | DF20: =DD20*$J20 -> 1.2 | DG20: 46098 | DI20: Finished | DJ20: =VLOOKUP(DI20,DATA!$B$13:$C$19,2,0) -> 100 | DK20: =VLOOKUP($DI$1,DATA!$B$24:$C$45,2,0) -> 0.03 | DL20: =DJ20*DK20/100 -> 0.03 | DM20: =DK20*$J20 -> 3.6 | DN20: Under review | DO20: =VLOOKUP(DN20,DATA!$B$13:$C$19,2,0) -> 90 | DP20: =VLOOKUP($DN$1,DATA!$B$24:$C$45,2,0) -> 0.07 | DQ20: =DO20*DP20/100 -> 0.063 | DR20: =DP20*$J20 -> 8.4 | DS20: 46099 | DU20: Almost ready | DV20: =VLOOKUP(DU20,DATA!$B$13:$C$19,2,0) -> 75 | DW20: =VLOOKUP($DU$1,DATA!$B$24:$C$45,2,0) -> 0.04 | DX20: =DV20*DW20/100 -> 0.03 | DY20: =DW20*$J20 -> 4.8 | DZ20: 46101 | EB20: Not started | EC20: =VLOOKUP(EB20,DATA!$B$13:$C$19,2,0) -> 0 | ED20: =VLOOKUP($EB$1,DATA!$B$24:$C$45,2,0) -> 0.05 | EE20: =EC20*ED20/100 -> 0 | EF20: =ED20*$J20 -> 6 | EG20: 46122 | EI20: Almost ready | EJ20: =VLOOKUP(EI20,DATA!$B$13:$C$19,2,0) -> 75 | EK20: =VLOOKUP($EI$1,DATA!$B$24:$C$45,2,0) -> 0.1 | EL20: =EJ20*EK20/100 -> 0.075 | EM20: =EK20*$J20 -> 12 | EN20: 46104 | EP20: Not started | EQ20: =VLOOKUP(EP20,DATA!$B$13:$C$19,2,0) -> 0 | ER20: =VLOOKUP($EP$1,DATA!$B$24:$C$45,2,0) -> 0.03 | ES20: =EQ20*ER20/100 -> 0 | ET20: =ER20*$J20 -> 3.6 | EU20: =SUM( IF(AH20<>"Finished",AL20,0) + N("READ INFO"), IF(AM20<>"Finished",AQ20,0) + N("LONG LEAD"), IF(AT20<>"Finished",AX20,0) + N("SWITCH LAYOUT"), IF(CJ20<>"Finished",CT20,0) + N("DESIGN"), IF(CU20<>"Finished",CY20,0) + N("REVISION"), IF(DB20<>"Finished",DF20,0) + N("CUST APRVL"), IF(DI20<>"Finished",DM20,0) + N("MEETINGS"), IF(DN20<>"Finished",DR20,0) + N("PURCHASING"), IF(DU20<>"Finished",DY20,0) + N("HANDOFF"), IF(EB20<>"Finished",EF20,0) + N("SUPPORT"), IF(EI20<>"Finished",EM20,0) + N("DOCUMENTATTION"), IF(EP20<>"Finished",ET20,0) + N("REDLINES"), ) -> 36 | EV20: ADRIAN CABELLO | EW20: FIDEL MALDONADO
A21: MX | B21: Open | C21: OP Mobility | D21: Masking cell | E21: Jeep J4U Complex Machines | F21: 3297 | G21: 3297-C | H21: 36 | J21: =BaseDeDatos[[#This Row],[Budget CS]]+BaseDeDatos[[#This Row],[Change Orders Budget]] -> 36 | K21: =IFERROR(VLOOKUP(G21, DATA!H:I, 2, FALSE), 0)+BaseDeDatos[[#This Row],[Labor Spend on Design errors]]+BaseDeDatos[[#This Row],[Labor Spent Customer changes]] -> 70.5 | N21: =AK21+AP21+AW21+CQ21+CX21+DE21+DL21+DQ21+DX21+EE21+EL21+ES21 -> 0.8189 | O21: =J21*S21 -> 70.5 | P21: 29.7 | Q21: =BaseDeDatos[[#This Row],[Budget]]*BaseDeDatos[[#This Row],[Labor Rate from CS]] -> 1069.2 | R21: =BaseDeDatos[[#This Row],[Labor Spent]]*BaseDeDatos[[#This Row],[Labor Rate from CS]] -> 2093.85 | S21: =K21/J21 -> 1.9583333 | T21: 183548 | U21: 14706.66 | V21: 12259.64 | W21: 52586.21 | X21: 52586.21 | AA21: 149369.44 | AB21: =AA21-X21-Q21 -> 95714.03 | AC21: =SUM(AB21,X21,R21,BaseDeDatos[[#This Row],[Additionals cost]]) -> 162653.73 | AD21: 0.1862 | AE21: 0.1821 | AF21: =(T21-SUM(X21,AB21,R21))/T21 -> 0.18062801 | AH21: Finished | AI21: =VLOOKUP(AH21,DATA!$B$13:$C$19,2,0) -> 100 | AK21: =BaseDeDatos[[#This Row],[Read info Status]]*(AJ21)/100 -> 0 | AL21: =AJ21*$J21 -> 0 | AM21: Finished | AN21: =VLOOKUP(AM21,DATA!$B$13:$C$19,2,0) -> 100 | AO21: =VLOOKUP($AM$1,DATA!$B$24:$C$45,2,0) -> 0.05 | AP21: =AN21*AO21/100 -> 0.05 | AQ21: =AO21*$J21 -> 1.8 | AR21: 46044 | AT21: Finished | AU21: =VLOOKUP(AT21,DATA!$B$13:$C$19,2,0) -> 100 | AV21: =VLOOKUP($AT$1,DATA!$B$24:$C$45,2,0) -> 0.01 | AW21: =AU21*AV21/100 -> 0.01 | AX21: =AV21*$J21 -> 0.36 | AY21: 46083 | BA21: Finished | BB21: =VLOOKUP(BA21,DATA!$B$13:$C$19,2,0) -> 100 | BC21: =VLOOKUP($BA$1,DATA!$B$24:$C$45,2,0) -> 0.01 | BD21: =BB21*BC21/100 -> 0.01 | BE21: =BC21*$J21 -> 0.36 | BF21: Finished | BG21: =VLOOKUP(BF21,DATA!$B$13:$C$19,2,0) -> 100 | BH21: =VLOOKUP($BF$1,DATA!$B$24:$C$45,2,0) -> 0.08 | BI21: =BG21*BH21/100 -> 0.08 | BJ21: =BH21*$J21 -> 2.88 | BK21: Finished | BL21: =VLOOKUP(BK21,DATA!$B$13:$C$19,2,0) -> 100 | BM21: =VLOOKUP($BK$1,DATA!$B$24:$C$45,2,0) -> 0.18 | BN21: =BL21*BM21/100 -> 0.18 | BO21: =BM21*$J21 -> 6.48 | BP21: Finished | BQ21: =VLOOKUP(BP21,DATA!$B$13:$C$19,2,0) -> 100 | BR21: =VLOOKUP($BP$1,DATA!$B$24:$C$45,2,0) -> 0.28 | BS21: =BQ21*BR21/100 -> 0.28 | BT21: =BR21*$J21 -> 10.08 | BU21: Under review | BV21: =VLOOKUP(BU21,DATA!$B$13:$C$19,2,0) -> 90 | BW21: =VLOOKUP($BU$1,DATA!$B$24:$C$45,2,0) -> 0.15 | BX21: =BV21*BW21/100 -> 0.135 | BY21: =BW21*$J21 -> 5.4 | BZ21: Finished | CA21: =VLOOKUP(BZ21,DATA!$B$13:$C$19,2,0) -> 100 | CB21: =VLOOKUP($BZ$1,DATA!$B$24:$C$45,2,0) -> 0.16 | CC21: =CA21*CB21/100 -> 0.16 | CD21: =CB21*$J21 -> 5.76 | CE21: Finished | CF21: =VLOOKUP(CE21,DATA!$B$13:$C$19,2,0) -> 100 | CG21: =VLOOKUP($CE$1,DATA!$B$24:$C$45,2,0) -> 0.13 | CH21: =CF21*CG21/100 -> 0.13 | CI21: =CG21*$J21 -> 4.68 | CJ21: Finished | CK21: =VLOOKUP(CJ21,DATA!$B$13:$C$19,2,0) -> 100 | CL21: =VLOOKUP($CJ$1,DATA!$B$24:$C$45,2,0) -> 0.01 | CM21: =CK21*CL21/100 -> 0.01 | CN21: =CL21*$J21 -> 0.36 | CO21: =CM21+CH21+CC21+BX21+BS21+BN21+BI21+BD21 -> 0.985 | CP21: =VLOOKUP($CO$1,DATA!$B$24:$C$45,2,0) -> 0.54 | CQ21: =CP21*CO21 -> 0.5319 | CR21: =CP21*$J21 -> 19.44 | CS21: =CQ21*$J21 -> 19.1484 | CT21: =CR21-CS21 -> 0.2916 | CU21: Finished | CV21: =VLOOKUP(CU21,DATA!$B$13:$C$19,2,0) -> 100 | CW21: =VLOOKUP($CU$1,DATA!$B$24:$C$45,2,0) -> 0.02 | CX21: =CV21*CW21/100 -> 0.02 | CY21: =CW21*$J21 -> 0.72 | CZ21: 46094 | DB21: Under review | DC21: =VLOOKUP(DB21,DATA!$B$13:$C$19,2,0) -> 90 | DD21: =VLOOKUP($DB$1,DATA!$B$24:$C$45,2,0) -> 0.01 | DE21: =DC21*DD21/100 -> 0.009 | DF21: =DD21*$J21 -> 0.36 | DG21: 46098 | DI21: Finished | DJ21: =VLOOKUP(DI21,DATA!$B$13:$C$19,2,0) -> 100 | DK21: =VLOOKUP($DI$1,DATA!$B$24:$C$45,2,0) -> 0.03 | DL21: =DJ21*DK21/100 -> 0.03 | DM21: =DK21*$J21 -> 1.08 | DN21: Under review | DO21: =VLOOKUP(DN21,DATA!$B$13:$C$19,2,0) -> 90 | DP21: =VLOOKUP($DN$1,DATA!$B$24:$C$45,2,0) -> 0.07 | DQ21: =DO21*DP21/100 -> 0.063 | DR21: =DP21*$J21 -> 2.52 | DS21: 46099 | DU21: Almost ready | DV21: =VLOOKUP(DU21,DATA!$B$13:$C$19,2,0) -> 75 | DW21: =VLOOKUP($DU$1,DATA!$B$24:$C$45,2,0) -> 0.04 | DX21: =DV21*DW21/100 -> 0.03 | DY21: =DW21*$J21 -> 1.44 | DZ21: 46101 | EB21: Not started | EC21: =VLOOKUP(EB21,DATA!$B$13:$C$19,2,0) -> 0 | ED21: =VLOOKUP($EB$1,DATA!$B$24:$C$45,2,0) -> 0.05 | EE21: =EC21*ED21/100 -> 0 | EF21: =ED21*$J21 -> 1.8 | EG21: 46122 | EI21: Almost ready | EJ21: =VLOOKUP(EI21,DATA!$B$13:$C$19,2,0) -> 75 | EK21: =VLOOKUP($EI$1,DATA!$B$24:$C$45,2,0) -> 0.1 | EL21: =EJ21*EK21/100 -> 0.075 | EM21: =EK21*$J21 -> 3.6 | EN21: 46104 | EP21: Not started | EQ21: =VLOOKUP(EP21,DATA!$B$13:$C$19,2,0) -> 0 | ER21: =VLOOKUP($EP$1,DATA!$B$24:$C$45,2,0) -> 0.03 | ES21: =EQ21*ER21/100 -> 0 | ET21: =ER21*$J21 -> 1.08 | EU21: =SUM( IF(AH21<>"Finished",AL21,0) + N("READ INFO"), IF(AM21<>"Finished",AQ21,0) + N("LONG LEAD"), IF(AT21<>"Finished",AX21,0) + N("SWITCH LAYOUT"), IF(CJ21<>"Finished",CT21,0) + N("DESIGN"), IF(CU21<>"Finished",CY21,0) + N("REVISION"), IF(DB21<>"Finished",DF21,0) + N("CUST APRVL"), IF(DI21<>"Finished",DM21,0) + N("MEETINGS"), IF(DN21<>"Finished",DR21,0) + N("PURCHASING"), IF(DU21<>"Finished",DY21,0) + N("HANDOFF"), IF(EB21<>"Finished",EF21,0) + N("SUPPORT"), IF(EI21<>"Finished",EM21,0) + N("DOCUMENTATTION"), IF(EP21<>"Finished",ET21,0) + N("REDLINES"), ) -> 10.8 | EV21: ADRIAN CABELLO | EW21: FIDEL MALDONADO
A22: MI | B22: Open | C22: OP Mobility | D22: 3300 CO Phase 3 | E22: Conveyor Ergonomy Changes | F22: 3300-CO06 | G22: 3300-CO06-A | H22: 20 | J22: =BaseDeDatos[[#This Row],[Budget CS]]+BaseDeDatos[[#This Row],[Change Orders Budget]] -> 20 | K22: =IFERROR(VLOOKUP(G22, DATA!H:I, 2, FALSE), 0)+BaseDeDatos[[#This Row],[Labor Spend on Design errors]]+BaseDeDatos[[#This Row],[Labor Spent Customer changes]] -> 4 | N22: =AK22+AP22+AW22+CQ22+CX22+DE22+DL22+DQ22+DX22+EE22+EL22+ES22 -> 0.13975 | O22: =J22*S22 -> 4 | P22: 26.73 | Q22: =BaseDeDatos[[#This Row],[Budget]]*BaseDeDatos[[#This Row],[Labor Rate from CS]] -> 534.6 | R22: =BaseDeDatos[[#This Row],[Labor Spent]]*BaseDeDatos[[#This Row],[Labor Rate from CS]] -> 106.92 | S22: =K22/J22 -> 0.2 | T22: 89500 | W22: 22363.57 | X22: 22363.57 | AA22: 126203.11 | AB22: =AA22-X22-Q22 -> 103304.94 | AC22: =SUM(AB22,X22,R22,BaseDeDatos[[#This Row],[Additionals cost]]) -> 125775.43 | AD22: -0.4101 | AE22: -0.0031 | AF22: =(T22-SUM(X22,AB22,R22))/T22 -> -0.40531207 | AH22: Finished | AI22: =VLOOKUP(AH22,DATA!$B$13:$C$19,2,0) -> 100 | AK22: =BaseDeDatos[[#This Row],[Read info Status]]*(AJ22)/100 -> 0 | AL22: =AJ22*$J22 -> 0 | AM22: In process | AN22: =VLOOKUP(AM22,DATA!$B$13:$C$19,2,0) -> 50 | AO22: =VLOOKUP($AM$1,DATA!$B$24:$C$45,2,0) -> 0.05 | AP22: =AN22*AO22/100 -> 0.025 | AQ22: =AO22*$J22 -> 1 | AT22: Not started | AU22: =VLOOKUP(AT22,DATA!$B$13:$C$19,2,0) -> 0 | AV22: =VLOOKUP($AT$1,DATA!$B$24:$C$45,2,0) -> 0.01 | AW22: =AU22*AV22/100 -> 0 | AX22: =AV22*$J22 -> 0.2 | BA22: Finished | BB22: =VLOOKUP(BA22,DATA!$B$13:$C$19,2,0) -> 100 | BC22: =VLOOKUP($BA$1,DATA!$B$24:$C$45,2,0) -> 0.01 | BD22: =BB22*BC22/100 -> 0.01 | BE22: =BC22*$J22 -> 0.2 | BF22: Draft | BG22: =VLOOKUP(BF22,DATA!$B$13:$C$19,2,0) -> 25 | BH22: =VLOOKUP($BF$1,DATA!$B$24:$C$45,2,0) -> 0.08 | BI22: =BG22*BH22/100 -> 0.02 | BJ22: =BH22*$J22 -> 1.6 | BK22: Not started | BL22: =VLOOKUP(BK22,DATA!$B$13:$C$19,2,0) -> 0 | BM22: =VLOOKUP($BK$1,DATA!$B$24:$C$45,2,0) -> 0.18 | BN22: =BL22*BM22/100 -> 0 | BO22: =BM22*$J22 -> 3.6 | BP22: Not started | BQ22: =VLOOKUP(BP22,DATA!$B$13:$C$19,2,0) -> 0 | BR22: =VLOOKUP($BP$1,DATA!$B$24:$C$45,2,0) -> 0.28 | BS22: =BQ22*BR22/100 -> 0 | BT22: =BR22*$J22 -> 5.6 | BU22: Finished | BV22: =VLOOKUP(BU22,DATA!$B$13:$C$19,2,0) -> 100 | BW22: =VLOOKUP($BU$1,DATA!$B$24:$C$45,2,0) -> 0.15 | BX22: =BV22*BW22/100 -> 0.15 | BY22: =BW22*$J22 -> 3 | BZ22: Not started | CA22: =VLOOKUP(BZ22,DATA!$B$13:$C$19,2,0) -> 0 | CB22: =VLOOKUP($BZ$1,DATA!$B$24:$C$45,2,0) -> 0.16 | CC22: =CA22*CB22/100 -> 0 | CD22: =CB22*$J22 -> 3.2 | CE22: Draft | CF22: =VLOOKUP(CE22,DATA!$B$13:$C$19,2,0) -> 25 | CG22: =VLOOKUP($CE$1,DATA!$B$24:$C$45,2,0) -> 0.13 | CH22: =CF22*CG22/100 -> 0.0325 | CI22: =CG22*$J22 -> 2.6 | CJ22: Not started | CK22: =VLOOKUP(CJ22,DATA!$B$13:$C$19,2,0) -> 0 | CL22: =VLOOKUP($CJ$1,DATA!$B$24:$C$45,2,0) -> 0.01 | CM22: =CK22*CL22/100 -> 0 | CN22: =CL22*$J22 -> 0.2 | CO22: =CM22+CH22+CC22+BX22+BS22+BN22+BI22+BD22 -> 0.2125 | CP22: =VLOOKUP($CO$1,DATA!$B$24:$C$45,2,0) -> 0.54 | CQ22: =CP22*CO22 -> 0.11475 | CR22: =CP22*$J22 -> 10.8 | CS22: =CQ22*$J22 -> 2.295 | CT22: =CR22-CS22 -> 8.505 | CU22: Not started | CV22: =VLOOKUP(CU22,DATA!$B$13:$C$19,2,0) -> 0 | CW22: =VLOOKUP($CU$1,DATA!$B$24:$C$45,2,0) -> 0.02 | CX22: =CV22*CW22/100 -> 0 | CY22: =CW22*$J22 -> 0.4 | DB22: Not started | DC22: =VLOOKUP(DB22,DATA!$B$13:$C$19,2,0) -> 0 | DD22: =VLOOKUP($DB$1,DATA!$B$24:$C$45,2,0) -> 0.01 | DE22: =DC22*DD22/100 -> 0 | DF22: =DD22*$J22 -> 0.2 | DI22: Not started | DJ22: =VLOOKUP(DI22,DATA!$B$13:$C$19,2,0) -> 0 | DK22: =VLOOKUP($DI$1,DATA!$B$24:$C$45,2,0) -> 0.03 | DL22: =DJ22*DK22/100 -> 0 | DM22: =DK22*$J22 -> 0.6 | DN22: Not started | DO22: =VLOOKUP(DN22,DATA!$B$13:$C$19,2,0) -> 0 | DP22: =VLOOKUP($DN$1,DATA!$B$24:$C$45,2,0) -> 0.07 | DQ22: =DO22*DP22/100 -> 0 | DR22: =DP22*$J22 -> 1.4 | DU22: Not started | DV22: =VLOOKUP(DU22,DATA!$B$13:$C$19,2,0) -> 0 | DW22: =VLOOKUP($DU$1,DATA!$B$24:$C$45,2,0) -> 0.04 | DX22: =DV22*DW22/100 -> 0 | DY22: =DW22*$J22 -> 0.8 | EB22: Not started | EC22: =VLOOKUP(EB22,DATA!$B$13:$C$19,2,0) -> 0 | ED22: =VLOOKUP($EB$1,DATA!$B$24:$C$45,2,0) -> 0.05 | EE22: =EC22*ED22/100 -> 0 | EF22: =ED22*$J22 -> 1 | EI22: Not started | EJ22: =VLOOKUP(EI22,DATA!$B$13:$C$19,2,0) -> 0 | EK22: =VLOOKUP($EI$1,DATA!$B$24:$C$45,2,0) -> 0.1 | EL22: =EJ22*EK22/100 -> 0 | EM22: =EK22*$J22 -> 2 | EP22: Not started | EQ22: =VLOOKUP(EP22,DATA!$B$13:$C$19,2,0) -> 0 | ER22: =VLOOKUP($EP$1,DATA!$B$24:$C$45,2,0) -> 0.03 | ES22: =EQ22*ER22/100 -> 0 | ET22: =ER22*$J22 -> 0.6 | EU22: =SUM( IF(AH22<>"Finished",AL22,0) + N("READ INFO"), IF(AM22<>"Finished",AQ22,0) + N("LONG LEAD"), IF(AT22<>"Finished",AX22,0) + N("SWITCH LAYOUT"), IF(CJ22<>"Finished",CT22,0) + N("DESIGN"), IF(CU22<>"Finished",CY22,0) + N("REVISION"), IF(DB22<>"Finished",DF22,0) + N("CUST APRVL"), IF(DI22<>"Finished",DM22,0) + N("MEETINGS"), IF(DN22<>"Finished",DR22,0) + N("PURCHASING"), IF(DU22<>"Finished",DY22,0) + N("HANDOFF"), IF(EB22<>"Finished",EF22,0) + N("SUPPORT"), IF(EI22<>"Finished",EM22,0) + N("DOCUMENTATTION"), IF(EP22<>"Finished",ET22,0) + N("REDLINES"), ) -> 16.705 | EV22: ADRIAN CABELLO | EW22: JUAN ADAME
A23: MI | B23: Open | C23: OP Mobility | D23: 3300 CO Phase 3 | E23: PTL & Additions | F23: 3300-CO06 | G23: 3300-CO06-B | H23: 30 | J23: =BaseDeDatos[[#This Row],[Budget CS]]+BaseDeDatos[[#This Row],[Change Orders Budget]] -> 30 | K23: =IFERROR(VLOOKUP(G23, DATA!H:I, 2, FALSE), 0)+BaseDeDatos[[#This Row],[Labor Spend on Design errors]]+BaseDeDatos[[#This Row],[Labor Spent Customer changes]] -> 3 | N23: =AK23+AP23+AW23+CQ23+CX23+DE23+DL23+DQ23+DX23+EE23+EL23+ES23 -> 0.22615 | O23: =J23*S23 -> 3 | P23: 26.73 | Q23: =BaseDeDatos[[#This Row],[Budget]]*BaseDeDatos[[#This Row],[Labor Rate from CS]] -> 801.9 | R23: =BaseDeDatos[[#This Row],[Labor Spent]]*BaseDeDatos[[#This Row],[Labor Rate from CS]] -> 80.19 | S23: =K23/J23 -> 0.1 | T23: 143300 | W23: 13794.08 | X23: 13794.08 | AA23: 112472.95 | AB23: =AA23-X23-Q23 -> 97876.97 | AC23: =SUM(AB23,X23,R23,BaseDeDatos[[#This Row],[Additionals cost]]) -> 111751.24 | AD23: 0.2151 | AE23: -0.0031 | AF23: =(T23-SUM(X23,AB23,R23))/T23 -> 0.22015883 | AH23: Finished | AI23: =VLOOKUP(AH23,DATA!$B$13:$C$19,2,0) -> 100 | AK23: =BaseDeDatos[[#This Row],[Read info Status]]*(AJ23)/100 -> 0 | AL23: =AJ23*$J23 -> 0 | AM23: In process | AN23: =VLOOKUP(AM23,DATA!$B$13:$C$19,2,0) -> 50 | AO23: =VLOOKUP($AM$1,DATA!$B$24:$C$45,2,0) -> 0.05 | AP23: =AN23*AO23/100 -> 0.025 | AQ23: =AO23*$J23 -> 1.5 | AT23: Not started | AU23: =VLOOKUP(AT23,DATA!$B$13:$C$19,2,0) -> 0 | AV23: =VLOOKUP($AT$1,DATA!$B$24:$C$45,2,0) -> 0.01 | AW23: =AU23*AV23/100 -> 0 | AX23: =AV23*$J23 -> 0.3 | BA23: Finished | BB23: =VLOOKUP(BA23,DATA!$B$13:$C$19,2,0) -> 100 | BC23: =VLOOKUP($BA$1,DATA!$B$24:$C$45,2,0) -> 0.01 | BD23: =BB23*BC23/100 -> 0.01 | BE23: =BC23*$J23 -> 0.3 | BF23: Draft | BG23: =VLOOKUP(BF23,DATA!$B$13:$C$19,2,0) -> 25 | BH23: =VLOOKUP($BF$1,DATA!$B$24:$C$45,2,0) -> 0.08 | BI23: =BG23*BH23/100 -> 0.02 | BJ23: =BH23*$J23 -> 2.4 | BK23: Not started | BL23: =VLOOKUP(BK23,DATA!$B$13:$C$19,2,0) -> 0 | BM23: =VLOOKUP($BK$1,DATA!$B$24:$C$45,2,0) -> 0.18 | BN23: =BL23*BM23/100 -> 0 | BO23: =BM23*$J23 -> 5.4 | BP23: Not started | BQ23: =VLOOKUP(BP23,DATA!$B$13:$C$19,2,0) -> 0 | BR23: =VLOOKUP($BP$1,DATA!$B$24:$C$45,2,0) -> 0.28 | BS23: =BQ23*BR23/100 -> 0 | BT23: =BR23*$J23 -> 8.4 | BU23: Finished | BV23: =VLOOKUP(BU23,DATA!$B$13:$C$19,2,0) -> 100 | BW23: =VLOOKUP($BU$1,DATA!$B$24:$C$45,2,0) -> 0.15 | BX23: =BV23*BW23/100 -> 0.15 | BY23: =BW23*$J23 -> 4.5 | BZ23: Finished | CA23: =VLOOKUP(BZ23,DATA!$B$13:$C$19,2,0) -> 100 | CB23: =VLOOKUP($BZ$1,DATA!$B$24:$C$45,2,0) -> 0.16 | CC23: =CA23*CB23/100 -> 0.16 | CD23: =CB23*$J23 -> 4.8 | CE23: Draft | CF23: =VLOOKUP(CE23,DATA!$B$13:$C$19,2,0) -> 25 | CG23: =VLOOKUP($CE$1,DATA!$B$24:$C$45,2,0) -> 0.13 | CH23: =CF23*CG23/100 -> 0.0325 | CI23: =CG23*$J23 -> 3.9 | CJ23: Not started | CK23: =VLOOKUP(CJ23,DATA!$B$13:$C$19,2,0) -> 0 | CL23: =VLOOKUP($CJ$1,DATA!$B$24:$C$45,2,0) -> 0.01 | CM23: =CK23*CL23/100 -> 0 | CN23: =CL23*$J23 -> 0.3 | CO23: =CM23+CH23+CC23+BX23+BS23+BN23+BI23+BD23 -> 0.3725 | CP23: =VLOOKUP($CO$1,DATA!$B$24:$C$45,2,0) -> 0.54 | CQ23: =CP23*CO23 -> 0.20115 | CR23: =CP23*$J23 -> 16.2 | CS23: =CQ23*$J23 -> 6.0345 | CT23: =CR23-CS23 -> 10.1655 | CU23: Not started | CV23: =VLOOKUP(CU23,DATA!$B$13:$C$19,2,0) -> 0 | CW23: =VLOOKUP($CU$1,DATA!$B$24:$C$45,2,0) -> 0.02 | CX23: =CV23*CW23/100 -> 0 | CY23: =CW23*$J23 -> 0.6 | DB23: Not started | DC23: =VLOOKUP(DB23,DATA!$B$13:$C$19,2,0) -> 0 | DD23: =VLOOKUP($DB$1,DATA!$B$24:$C$45,2,0) -> 0.01 | DE23: =DC23*DD23/100 -> 0 | DF23: =DD23*$J23 -> 0.3 | DI23: Not started | DJ23: =VLOOKUP(DI23,DATA!$B$13:$C$19,2,0) -> 0 | DK23: =VLOOKUP($DI$1,DATA!$B$24:$C$45,2,0) -> 0.03 | DL23: =DJ23*DK23/100 -> 0 | DM23: =DK23*$J23 -> 0.9 | DN23: Not started | DO23: =VLOOKUP(DN23,DATA!$B$13:$C$19,2,0) -> 0 | DP23: =VLOOKUP($DN$1,DATA!$B$24:$C$45,2,0) -> 0.07 | DQ23: =DO23*DP23/100 -> 0 | DR23: =DP23*$J23 -> 2.1 | DU23: Not started | DV23: =VLOOKUP(DU23,DATA!$B$13:$C$19,2,0) -> 0 | DW23: =VLOOKUP($DU$1,DATA!$B$24:$C$45,2,0) -> 0.04 | DX23: =DV23*DW23/100 -> 0 | DY23: =DW23*$J23 -> 1.2 | EB23: Not started | EC23: =VLOOKUP(EB23,DATA!$B$13:$C$19,2,0) -> 0 | ED23: =VLOOKUP($EB$1,DATA!$B$24:$C$45,2,0) -> 0.05 | EE23: =EC23*ED23/100 -> 0 | EF23: =ED23*$J23 -> 1.5 | EI23: Not started | EJ23: =VLOOKUP(EI23,DATA!$B$13:$C$19,2,0) -> 0 | EK23: =VLOOKUP($EI$1,DATA!$B$24:$C$45,2,0) -> 0.1 | EL23: =EJ23*EK23/100 -> 0 | EM23: =EK23*$J23 -> 3 | EP23: Not started | EQ23: =VLOOKUP(EP23,DATA!$B$13:$C$19,2,0) -> 0 | ER23: =VLOOKUP($EP$1,DATA!$B$24:$C$45,2,0) -> 0.03 | ES23: =EQ23*ER23/100 -> 0 | ET23: =ER23*$J23 -> 0.9 | EU23: =SUM( IF(AH23<>"Finished",AL23,0) + N("READ INFO"), IF(AM23<>"Finished",AQ23,0) + N("LONG LEAD"), IF(AT23<>"Finished",AX23,0) + N("SWITCH LAYOUT"), IF(CJ23<>"Finished",CT23,0) + N("DESIGN"), IF(CU23<>"Finished",CY23,0) + N("REVISION"), IF(DB23<>"Finished",DF23,0) + N("CUST APRVL"), IF(DI23<>"Finished",DM23,0) + N("MEETINGS"), IF(DN23<>"Finished",DR23,0) + N("PURCHASING"), IF(DU23<>"Finished",DY23,0) + N("HANDOFF"), IF(EB23<>"Finished",EF23,0) + N("SUPPORT"), IF(EI23<>"Finished",EM23,0) + N("DOCUMENTATTION"), IF(EP23<>"Finished",ET23,0) + N("REDLINES"), ) -> 22.4655 | EV23: ADRIAN CABELLO | EW23: JUAN ADAME
A24: MI | B24: Open | C24: OP Mobility | D24: 3300 CO Phase 3 | E24: Banner Strip Lights | F24: 3300-CO06 | G24: 3300-CO06-C | H24: 10 | J24: =BaseDeDatos[[#This Row],[Budget CS]]+BaseDeDatos[[#This Row],[Change Orders Budget]] -> 10 | K24: =IFERROR(VLOOKUP(G24, DATA!H:I, 2, FALSE), 0)+BaseDeDatos[[#This Row],[Labor Spend on Design errors]]+BaseDeDatos[[#This Row],[Labor Spent Customer changes]] -> 3 | N24: =AK24+AP24+AW24+CQ24+CX24+DE24+DL24+DQ24+DX24+EE24+EL24+ES24 -> 0.349 | O24: =J24*S24 -> 3 | P24: 26.73 | Q24: =BaseDeDatos[[#This Row],[Budget]]*BaseDeDatos[[#This Row],[Labor Rate from CS]] -> 267.3 | R24: =BaseDeDatos[[#This Row],[Labor Spent]]*BaseDeDatos[[#This Row],[Labor Rate from CS]] -> 80.19 | S24: =K24/J24 -> 0.3 | T24: 8835 | W24: 472 | X24: 472 | AA24: 6933.58 | AB24: =AA24-X24-Q24 -> 6194.28 | AC24: =SUM(AB24,X24,R24,BaseDeDatos[[#This Row],[Additionals cost]]) -> 6746.47 | AD24: 0.2152 | AE24: -0.0031 | AF24: =(T24-SUM(X24,AB24,R24))/T24 -> 0.23639276 | AH24: Finished | AI24: =VLOOKUP(AH24,DATA!$B$13:$C$19,2,0) -> 100 | AK24: =BaseDeDatos[[#This Row],[Read info Status]]*(AJ24)/100 -> 0 | AL24: =AJ24*$J24 -> 0 | AM24: In process | AN24: =VLOOKUP(AM24,DATA!$B$13:$C$19,2,0) -> 50 | AO24: =VLOOKUP($AM$1,DATA!$B$24:$C$45,2,0) -> 0.05 | AP24: =AN24*AO24/100 -> 0.025 | AQ24: =AO24*$J24 -> 0.5 | AT24: Not started | AU24: =VLOOKUP(AT24,DATA!$B$13:$C$19,2,0) -> 0 | AV24: =VLOOKUP($AT$1,DATA!$B$24:$C$45,2,0) -> 0.01 | AW24: =AU24*AV24/100 -> 0 | AX24: =AV24*$J24 -> 0.1 | BA24: Finished | BB24: =VLOOKUP(BA24,DATA!$B$13:$C$19,2,0) -> 100 | BC24: =VLOOKUP($BA$1,DATA!$B$24:$C$45,2,0) -> 0.01 | BD24: =BB24*BC24/100 -> 0.01 | BE24: =BC24*$J24 -> 0.1 | BF24: Finished | BG24: =VLOOKUP(BF24,DATA!$B$13:$C$19,2,0) -> 100 | BH24: =VLOOKUP($BF$1,DATA!$B$24:$C$45,2,0) -> 0.08 | BI24: =BG24*BH24/100 -> 0.08 | BJ24: =BH24*$J24 -> 0.8 | BK24: Not started | BL24: =VLOOKUP(BK24,DATA!$B$13:$C$19,2,0) -> 0 | BM24: =VLOOKUP($BK$1,DATA!$B$24:$C$45,2,0) -> 0.18 | BN24: =BL24*BM24/100 -> 0 | BO24: =BM24*$J24 -> 1.8 | BP24: Draft | BQ24: =VLOOKUP(BP24,DATA!$B$13:$C$19,2,0) -> 25 | BR24: =VLOOKUP($BP$1,DATA!$B$24:$C$45,2,0) -> 0.28 | BS24: =BQ24*BR24/100 -> 0.07 | BT24: =BR24*$J24 -> 2.8 | BU24: Finished | BV24: =VLOOKUP(BU24,DATA!$B$13:$C$19,2,0) -> 100 | BW24: =VLOOKUP($BU$1,DATA!$B$24:$C$45,2,0) -> 0.15 | BX24: =BV24*BW24/100 -> 0.15 | BY24: =BW24*$J24 -> 1.5 | BZ24: Finished | CA24: =VLOOKUP(BZ24,DATA!$B$13:$C$19,2,0) -> 100 | CB24: =VLOOKUP($BZ$1,DATA!$B$24:$C$45,2,0) -> 0.16 | CC24: =CA24*CB24/100 -> 0.16 | CD24: =CB24*$J24 -> 1.6 | CE24: Finished | CF24: =VLOOKUP(CE24,DATA!$B$13:$C$19,2,0) -> 100 | CG24: =VLOOKUP($CE$1,DATA!$B$24:$C$45,2,0) -> 0.13 | CH24: =CF24*CG24/100 -> 0.13 | CI24: =CG24*$J24 -> 1.3 | CJ24: Not started | CK24: =VLOOKUP(CJ24,DATA!$B$13:$C$19,2,0) -> 0 | CL24: =VLOOKUP($CJ$1,DATA!$B$24:$C$45,2,0) -> 0.01 | CM24: =CK24*CL24/100 -> 0 | CN24: =CL24*$J24 -> 0.1 | CO24: =CM24+CH24+CC24+BX24+BS24+BN24+BI24+BD24 -> 0.6 | CP24: =VLOOKUP($CO$1,DATA!$B$24:$C$45,2,0) -> 0.54 | CQ24: =CP24*CO24 -> 0.324 | CR24: =CP24*$J24 -> 5.4 | CS24: =CQ24*$J24 -> 3.24 | CT24: =CR24-CS24 -> 2.16 | CU24: Not started | CV24: =VLOOKUP(CU24,DATA!$B$13:$C$19,2,0) -> 0 | CW24: =VLOOKUP($CU$1,DATA!$B$24:$C$45,2,0) -> 0.02 | CX24: =CV24*CW24/100 -> 0 | CY24: =CW24*$J24 -> 0.2 | DB24: Not started | DC24: =VLOOKUP(DB24,DATA!$B$13:$C$19,2,0) -> 0 | DD24: =VLOOKUP($DB$1,DATA!$B$24:$C$45,2,0) -> 0.01 | DE24: =DC24*DD24/100 -> 0 | DF24: =DD24*$J24 -> 0.1 | DI24: Not started | DJ24: =VLOOKUP(DI24,DATA!$B$13:$C$19,2,0) -> 0 | DK24: =VLOOKUP($DI$1,DATA!$B$24:$C$45,2,0) -> 0.03 | DL24: =DJ24*DK24/100 -> 0 | DM24: =DK24*$J24 -> 0.3 | DN24: Not started | DO24: =VLOOKUP(DN24,DATA!$B$13:$C$19,2,0) -> 0 | DP24: =VLOOKUP($DN$1,DATA!$B$24:$C$45,2,0) -> 0.07 | DQ24: =DO24*DP24/100 -> 0 | DR24: =DP24*$J24 -> 0.7 | DU24: Not started | DV24: =VLOOKUP(DU24,DATA!$B$13:$C$19,2,0) -> 0 | DW24: =VLOOKUP($DU$1,DATA!$B$24:$C$45,2,0) -> 0.04 | DX24: =DV24*DW24/100 -> 0 | DY24: =DW24*$J24 -> 0.4 | EB24: Not started | EC24: =VLOOKUP(EB24,DATA!$B$13:$C$19,2,0) -> 0 | ED24: =VLOOKUP($EB$1,DATA!$B$24:$C$45,2,0) -> 0.05 | EE24: =EC24*ED24/100 -> 0 | EF24: =ED24*$J24 -> 0.5 | EI24: Not started | EJ24: =VLOOKUP(EI24,DATA!$B$13:$C$19,2,0) -> 0 | EK24: =VLOOKUP($EI$1,DATA!$B$24:$C$45,2,0) -> 0.1 | EL24: =EJ24*EK24/100 -> 0 | EM24: =EK24*$J24 -> 1 | EP24: Not started | EQ24: =VLOOKUP(EP24,DATA!$B$13:$C$19,2,0) -> 0 | ER24: =VLOOKUP($EP$1,DATA!$B$24:$C$45,2,0) -> 0.03 | ES24: =EQ24*ER24/100 -> 0 | ET24: =ER24*$J24 -> 0.3 | EU24: =SUM( IF(AH24<>"Finished",AL24,0) + N("READ INFO"), IF(AM24<>"Finished",AQ24,0) + N("LONG LEAD"), IF(AT24<>"Finished",AX24,0) + N("SWITCH LAYOUT"), IF(CJ24<>"Finished",CT24,0) + N("DESIGN"), IF(CU24<>"Finished",CY24,0) + N("REVISION"), IF(DB24<>"Finished",DF24,0) + N("CUST APRVL"), IF(DI24<>"Finished",DM24,0) + N("MEETINGS"), IF(DN24<>"Finished",DR24,0) + N("PURCHASING"), IF(DU24<>"Finished",DY24,0) + N("HANDOFF"), IF(EB24<>"Finished",EF24,0) + N("SUPPORT"), IF(EI24<>"Finished",EM24,0) + N("DOCUMENTATTION"), IF(EP24<>"Finished",ET24,0) + N("REDLINES"), ) -> 6.26 | EV24: ADRIAN CABELLO | EW24: JUAN ADAME
A25: MX | B25: Close | C25: VALEO | D25: 1 set of LH-RH Fixtures for St.10 | E25: Valeo Ford 833 HL | F25: 3328 | G25: 3328-A | H25: 30 | J25: =BaseDeDatos[[#This Row],[Budget CS]]+BaseDeDatos[[#This Row],[Change Orders Budget]] -> 30 | K25: =IFERROR(VLOOKUP(G25, DATA!H:I, 2, FALSE), 0)+BaseDeDatos[[#This Row],[Labor Spend on Design errors]]+BaseDeDatos[[#This Row],[Labor Spent Customer changes]] -> 20.5 | N25: =AK25+AP25+AW25+CQ25+CX25+DE25+DL25+DQ25+DX25+EE25+EL25+ES25 -> 0.945 | O25: =J25*S25 -> 20.5 | P25: 26.73 | Q25: =BaseDeDatos[[#This Row],[Budget]]*BaseDeDatos[[#This Row],[Labor Rate from CS]] -> 801.9 | R25: =BaseDeDatos[[#This Row],[Labor Spent]]*BaseDeDatos[[#This Row],[Labor Rate from CS]] -> 547.965 | S25: =K25/J25 -> 0.68333333 | T25: 45410 | U25: 10493.57 | V25: 8236.48 | W25: 6866 | X25: 6866 | AA25: 35641.82 | AB25: =AA25-X25-Q25 -> 27973.92 | AC25: =SUM(AB25,X25,R25,BaseDeDatos[[#This Row],[Additionals cost]]) -> 43624.365 | AD25: 0.2151 | AE25: 0.235 | AF25: =(T25-SUM(X25,AB25,R25))/T25 -> 0.22070282 | AG25: 45824 | AH25: Finished | AI25: =VLOOKUP(AH25,DATA!$B$13:$C$19,2,0) -> 100 | AJ25: =VLOOKUP($AH$1,DATA!$B$24:$C$45,2,0) -> 0.05 | AK25: =BaseDeDatos[[#This Row],[Read info Status]]*(AJ25)/100 -> 0.05 | AL25: =AJ25*$J25 -> 1.5 | AM25: Finished | AN25: =VLOOKUP(AM25,DATA!$B$13:$C$19,2,0) -> 100 | AO25: =VLOOKUP($AM$1,DATA!$B$24:$C$45,2,0) -> 0.05 | AP25: =AN25*AO25/100 -> 0.05 | AQ25: =AO25*$J25 -> 1.5 | AR25: 45838 | AS25: 45840 | AT25: Finished | AU25: =VLOOKUP(AT25,DATA!$B$13:$C$19,2,0) -> 100 | AV25: =VLOOKUP($AT$1,DATA!$B$24:$C$45,2,0) -> 0.01 | AW25: =AU25*AV25/100 -> 0.01 | AX25: =AV25*$J25 -> 0.3 | AY25: 45905 | AZ25: 45930 | BA25: Finished | BB25: =VLOOKUP(BA25,DATA!$B$13:$C$19,2,0) -> 100 | BC25: =VLOOKUP($BA$1,DATA!$B$24:$C$45,2,0) -> 0.01 | BD25: =BB25*BC25/100 -> 0.01 | BE25: =BC25*$J25 -> 0.3 | BF25: Finished | BG25: =VLOOKUP(BF25,DATA!$B$13:$C$19,2,0) -> 100 | BH25: =VLOOKUP($BF$1,DATA!$B$24:$C$45,2,0) -> 0.08 | BI25: =BG25*BH25/100 -> 0.08 | BJ25: =BH25*$J25 -> 2.4 | BK25: Finished | BL25: =VLOOKUP(BK25,DATA!$B$13:$C$19,2,0) -> 100 | BM25: =VLOOKUP($BK$1,DATA!$B$24:$C$45,2,0) -> 0.18 | BN25: =BL25*BM25/100 -> 0.18 | BO25: =BM25*$J25 -> 5.4 | BP25: Finished | BQ25: =VLOOKUP(BP25,DATA!$B$13:$C$19,2,0) -> 100 | BR25: =VLOOKUP($BP$1,DATA!$B$24:$C$45,2,0) -> 0.28 | BS25: =BQ25*BR25/100 -> 0.28 | BT25: =BR25*$J25 -> 8.4 | BU25: Finished | BV25: =VLOOKUP(BU25,DATA!$B$13:$C$19,2,0) -> 100 | BW25: =VLOOKUP($BU$1,DATA!$B$24:$C$45,2,0) -> 0.15 | BX25: =BV25*BW25/100 -> 0.15 | BY25: =BW25*$J25 -> 4.5 | BZ25: Finished | CA25: =VLOOKUP(BZ25,DATA!$B$13:$C$19,2,0) -> 100 | CB25: =VLOOKUP($BZ$1,DATA!$B$24:$C$45,2,0) -> 0.16 | CC25: =CA25*CB25/100 -> 0.16 | CD25: =CB25*$J25 -> 4.8 | CE25: Finished | CF25: =VLOOKUP(CE25,DATA!$B$13:$C$19,2,0) -> 100 | CG25: =VLOOKUP($CE$1,DATA!$B$24:$C$45,2,0) -> 0.13 | CH25: =CF25*CG25/100 -> 0.13 | CI25: =CG25*$J25 -> 3.9 | CJ25: Finished | CK25: =VLOOKUP(CJ25,DATA!$B$13:$C$19,2,0) -> 100 | CL25: =VLOOKUP($CJ$1,DATA!$B$24:$C$45,2,0) -> 0.01 | CM25: =CK25*CL25/100 -> 0.01 | CN25: =CL25*$J25 -> 0.3 | CO25: =CM25+CH25+CC25+BX25+BS25+BN25+BI25+BD25 -> 1 | CP25: =VLOOKUP($CO$1,DATA!$B$24:$C$45,2,0) -> 0.54 | CQ25: =CP25*CO25 -> 0.54 | CR25: =CP25*$J25 -> 16.2 | CS25: =CQ25*$J25 -> 16.2 | CT25: =CR25-CS25 -> 0 | CU25: Finished | CV25: =VLOOKUP(CU25,DATA!$B$13:$C$19,2,0) -> 100 | CW25: =VLOOKUP($CU$1,DATA!$B$24:$C$45,2,0) -> 0.02 | CX25: =CV25*CW25/100 -> 0.02 | CY25: =CW25*$J25 -> 0.6 | CZ25: 45916 | DA25: 45931 | DB25: Finished | DC25: =VLOOKUP(DB25,DATA!$B$13:$C$19,2,0) -> 100 | DD25: =VLOOKUP($DB$1,DATA!$B$24:$C$45,2,0) -> 0.01 | DE25: =DC25*DD25/100 -> 0.01 | DF25: =DD25*$J25 -> 0.3 | DG25: 45919 | DH25: 45936 | DI25: Finished | DJ25: =VLOOKUP(DI25,DATA!$B$13:$C$19,2,0) -> 100 | DK25: =VLOOKUP($DI$1,DATA!$B$24:$C$45,2,0) -> 0.03 | DL25: =DJ25*DK25/100 -> 0.03 | DM25: =DK25*$J25 -> 0.9 | DN25: Finished | DO25: =VLOOKUP(DN25,DATA!$B$13:$C$19,2,0) -> 100 | DP25: =VLOOKUP($DN$1,DATA!$B$24:$C$45,2,0) -> 0.07 | DQ25: =DO25*DP25/100 -> 0.07 | DR25: =DP25*$J25 -> 2.1 | DS25: 45919 | DT25: 45939 | DU25: Finished | DV25: =VLOOKUP(DU25,DATA!$B$13:$C$19,2,0) -> 100 | DW25: =VLOOKUP($DU$1,DATA!$B$24:$C$45,2,0) -> 0.04 | DX25: =DV25*DW25/100 -> 0.04 | DY25: =DW25*$J25 -> 1.2 | DZ25: 45923 | EA25: 45953 | EB25: In process | EC25: =VLOOKUP(EB25,DATA!$B$13:$C$19,2,0) -> 50 | ED25: =VLOOKUP($EB$1,DATA!$B$24:$C$45,2,0) -> 0.05 | EE25: =EC25*ED25/100 -> 0.025 | EF25: =ED25*$J25 -> 1.5 | EI25: Finished | EJ25: =VLOOKUP(EI25,DATA!$B$13:$C$19,2,0) -> 100 | EK25: =VLOOKUP($EI$1,DATA!$B$24:$C$45,2,0) -> 0.1 | EL25: =EJ25*EK25/100 -> 0.1 | EM25: =EK25*$J25 -> 3 | EO25: 45986 | EP25: Not started | EQ25: =VLOOKUP(EP25,DATA!$B$13:$C$19,2,0) -> 0 | ER25: =VLOOKUP($EP$1,DATA!$B$24:$C$45,2,0) -> 0.03 | ES25: =EQ25*ER25/100 -> 0 | ET25: =ER25*$J25 -> 0.9 | EU25: =SUM( IF(AH25<>"Finished",AL25,0) + N("READ INFO"), IF(AM25<>"Finished",AQ25,0) + N("LONG LEAD"), IF(AT25<>"Finished",AX25,0) + N("SWITCH LAYOUT"), IF(CJ25<>"Finished",CT25,0) + N("DESIGN"), IF(CU25<>"Finished",CY25,0) + N("REVISION"), IF(DB25<>"Finished",DF25,0) + N("CUST APRVL"), IF(DI25<>"Finished",DM25,0) + N("MEETINGS"), IF(DN25<>"Finished",DR25,0) + N("PURCHASING"), IF(DU25<>"Finished",DY25,0) + N("HANDOFF"), IF(EB25<>"Finished",EF25,0) + N("SUPPORT"), IF(EI25<>"Finished",EM25,0) + N("DOCUMENTATTION"), IF(EP25<>"Finished",ET25,0) + N("REDLINES"), ) -> 2.4 | EV25: JUAN ADAME | EW25: HILDA MATA
A26: MX | B26: Close | C26: VALEO | D26: 1 set of LH-RH Fixtures for St.20 | E26: Valeo Ford 833 HL | F26: 3328 | G26: 3328-B | H26: 20 | J26: =BaseDeDatos[[#This Row],[Budget CS]]+BaseDeDatos[[#This Row],[Change Orders Budget]] -> 20 | K26: =IFERROR(VLOOKUP(G26, DATA!H:I, 2, FALSE), 0)+BaseDeDatos[[#This Row],[Labor Spend on Design errors]]+BaseDeDatos[[#This Row],[Labor Spent Customer changes]] -> 14.5 | N26: =AK26+AP26+AW26+CQ26+CX26+DE26+DL26+DQ26+DX26+EE26+EL26+ES26 -> 0.945 | O26: =J26*S26 -> 14.5 | P26: 26.73 | Q26: =BaseDeDatos[[#This Row],[Budget]]*BaseDeDatos[[#This Row],[Labor Rate from CS]] -> 534.6 | R26: =BaseDeDatos[[#This Row],[Labor Spent]]*BaseDeDatos[[#This Row],[Labor Rate from CS]] -> 387.585 | S26: =K26/J26 -> 0.725 | T26: 30695 | U26: 10493.57 | V26: 8236.48 | W26: 2144 | X26: 2144 | AA26: 24091.07 | AB26: =AA26-X26-Q26 -> 21412.47 | AC26: =SUM(AB26,X26,R26,BaseDeDatos[[#This Row],[Additionals cost]]) -> 32180.535 | AD26: 0.2151 | AE26: 0.235 | AF26: =(T26-SUM(X26,AB26,R26))/T26 -> 0.21993631 | AG26: 45824 | AH26: Finished | AI26: =VLOOKUP(AH26,DATA!$B$13:$C$19,2,0) -> 100 | AJ26: =VLOOKUP($AH$1,DATA!$B$24:$C$45,2,0) -> 0.05 | AK26: =BaseDeDatos[[#This Row],[Read info Status]]*(AJ26)/100 -> 0.05 | AL26: =AJ26*$J26 -> 1 | AM26: Finished | AN26: =VLOOKUP(AM26,DATA!$B$13:$C$19,2,0) -> 100 | AO26: =VLOOKUP($AM$1,DATA!$B$24:$C$45,2,0) -> 0.05 | AP26: =AN26*AO26/100 -> 0.05 | AQ26: =AO26*$J26 -> 1 | AR26: 45838 | AS26: 45840 | AT26: Finished | AU26: =VLOOKUP(AT26,DATA!$B$13:$C$19,2,0) -> 100 | AV26: =VLOOKUP($AT$1,DATA!$B$24:$C$45,2,0) -> 0.01 | AW26: =AU26*AV26/100 -> 0.01 | AX26: =AV26*$J26 -> 0.2 | AY26: 45905 | AZ26: 45930 | BA26: Finished | BB26: =VLOOKUP(BA26,DATA!$B$13:$C$19,2,0) -> 100 | BC26: =VLOOKUP($BA$1,DATA!$B$24:$C$45,2,0) -> 0.01 | BD26: =BB26*BC26/100 -> 0.01 | BE26: =BC26*$J26 -> 0.2 | BF26: Finished | BG26: =VLOOKUP(BF26,DATA!$B$13:$C$19,2,0) -> 100 | BH26: =VLOOKUP($BF$1,DATA!$B$24:$C$45,2,0) -> 0.08 | BI26: =BG26*BH26/100 -> 0.08 | BJ26: =BH26*$J26 -> 1.6 | BK26: Finished | BL26: =VLOOKUP(BK26,DATA!$B$13:$C$19,2,0) -> 100 | BM26: =VLOOKUP($BK$1,DATA!$B$24:$C$45,2,0) -> 0.18 | BN26: =BL26*BM26/100 -> 0.18 | BO26: =BM26*$J26 -> 3.6 | BP26: Finished | BQ26: =VLOOKUP(BP26,DATA!$B$13:$C$19,2,0) -> 100 | BR26: =VLOOKUP($BP$1,DATA!$B$24:$C$45,2,0) -> 0.28 | BS26: =BQ26*BR26/100 -> 0.28 | BT26: =BR26*$J26 -> 5.6 | BU26: Finished | BV26: =VLOOKUP(BU26,DATA!$B$13:$C$19,2,0) -> 100 | BW26: =VLOOKUP($BU$1,DATA!$B$24:$C$45,2,0) -> 0.15 | BX26: =BV26*BW26/100 -> 0.15 | BY26: =BW26*$J26 -> 3 | BZ26: Finished | CA26: =VLOOKUP(BZ26,DATA!$B$13:$C$19,2,0) -> 100 | CB26: =VLOOKUP($BZ$1,DATA!$B$24:$C$45,2,0) -> 0.16 | CC26: =CA26*CB26/100 -> 0.16 | CD26: =CB26*$J26 -> 3.2 | CE26: Finished | CF26: =VLOOKUP(CE26,DATA!$B$13:$C$19,2,0) -> 100 | CG26: =VLOOKUP($CE$1,DATA!$B$24:$C$45,2,0) -> 0.13 | CH26: =CF26*CG26/100 -> 0.13 | CI26: =CG26*$J26 -> 2.6 | CJ26: Finished | CK26: =VLOOKUP(CJ26,DATA!$B$13:$C$19,2,0) -> 100 | CL26: =VLOOKUP($CJ$1,DATA!$B$24:$C$45,2,0) -> 0.01 | CM26: =CK26*CL26/100 -> 0.01 | CN26: =CL26*$J26 -> 0.2 | CO26: =CM26+CH26+CC26+BX26+BS26+BN26+BI26+BD26 -> 1 | CP26: =VLOOKUP($CO$1,DATA!$B$24:$C$45,2,0) -> 0.54 | CQ26: =CP26*CO26 -> 0.54 | CR26: =CP26*$J26 -> 10.8 | CS26: =CQ26*$J26 -> 10.8 | CT26: =CR26-CS26 -> 0 | CU26: Finished | CV26: =VLOOKUP(CU26,DATA!$B$13:$C$19,2,0) -> 100 | CW26: =VLOOKUP($CU$1,DATA!$B$24:$C$45,2,0) -> 0.02 | CX26: =CV26*CW26/100 -> 0.02 | CY26: =CW26*$J26 -> 0.4 | CZ26: 45916 | DA26: 45931 | DB26: Finished | DC26: =VLOOKUP(DB26,DATA!$B$13:$C$19,2,0) -> 100 | DD26: =VLOOKUP($DB$1,DATA!$B$24:$C$45,2,0) -> 0.01 | DE26: =DC26*DD26/100 -> 0.01 | DF26: =DD26*$J26 -> 0.2 | DG26: 45919 | DH26: 45936 | DI26: Finished | DJ26: =VLOOKUP(DI26,DATA!$B$13:$C$19,2,0) -> 100 | DK26: =VLOOKUP($DI$1,DATA!$B$24:$C$45,2,0) -> 0.03 | DL26: =DJ26*DK26/100 -> 0.03 | DM26: =DK26*$J26 -> 0.6 | DN26: Finished | DO26: =VLOOKUP(DN26,DATA!$B$13:$C$19,2,0) -> 100 | DP26: =VLOOKUP($DN$1,DATA!$B$24:$C$45,2,0) -> 0.07 | DQ26: =DO26*DP26/100 -> 0.07 | DR26: =DP26*$J26 -> 1.4 | DS26: 45919 | DT26: 45939 | DU26: Finished | DV26: =VLOOKUP(DU26,DATA!$B$13:$C$19,2,0) -> 100 | DW26: =VLOOKUP($DU$1,DATA!$B$24:$C$45,2,0) -> 0.04 | DX26: =DV26*DW26/100 -> 0.04 | DY26: =DW26*$J26 -> 0.8 | DZ26: 45923 | EA26: 45953 | EB26: In process | EC26: =VLOOKUP(EB26,DATA!$B$13:$C$19,2,0) -> 50 | ED26: =VLOOKUP($EB$1,DATA!$B$24:$C$45,2,0) -> 0.05 | EE26: =EC26*ED26/100 -> 0.025 | EF26: =ED26*$J26 -> 1 | EI26: Finished | EJ26: =VLOOKUP(EI26,DATA!$B$13:$C$19,2,0) -> 100 | EK26: =VLOOKUP($EI$1,DATA!$B$24:$C$45,2,0) -> 0.1 | EL26: =EJ26*EK26/100 -> 0.1 | EM26: =EK26*$J26 -> 2 | EO26: 45986 | EP26: Not started | EQ26: =VLOOKUP(EP26,DATA!$B$13:$C$19,2,0) -> 0 | ER26: =VLOOKUP($EP$1,DATA!$B$24:$C$45,2,0) -> 0.03 | ES26: =EQ26*ER26/100 -> 0 | ET26: =ER26*$J26 -> 0.6 | EU26: =SUM( IF(AH26<>"Finished",AL26,0) + N("READ INFO"), IF(AM26<>"Finished",AQ26,0) + N("LONG LEAD"), IF(AT26<>"Finished",AX26,0) + N("SWITCH LAYOUT"), IF(CJ26<>"Finished",CT26,0) + N("DESIGN"), IF(CU26<>"Finished",CY26,0) + N("REVISION"), IF(DB26<>"Finished",DF26,0) + N("CUST APRVL"), IF(DI26<>"Finished",DM26,0) + N("MEETINGS"), IF(DN26<>"Finished",DR26,0) + N("PURCHASING"), IF(DU26<>"Finished",DY26,0) + N("HANDOFF"), IF(EB26<>"Finished",EF26,0) + N("SUPPORT"), IF(EI26<>"Finished",EM26,0) + N("DOCUMENTATTION"), IF(EP26<>"Finished",ET26,0) + N("REDLINES"), ) -> 1.6 | EV26: JUAN ADAME | EW26: HILDA MATA
